Workbook

Sheet Guida
A1: Guida — Motore Prezzi Asta Fantacalcio
A2: Questo file calcola automaticamente un prezzo massimo consigliato e un range di valutazione per ciascun giocatore, in base al budget, alla rosa, alle regole della lega e ai dati FVM/statistici. Il motore si aggiorna modificando i parametri e gli assegnamenti dell'asta.
A3: Come e' organizzato il file
A5: • Info Lega: dati della tua lega (budget, rosa, regole, nomi squadre). 'La Mia Squadra' (B28) identifica la tua squadra.
A6: • Info Strategia: modulo preferito, aggressivita' e lista 'Giocatori Preferiti' (colonna D).
A7: • Parametri Modello: tutte le leve del motore prezzi, incluse soglia minima di presenze storiche e gestione della scarsita'.
A8: • Input Giocatori 2026_27: il listone originale, invariato — e' la fonte dati.
A9: • Output Utente: tabella madre con un giocatore per riga, prezzo consigliato, range, statistiche e stato dell'asta.
A10: • Giocatori Liberi: elenco ordinato dei giocatori non ancora assegnati; il calcolo della scarsita' puo' escludere i giocatori con Qt.A=1.
A11: • La Mia Rosa: la tua rosa attuale + budget speso/rimanente + slot per ruolo, live durante l'asta.
A12: Come si calcola il prezzo (Output Utente)
A14: 1. Prezzo Base FVM = (FVM del giocatore / Somma FVM Pool Totale) × Budget Totale Lega. Il pool comprende, per ciascun ruolo, i migliori N giocatori per FVM, dove N e' il numero totale di slot di quel ruolo nella lega. Il denominatore e' la somma dei pool di tutti i ruoli.
... A58: Generato: 2026-08-12

Sheet Dashboard Asta
A1: DASHBOARD ASTA — vista live
A3: Giocatori chiamati / Totale | D3: % Asta completata | G3: Prezzo medio pagato | I3: Budget medio residuo squadre attive
A4: ='Stato Asta'!$C$3 -> 0 / 491 | D4: ='Stato Asta'!$C$4 -> 0 | G4: ='Stato Asta'!$C$6 | I4: ='Stato Asta'!$C$5 -> 1000
A6: Ruolo | B6: TOP | C6: BUONI | D6: MEDIA | E6: SCOMMESSE | F6: Totale Disp. | G6: Slot Residui Lega | H6: Quality Coverage | I6: Pressione Asta (scarsita') | J6: Pressione Competitiva
A7: P | B7: ='Stato Asta'!$B$9 -> 7 | C7: ='Stato Asta'!$C$9 -> 11 | D7: ='Stato Asta'!$I$9 -> 6 | E7: ='Stato Asta'!$J$9 -> 0 | F7: ='Stato Asta'!$K$9 -> 24 | G7: ='Stato Asta'!$E$9 -> 24 | H7: ='Stato Asta'!$L$9 -> 0.75 | I7: ='Stato Asta'!$G$9 -> 🔴 Non aspettare | J7: ='Pressione Competitiva'!$F$3 -> 🔴 Molto Alta
A8: D | B8: ='Stato Asta'!$B$10 -> 18 | C8: ='Stato Asta'!$C$10 -> 37 | D8: ='Stato Asta'!$I$10 -> 56 | E8: ='Stato Asta'!$J$10 -> 37 | F8: ='Stato Asta'!$K$10 -> 148 | G8: ='Stato Asta'!$E$10 -> 64 | H8: ='Stato Asta'!$L$10 -> 0.37162162 | I8: ='Stato Asta'!$G$10 -> 🔴 Non aspettare | J8: ='Pressione Competitiva'!$F$4 -> 🔴 Molto Alta
A9: C | B9: ='Stato Asta'!$B$11 -> 18 | C9: ='Stato Asta'!$C$11 -> 37 | D9: ='Stato Asta'!$I$11 -> 49 | E9: ='Stato Asta'!$J$11 -> 51 | F9: ='Stato Asta'!$K$11 -> 155 | G9: ='Stato Asta'!$E$11 -> 64 | H9: ='Stato Asta'!$L$11 -> 0.35483871 | I9: ='Stato Asta'!$G$11 -> 🔴 Non aspettare | J9: ='Pressione Competitiva'!$F$5 -> 🔴 Molto Alta
A10: A | B10: ='Stato Asta'!$B$12 -> 9 | C10: ='Stato Asta'!$C$12 -> 17 | D10: ='Stato Asta'!$I$12 -> 28 | E10: ='Stato Asta'!$J$12 -> 23 | F10: ='Stato Asta'!$K$12 -> 77 | G10: ='Stato Asta'!$E$12 -> 48 | H10: ='Stato Asta'!$L$12 -> 0.33766234 | I10: ='Stato Asta'!$G$12 -> 🔴 Non aspettare | J10: ='Pressione Competitiva'!$F$6 -> 🔴 Molto Alta
A12: LA MIA ROSA — sintesi
A13: Budget Residuo | C13: Slot Residui | E13: FVM Totale Acquistato | G13: Crediti Spesi | I13: Efficienza (FVM/credito)
A14: ='La Mia Rosa'!$S$2 -> 1000 | C14: ='La Mia Rosa'!$S$3 -> 25 | E14: ='La Mia Rosa'!$R$6 -> 0 | G14: ='La Mia Rosa'!$R$7 -> 0 | I14: ='La Mia Rosa'!$R$8
A16: Copertura Titolari (prossimo bisogno)
A17: Ruolo | B17: Titolari Coperti | C17: Titolari Necessari | D17: Riserve Coperte | E17: Prossimo Slot
A18: P | B18: ='La Mia Rosa'!$R$13 -> 0 | C18: ='La Mia Rosa'!$S$13 -> 1 | D18: ='La Mia Rosa'!$T$13 -> 0 | E18: ='La Mia Rosa'!$U$13 -> Titolare
A19: D | B19: ='La Mia Rosa'!$R$14 -> 0 | C19: ='La Mia Rosa'!$S$14 -> 3 | D19: ='La Mia Rosa'!$T$14 -> 0 | E19: ='La Mia Rosa'!$U$14 -> Titolare
A20: C | B20: ='La Mia Rosa'!$R$15 -> 0 | C20: ='La Mia Rosa'!$S$15 -> 4 | D20: ='La Mia Rosa'!$T$15 -> 0 | E20: ='La Mia Rosa'!$U$15 -> Titolare
A21: A | B21: ='La Mia Rosa'!$R$16 -> 0 | C21: ='La Mia Rosa'!$S$16 -> 3 | D21: ='La Mia Rosa'!$T$16 -> 0 | E21: ='La Mia Rosa'!$U$16 -> Titolare

Sheet Decisione Live
A1: DECISIONE LIVE — scheda giocatore in asta
A3: Nome Giocatore (scrivi il nome esatto)
A4: Prezzo Attuale in Asta (crediti)
A6: Ruolo | B6: =IFERROR(INDEX('Output Utente'!$B$2:$B$492,MATCH($B$3,'Output Utente'!$C$2:$C$492,0)),"")
A7: FVM / 1000 | B7: =IFERROR(INDEX('Output Utente'!$O$2:$O$492,MATCH($B$3,'Output Utente'!$C$2:$C$492,0)),"")
A8: Fascia (mercato) | B8: =IFERROR(INDEX('Output Utente'!$P$2:$P$492,MATCH($B$3,'Output Utente'!$C$2:$C$492,0)),"")
A9: Titolare/Riserva (mercato) | B9: =IFERROR(INDEX('Output Utente'!$AF$2:$AF$492,MATCH($B$3,'Output Utente'!$C$2:$C$492,0)),"")
A10: E' un tuo Preferito (Whichlist) | B10: =IFERROR(INDEX('Output Utente'!$E$2:$E$492,MATCH($B$3,'Output Utente'!$C$2:$C$492,0)),"")
A12: VALORE / RANGE / MAX BID
A13: Valutazione Min (Range Min) | B13: =IFERROR(INDEX('Output Utente'!$G$2:$G$492,MATCH($B$3,'Output Utente'!$C$2:$C$492,0)),"") | C13: Prezzo ragionevole minimo secondo il motore.
A14: Valutazione Max (Range Max) | B14: =IFERROR(INDEX('Output Utente'!$H$2:$H$492,MATCH($B$3,'Output Utente'!$C$2:$C$492,0)),"") | C14: Prezzo ragionevole massimo secondo il motore.
A15: Offerta Max Strategica | B15: =IFERROR(INDEX('Output Utente'!$F$2:$F$492,MATCH($B$3,'Output Utente'!$C$2:$C$492,0)),"") | C15: Range + Aggressivita' + eventuale boost Preferito. Non ancora limitata dal budget.
A16: Budget Residuo (tuo) | B16: =IFERROR(INDEX('Output Utente'!$W$2:$W$492,MATCH($B$3,'Output Utente'!$C$2:$C$492,0)),"")
A17: Slot Residui (tuoi, tutti i ruoli) | B17: =IFERROR(INDEX('Output Utente'!$X$2:$X$492,MATCH($B$3,'Output Utente'!$C$2:$C$492,0)),"")
A18: OFFERTA MAX DINAMICA (il tuo vero tetto) | B18: =IFERROR(INDEX('Output Utente'!$AA$2:$AA$492,MATCH($B$3,'Output Utente'!$C$2:$C$492,0)),"") | C18: MIN(Offerta Max Strategica, Budget Spendibile). Non puo' mai superare quanto puoi davvero permetterti.
A20: PRESSIONE COMPETITIVA (informativa)
A21: Pressione Competitiva sul ruolo | B21: =IFERROR(INDEX('Pressione Competitiva'!$F$3:$F$6,MATCH($B$6,'Pressione Competitiva'!$B$3:$B$6,0)),"")
A22: Motivo | B22: =IFERROR(INDEX('Pressione Competitiva'!$G$3:$G$6,MATCH($B$6,'Pressione Competitiva'!$B$3:$B$6,0)),"")
A24: DECISIONE
A25: Prezzo Attuale (da cella B4) | B25: =$B$4 -> 0
A26: Opportunity Gap (Max Bid Dinamica - Prezzo Attuale) | B26: =IF($B$4="","",$B$18-$B$4)
A27: Segnale | B27: =IFERROR(IF($B$4="","",IF($B$26>=$B$18*'Parametri Modello'!$B$68,"🟢 Opportunita'",IF($B$26<=$B$18*'Parametri Modello'!$B$69,"🔴 Sovrapprezzo","🟡 Prezzo Corretto"))),"")
A28: DECISIONE | B28: =IF($B$4="","",IF($B$4>$B$18,"🔴 PASS",IF($B$4<=$B$18*(1-'Parametri Modello'!$B$68),"🟢 BID","🟡 ATTENZIONE")))
A29: Motivo | B29: =IF($B$4="","",IF($B$4>$B$18,"Hai superato il tuo tetto di "&($B$4-$B$18)&" crediti.",IF($B$4<=$B$18*(1-'Parametri Modello'!$B$68),"Margine ampio: "&$B$26&" crediti sotto il tuo tetto.","Margine ridotto: solo "&$B$26&" crediti sotto il tuo tetto.")))
A31: Attenzione | B31: ="Sovrapprezzo rispetto al FVM non significa automaticamente non comprarlo: se la Pressione Competitiva e' alta e ti serve ancora un titolare "&IF($B$6<>"",$B$6,"in questo ruolo")&", puo' comunque valere il tuo Max Bid Dinamico." -> Sovrapprezzo rispetto al FVM non significa automaticamente non comprarlo: se la Pressione Competitiva e' alta e ti serve ancora un titolare in questo ruolo, puo' comunque valere il tuo Max Bid Dinamico.

Sheet Output Utente
A1: Id | B1: R | C1: Nome | D1: Squadra Assegnata | E1: Whichlist | F1: Offerta Max | G1: Valutazione Min | H1: Valutazione Max | I1: Presenze 25/26 (Pv) | J1: Assenze 25/26 (stim.) | K1: Gol 25/26 | L1: Assist 25/26 | M1: Prezzo Pagato | N1: Qt.A | O1: FVM/1000 | P1: Fascia Aspettativa | Q1: _OrdineLiberi | R1: _OrdineMiaRosa | S1: Mv 25/26 | T1: Fm 25/26 | U1: Sostenibilità Budget | V1: Rank FVM nel Ruolo | W1: Budget Residuo | X1: Slot Residui | Y1: Budget Minimo Riserva | Z1: Budget Spendibile | AA1: Offerta Max Dinamica | AB1: Prezzo Corrente | AC1: Decisione Live | AD1: Confidence Storico | AE1: Pressione Ruolo | AF1: Titolare/Riserva (mercato) | AG1: Pressione Competitiva Ruolo | AH1: Opportunity Gap | AI1: Opportunity Gap Segnale | AJ1: Motivo Decisione | AK1: _RankDisponibiliRuoloFascia | AL1: _ChiaveRuoloFasciaRank
A2: 2764 | B2: A | C2: Martinez L. | E2: =IF(COUNTIF('Info Strategia'!$D$2:$D$51,$C2)>0,"SI","NO") -> NO | F2: =IFERROR(ROUND(($G2+($H2-$G2)*'Info Strategia'!$B$6)*(1+IF($E2="SI",'Parametri Modello'!$B$7*'Info Strategia'!$B$6,0)),0),"") -> 397 | G2: =IFERROR(ROUND(MAX(1,(IF($V2<=INDEX('Parametri Modello'!$C$57:$C$60,MATCH($B2,'Parametri Modello'!$A$57:$A$60,0)),IF(INDEX('Parametri Modello'!$E$57:$E$60,MATCH($B2,'Parametri Modello'!$A$57:$A$60,0))=0,0,($O2/INDEX('Parametri Modello'!$E$57:$E$60,MATCH($B2,'Parametri Modello'!$A$57:$A$60,0)))*(INDEX('Parametri Modello'!$D$57:$D$60,MATCH($B2,'Parametri Modello'!$A$57:$A$60,0))*(INDEX('Parametri Modello'!$B$50:$B$53,MATCH($B2,'Parametri Modello'!$A$50:$A$53,0))*'Parametri Modello'!$B$44))),IF(INDEX('Parametri Modello'!$F$57:$F$60,MATCH($B2,'Parametri Modello'!$A$57:$A$60,0))=0,0,($O2/INDEX('Parametri Modello'!$F$57:$F$60,MATCH($B2,'Parametri Modello'!$A$57:$A$60,0)))*((1-INDEX('Parametri Modello'!$D$57:$D$60,MATCH($B2,'Parametri Modello'!$A$57:$A$60,0)))*(INDEX('Parametri Modello'!$B$50:$B$53,MATCH($B2,'Parametri Modello'!$A$50:$A$53,0))*'Parametri Modello'!$B$44))))*(1+IF(IF($B2="D",'Info Lega'!$B$25,IF($B2="C",'Info Lega'!$B$26,"No"))="Si",'Parametri Modello'!$B$5,0))*(1+MAX(-0.25,MIN(0.25,IF(OR($T2="",$I2="",$I2=0,INDEX('Parametri Modello'!$B$19:$B$22,MATCH($B2,'Parametri Modello'!$A$19:$A$22,0))="",INDEX('Parametri Modello'!$B$19:$B$22,MATCH($B2,'Parametri Modello'!$A$19:$A$22,0))=0),0,(($T2-INDEX('Parametri Modello'!$B$19:$B$22,MATCH($B2,'Parametri Modello'!$A$19:$A$22,0)))/INDEX('Parametri Modello'!$B$19:$B$22,MATCH($B2,'Parametri Modello'!$A$19:$A$22,0)))*'Parametri Modello'!$B$9))))*(1+IF('Parametri Modello'!$B$27="Si",MAX(-'Parametri Modello'!$B$28,MIN('Parametri Modello'!$B$28*1.5,IF(OR(INDEX('Parametri Modello'!$F$32:$F$35,MATCH($B2,'Parametri Modello'!$A$32:$A$35,0))="",INDEX('Parametri Modello'!$F$32:$F$35,MATCH($B2,'Parametri Modello'!$A$32:$A$35,0))=0),0,(1/INDEX('Parametri Modello'!$F$32:$F$35,MATCH($B2,'Parametri Modello'!$A$32:$A$35,0))-1)*'Parametri Modello'!$B$28))),0)))*(1-INDEX('Parametri Modello'!$B$12:$B$15,MATCH($B2,'Parametri Modello'!$A$12:$A$15,0)))),0),"") -> 248 | H2: =IFERROR(ROUND((IF($V2<=INDEX('Parametri Modello'!$C$57:$C$60,MATCH($B2,'Parametri Modello'!$A$57:$A$60,0)),IF(INDEX('Parametri Modello'!$E$57:$E$60,MATCH($B2,'Parametri Modello'!$A$57:$A$60,0))=0,0,($O2/INDEX('Parametri Modello'!$E$57:$E$60,MATCH($B2,'Parametri Modello'!$A$57:$A$60,0)))*(INDEX('Parametri Modello'!$D$57:$D$60,MATCH($B2,'Parametri Modello'!$A$57:$A$60,0))*(INDEX('Parametri Modello'!$B$50:$B$53,MATCH($B2,'Parametri Modello'!$A$50:$A$53,0))*'Parametri Modello'!$B$44))),IF(INDEX('Parametri Modello'!$F$57:$F$60,MATCH($B2,'Parametri Modello'!$A$57:$A$60,0))=0,0,($O2/INDEX('Parametri Modello'!$F$57:$F$60,MATCH($B2,'Parametri Modello'!$A$57:$A$60,0)))*((1-INDEX('Parametri Modello'!$D$57:$D$60,MATCH($B2,'Parametri Modello'!$A$57:$A$60,0)))*(INDEX('Parametri Modello'!$B$50:$B$53,MATCH($B2,'Parametri Modello'!$A$50:$A$53,0))*'Parametri Modello'!$B$44))))*(1+IF(IF($B2="D",'Info Lega'!$B$25,IF($B2="C",'Info Lega'!$B$26,"No"))="Si",'Parametri Modello'!$B$5,0))*(1+MAX(-0.25,MIN(0.25,IF(OR($T2="",$I2="",$I2=0,INDEX('Parametri Modello'!$B$19:$B$22,MATCH($B2,'Parametri Modello'!$A$19:$A$22,0))="",INDEX('Parametri Modello'!$B$19:$B$22,MATCH($B2,'Parametri Modello'!$A$19:$A$22,0))=0),0,(($T2-INDEX('Parametri Modello'!$B$19:$B$22,MATCH($B2,'Parametri Modello'!$A$19:$A$22,0)))/INDEX('Parametri Modello'!$B$19:$B$22,MATCH($B2,'Parametri Modello'!$A$19:$A$22,0)))*'Parametri Modello'!$B$9))))*(1+IF('Parametri Modello'!$B$27="Si",MAX(-'Parametri Modello'!$B$28,MIN('Parametri Modello'!$B$28*1.5,IF(OR(INDEX('Parametri Modello'!$F$32:$F$35,MATCH($B2,'Parametri Modello'!$A$32:$A$35,0))="",INDEX('Parametri Modello'!$F$32:$F$35,MATCH($B2,'Parametri Modello'!$A$32:$A$35,0))=0),0,(1/INDEX('Parametri Modello'!$F$32:$F$35,MATCH($B2,'Parametri Modello'!$A$32:$A$35,0))-1)*'Parametri Modello'!$B$28))),0)))*(1+INDEX('Parametri Modello'!$B$12:$B$15,MATCH($B2,'Parametri Modello'!$A$12:$A$15,0))),0),"") -> 461 | I2: =IFERROR(INDEX('Input Statistiche 2025_26'!$F$3:$F$665,MATCH($A2,'Input Statistiche 2025_26'!$A$3:$A$665,0)),"") -> 30 | J2: =IFERROR(IF($I2="","",MAX(0,38-$I2)),"") -> 8 | K2: =IFERROR(INDEX('Input Statistiche 2025_26'!$I$3:$I$665,MATCH($A2,'Input Statistiche 2025_26'!$A$3:$A$665,0)),"") -> 17 | L2: =IFERROR(INDEX('Input Statistiche 2025_26'!$O$3:$O$665,MATCH($A2,'Input Statistiche 2025_26'!$A$3:$A$665,0)),"") -> 6 | N2: =IFERROR(INDEX('Input Giocatori 2026_27'!$E$3:$E$493,MATCH($A2,'Input Giocatori 2026_27'!$A$3:$A$493,0)),"") -> 35 | O2: =IFERROR(INDEX('Input Giocatori 2026_27'!$G$3:$G$493,MATCH($A2,'Input Giocatori 2026_27'!$A$3:$A$493,0)),"") -> 370 | P2: =IFERROR(IF($O2="","",IF((1-(COUNTIFS($B$2:$B$492,$B2,$O$2:$O$492,">"&$O2)+1-1)/COUNTIF($B$2:$B$492,$B2))>='Parametri Modello'!$B$63,"Top",IF((1-(COUNTIFS($B$2:$B$492,$B2,$O$2:$O$492,">"&$O2)+1-1)/COUNTIF($B$2:$B$492,$B2))>='Parametri Modello'!$B$64,"Buono",IF((1-(COUNTIFS($B$2:$B$492,$B2,$O$2:$O$492,">"&$O2)+1-1)/COUNTIF($B$2:$B$492,$B2))>='Parametri Modello'!$B$65,"Nella Media","Scommessa/Riserva")))),"") -> Top | Q2: =IF(AND($D2="",$N2>1),SUMPRODUCT(($D$2:$D2="")*($N$2:$N2>1)),"") -> 1 | R2: =IF($D2='Info Lega'!$B$28,COUNTIFS($D$2:$D2,'Info Lega'!$B$28),"") | S2: =IFERROR(INDEX('Input Statistiche 2025_26'!$G$3:$G$665,MATCH($A2,'Input Statistiche 2025_26'!$A$3:$A$665,0)),"") -> 6.42 | T2: =IFERROR(INDEX('Input Statistiche 2025_26'!$H$3:$H$665,MATCH($A2,'Input Statistiche 2025_26'!$A$3:$A$665,0)),"") -> 8.25 | U2: =IF(OR('La Mia Rosa'!$O$12="",$D2<>""),"",IF($F2<='La Mia Rosa'!$O$12*'Parametri Modello'!$B$24,"OK",IF($F2<='La Mia Rosa'!$O$12*'Parametri Modello'!$B$25,"Attenzione","Rischio Alto"))) -> Rischio Alto | V2: =IFERROR(COUNTIFS($B$2:$B$492,$B2,$O$2:$O$492,">"&$O2)+1,"") -> 1 | W2: ='Info Lega'!$B$4-SUMIFS($M$2:$M$492,$D$2:$D$492,'Info Lega'!$B$28) -> 1000 | X2: =('Info Lega'!$B$5-COUNTIFS($D$2:$D$492,'Info Lega'!$B$28,$B$2:$B$492,"P"))+('Info Lega'!$B$6-COUNTIFS($D$2:$D$492,'Info Lega'!$B$28,$B$2:$B$492,"D"))+('Info Lega'!$B$7-COUNTIFS($D$2:$D$492,'Info Lega'!$B$28,$B$2:$B$492,"C"))+('Info Lega'!$B$8-COUNTIFS($D$2:$D$492,'Info Lega'!$B$28,$B$2:$B$492,"A")) -> 25 | Y2: =X2*'Parametri Modello'!$B$30 -> 25 | Z2: =MAX(0,W2-Y2) -> 975 | AA2: =MIN(F2,Z2) -> 397 | AC2: =IF($AB2="","",IF($AB2>$AA2,"PASS",IF($AB2<=$AA2*(1-'Parametri Modello'!$B$68),"BID","ATTENZIONE"))) | AD2: =IF(I2="","",ROUND(100*(1-EXP(-I2/30)),0)) -> 63 | AE2: =IFERROR(INDEX('Stato Asta'!$G$9:$G$12,MATCH($B2,'Stato Asta'!$A$9:$A$12,0)),"") -> 🔴 Non aspettare | AF2: =IFERROR(IF($V2<=INDEX('Parametri Modello'!$C$57:$C$60,MATCH($B2,'Parametri Modello'!$A$57:$A$60,0)),"Titolare","Riserva"),"") -> Titolare | AG2: =IFERROR(INDEX('Pressione Competitiva'!$F$3:$F$6,MATCH($B2,'Pressione Competitiva'!$B$3:$B$6,0)),"") -> 🔴 Molto Alta | AH2: =IF($AB2="","",$AA2-$AB2) | AI2: =IFERROR(IF($AH2="","",IF($AH2>=$AA2*'Parametri Modello'!$B$68,"🟢 Opportunita'",IF($AH2<=$AA2*'Parametri Modello'!$B$69,"🔴 Sovrapprezzo","🟡 Prezzo Corretto"))),"") | AJ2: =IF($AB2="","",IF($AC2="PASS","Prezzo sopra la tua Offerta Max Dinamica ("&$AA2&" cr).",IF($AC2="BID","Margine ampio sul tuo tetto (+"&($AA2-$AB2)&" cr).","Margine ridotto: sei vicino al tuo tetto ("&($AA2-$AB2)&" cr residui)."))) | AK2: =IF(AND($D2="",$N2>1),COUNTIFS($B$2:$B$492,$B2,$P$2:$P$492,$P2,$D$2:$D$492,"",$N$2:$N$492,">1",$O$2:$O$492,">"&$O2)+1,"") -> 1 | AL2: =IF($AK2="","",$B2&"|"&$P2&"|"&$AK2) -> A|Top|1
A3: 5585 | B3: A | C3: Malen | E3: =IF(COUNTIF('Info Strategia'!$D$2:$D$51,$C3)>0,"SI","NO") -> NO | F3: =IFERROR(ROUND(($G3+($H3-$G3)*'Info Strategia'!$B$6)*(1+IF($E3="SI",'Parametri Modello'!$B$7*'Info Strategia'!$B$6,0)),0),"") -> 400 | G3: =IFERROR(ROUND(MAX(1,(IF($V3<=INDEX('Parametri Modello'!$C$57:$C$60,MATCH($B3,'Parametri Modello'!$A$57:$A$60,0)),IF(INDEX('Parametri Modello'!$E$57:$E$60,MATCH($B3,'Parametri Modello'!$A$57:$A$60,0))=0,0,($O3/INDEX('Parametri Modello'!$E$57:$E$60,MATCH($B3,'Parametri Modello'!$A$57:$A$60,0)))*(INDEX('Parametri Modello'!$D$57:$D$60,MATCH($B3,'Parametri Modello'!$A$57:$A$60,0))*(INDEX('Parametri Modello'!$B$50:$B$53,MATCH($B3,'Parametri Modello'!$A$50:$A$53,0))*'Parametri Modello'!$B$44))),IF(INDEX('Parametri Modello'!$F$57:$F$60,MATCH($B3,'Parametri Modello'!$A$57:$A$60,0))=0,0,($O3/INDEX('Parametri Modello'!$F$57:$F$60,MATCH($B3,'Parametri Modello'!$A$57:$A$60,0)))*((1-INDEX('Parametri Modello'!$D$57:$D$60,MATCH($B3,'Parametri Modello'!$A$57:$A$60,0)))*(INDEX('Parametri Modello'!$B$50:$B$53,MATCH($B3,'Parametri Modello'!$A$50:$A$53,0))*'Parametri Modello'!$B$44))))*(1+IF(IF($B3="D",'Info Lega'!$B$25,IF($B3="C",'Info Lega'!$B$26,"No"))="Si",'Parametri Modello'!$B$5,0))*(1+MAX(-0.25,MIN(0.25,IF(OR($T3="",$I3="",$I3=0,INDEX('Parametri Modello'!$B$19:$B$22,MATCH($B3,'Parametri Modello'!$A$19:$A$22,0))="",INDEX('Parametri Modello'!$B$19:$B$22,MATCH($B3,'Parametri Modello'!$A$19:$A$22,0))=0),0,(($T3-INDEX('Parametri Modello'!$B$19:$B$22,MATCH($B3,'Parametri Modello'!$A$19:$A$22,0)))/INDEX('Parametri Modello'!$B$19:$B$22,MATCH($B3,'Parametri Modello'!$A$19:$A$22,0)))*'Parametri Modello'!$B$9))))*(1+IF('Parametri Modello'!$B$27="Si",MAX(-'Parametri Modello'!$B$28,MIN('Parametri Modello'!$B$28*1.5,IF(OR(INDEX('Parametri Modello'!$F$32:$F$35,MATCH($B3,'Parametri Modello'!$A$32:$A$35,0))="",INDEX('Parametri Modello'!$F$32:$F$35,MATCH($B3,'Parametri Modello'!$A$32:$A$35,0))=0),0,(1/INDEX('Parametri Modello'!$F$32:$F$35,MATCH($B3,'Parametri Modello'!$A$32:$A$35,0))-1)*'Parametri Modello'!$B$28))),0)))*(1-INDEX('Parametri Modello'!$B$12:$B$15,MATCH($B3,'Parametri Modello'!$A$12:$A$15,0)))),0),"") -> 250 | H3: =IFERROR(ROUND((IF($V3<=INDEX('Parametri Modello'!$C$57:$C$60,MATCH($B3,'Parametri Modello'!$A$57:$A$60,0)),IF(INDEX('Parametri Modello'!$E$57:$E$60,MATCH($B3,'Parametri Modello'!$A$57:$A$60,0))=0,0,($O3/INDEX('Parametri Modello'!$E$57:$E$60,MATCH($B3,'Parametri Modello'!$A$57:$A$60,0)))*(INDEX('Parametri Modello'!$D$57:$D$60,MATCH($B3,'Parametri Modello'!$A$57:$A$60,0))*(INDEX('Parametri Modello'!$B$50:$B$53,MATCH($B3,'Parametri Modello'!$A$50:$A$53,0))*'Parametri Modello'!$B$44))),IF(INDEX('Parametri Modello'!$F$57:$F$60,MATCH($B3,'Parametri Modello'!$A$57:$A$60,0))=0,0,($O3/INDEX('Parametri Modello'!$F$57:$F$60,MATCH($B3,'Parametri Modello'!$A$57:$A$60,0)))*((1-INDEX('Parametri Modello'!$D$57:$D$60,MATCH($B3,'Parametri Modello'!$A$57:$A$60,0)))*(INDEX('Parametri Modello'!$B$50:$B$53,MATCH($B3,'Parametri Modello'!$A$50:$A$53,0))*'Parametri Modello'!$B$44))))*(1+IF(IF($B3="D",'Info Lega'!$B$25,IF($B3="C",'Info Lega'!$B$26,"No"))="Si",'Parametri Modello'!$B$5,0))*(1+MAX(-0.25,MIN(0.25,IF(OR($T3="",$I3="",$I3=0,INDEX('Parametri Modello'!$B$19:$B$22,MATCH($B3,'Parametri Modello'!$A$19:$A$22,0))="",INDEX('Parametri Modello'!$B$19:$B$22,MATCH($B3,'Parametri Modello'!$A$19:$A$22,0))=0),0,(($T3-INDEX('Parametri Modello'!$B$19:$B$22,MATCH($B3,'Parametri Modello'!$A$19:$A$22,0)))/INDEX('Parametri Modello'!$B$19:$B$22,MATCH($B3,'Parametri Modello'!$A$19:$A$22,0)))*'Parametri Modello'!$B$9))))*(1+IF('Parametri Modello'!$B$27="Si",MAX(-'Parametri Modello'!$B$28,MIN('Parametri Modello'!$B$28*1.5,IF(OR(INDEX('Parametri Modello'!$F$32:$F$35,MATCH($B3,'Parametri Modello'!$A$32:$A$35,0))="",INDEX('Parametri Modello'!$F$32:$F$35,MATCH($B3,'Parametri Modello'!$A$32:$A$35,0))=0),0,(1/INDEX('Parametri Modello'!$F$32:$F$35,MATCH($B3,'Parametri Modello'!$A$32:$A$35,0))-1)*'Parametri Modello'!$B$28))),0)))*(1+INDEX('Parametri Modello'!$B$12:$B$15,MATCH($B3,'Parametri Modello'!$A$12:$A$15,0))),0),"") -> 464 | I3: =IFERROR(INDEX('Input Statistiche 2025_26'!$F$3:$F$665,MATCH($A3,'Input Statistiche 2025_26'!$A$3:$A$665,0)),"") -> 18 | J3: =IFERROR(IF($I3="","",MAX(0,38-$I3)),"") -> 20 | K3: =IFERROR(INDEX('Input Statistiche 2025_26'!$I$3:$I$665,MATCH($A3,'Input Statistiche 2025_26'!$A$3:$A$665,0)),"") -> 14 | L3: =IFERROR(INDEX('Input Statistiche 2025_26'!$O$3:$O$665,MATCH($A3,'Input Statistiche 2025_26'!$A$3:$A$665,0)),"") -> 2 | N3: =IFERROR(INDEX('Input Giocatori 2026_27'!$E$3:$E$493,MATCH($A3,'Input Giocatori 2026_27'!$A$3:$A$493,0)),"") -> 34 | O3: =IFERROR(INDEX('Input Giocatori 2026_27'!$G$3:$G$493,MATCH($A3,'Input Giocatori 2026_27'!$A$3:$A$493,0)),"") -> 365 | P3: =IFERROR(IF($O3="","",IF((1-(COUNTIFS($B$2:$B$492,$B3,$O$2:$O$492,">"&$O3)+1-1)/COUNTIF($B$2:$B$492,$B3))>='Parametri Modello'!$B$63,"Top",IF((1-(COUNTIFS($B$2:$B$492,$B3,$O$2:$O$492,">"&$O3)+1-1)/COUNTIF($B$2:$B$492,$B3))>='Parametri Modello'!$B$64,"Buono",IF((1-(COUNTIFS($B$2:$B$492,$B3,$O$2:$O$492,">"&$O3)+1-1)/COUNTIF($B$2:$B$492,$B3))>='Parametri Modello'!$B$65,"Nella Media","Scommessa/Riserva")))),"") -> Top | Q3: =IF(AND($D3="",$N3>1),SUMPRODUCT(($D$2:$D3="")*($N$2:$N3>1)),"") -> 2 | R3: =IF($D3='Info Lega'!$B$28,COUNTIFS($D$2:$D3,'Info Lega'!$B$28),"") | S3: =IFERROR(INDEX('Input Statistiche 2025_26'!$G$3:$G$665,MATCH($A3,'Input Statistiche 2025_26'!$A$3:$A$665,0)),"") -> 6.72 | T3: =IFERROR(INDEX('Input Statistiche 2025_26'!$H$3:$H$665,MATCH($A3,'Input Statistiche 2025_26'!$A$3:$A$665,0)),"") -> 8.97 | U3: =IF(OR('La Mia Rosa'!$O$12="",$D3<>""),"",IF($F3<='La Mia Rosa'!$O$12*'Parametri Modello'!$B$24,"OK",IF($F3<='La Mia Rosa'!$O$12*'Parametri Modello'!$B$25,"Attenzione","Rischio Alto"))) -> Rischio Alto | V3: =IFERROR(COUNTIFS($B$2:$B$492,$B3,$O$2:$O$492,">"&$O3)+1,"") -> 2 | W3: ='Info Lega'!$B$4-SUMIFS($M$2:$M$492,$D$2:$D$492,'Info Lega'!$B$28) -> 1000 | X3: =('Info Lega'!$B$5-COUNTIFS($D$2:$D$492,'Info Lega'!$B$28,$B$2:$B$492,"P"))+('Info Lega'!$B$6-COUNTIFS($D$2:$D$492,'Info Lega'!$B$28,$B$2:$B$492,"D"))+('Info Lega'!$B$7-COUNTIFS($D$2:$D$492,'Info Lega'!$B$28,$B$2:$B$492,"C"))+('Info Lega'!$B$8-COUNTIFS($D$2:$D$492,'Info Lega'!$B$28,$B$2:$B$492,"A")) -> 25 | Y3: =X3*'Parametri Modello'!$B$30 -> 25 | Z3: =MAX(0,W3-Y3) -> 975 | AA3: =MIN(F3,Z3) -> 400 | AC3: =IF($AB3="","",IF($AB3>$AA3,"PASS",IF($AB3<=$AA3*(1-'Parametri Modello'!$B$68),"BID","ATTENZIONE"))) | AD3: =IF(I3="","",ROUND(100*(1-EXP(-I3/30)),0)) -> 45 | AE3: =IFERROR(INDEX('Stato Asta'!$G$9:$G$12,MATCH($B3,'Stato Asta'!$A$9:$A$12,0)),"") -> 🔴 Non aspettare | AF3: =IFERROR(IF($V3<=INDEX('Parametri Modello'!$C$57:$C$60,MATCH($B3,'Parametri Modello'!$A$57:$A$60,0)),"Titolare","Riserva"),"") -> Titolare | AG3: =IFERROR(INDEX('Pressione Competitiva'!$F$3:$F$6,MATCH($B3,'Pressione Competitiva'!$B$3:$B$6,0)),"") -> 🔴 Molto Alta | AH3: =IF($AB3="","",$AA3-$AB3) | AI3: =IFERROR(IF($AH3="","",IF($AH3>=$AA3*'Parametri Modello'!$B$68,"🟢 Opportunita'",IF($AH3<=$AA3*'Parametri Modello'!$B$69,"🔴 Sovrapprezzo","🟡 Prezzo Corretto"))),"") | AJ3: =IF($AB3="","",IF($AC3="PASS","Prezzo sopra la tua Offerta Max Dinamica ("&$AA3&" cr).",IF($AC3="BID","Margine ampio sul tuo tetto (+"&($AA3-$AB3)&" cr).","Margine ridotto: sei vicino al tuo tetto ("&($AA3-$AB3)&" cr residui)."))) | AK3: =IF(AND($D3="",$N3>1),COUNTIFS($B$2:$B$492,$B3,$P$2:$P$492,$P3,$D$2:$D$492,"",$N$2:$N$492,">1",$O$2:$O$492,">"&$O3)+1,"") -> 2 | AL3: =IF($AK3="","",$B3&"|"&$P3&"|"&$AK3) -> A|Top|2
A4: 4871 | B4: A | C4: Thuram | E4: =IF(COUNTIF('Info Strategia'!$D$2:$D$51,$C4)>0,"SI","NO") -> NO | F4: =IFERROR(ROUND(($G4+($H4-$G4)*'Info Strategia'!$B$6)*(1+IF($E4="SI",'Parametri Modello'!$B$7*'Info Strategia'!$B$6,0)),0),"") -> 298 | G4: =IFERROR(ROUND(MAX(1,(IF($V4<=INDEX('Parametri Modello'!$C$57:$C$60,MATCH($B4,'Parametri Modello'!$A$57:$A$60,0)),IF(INDEX('Parametri Modello'!$E$57:$E$60,MATCH($B4,'Parametri Modello'!$A$57:$A$60,0))=0,0,($O4/INDEX('Parametri Modello'!$E$57:$E$60,MATCH($B4,'Parametri Modello'!$A$57:$A$60,0)))*(INDEX('Parametri Modello'!$D$57:$D$60,MATCH($B4,'Parametri Modello'!$A$57:$A$60,0))*(INDEX('Parametri Modello'!$B$50:$B$53,MATCH($B4,'Parametri Modello'!$A$50:$A$53,0))*'Parametri Modello'!$B$44))),IF(INDEX('Parametri Modello'!$F$57:$F$60,MATCH($B4,'Parametri Modello'!$A$57:$A$60,0))=0,0,($O4/INDEX('Parametri Modello'!$F$57:$F$60,MATCH($B4,'Parametri Modello'!$A$57:$A$60,0)))*((1-INDEX('Parametri Modello'!$D$57:$D$60,MATCH($B4,'Parametri Modello'!$A$57:$A$60,0)))*(INDEX('Parametri Modello'!$B$50:$B$53,MATCH($B4,'Parametri Modello'!$A$50:$A$53,0))*'Parametri Modello'!$B$44))))*(1+IF(IF($B4="D",'Info Lega'!$B$25,IF($B4="C",'Info Lega'!$B$26,"No"))="Si",'Parametri Modello'!$B$5,0))*(1+MAX(-0.25,MIN(0.25,IF(OR($T4="",$I4="",$I4=0,INDEX('Parametri Modello'!$B$19:$B$22,MATCH($B4,'Parametri Modello'!$A$19:$A$22,0))="",INDEX('Parametri Modello'!$B$19:$B$22,MATCH($B4,'Parametri Modello'!$A$19:$A$22,0))=0),0,(($T4-INDEX('Parametri Modello'!$B$19:$B$22,MATCH($B4,'Parametri Modello'!$A$19:$A$22,0)))/INDEX('Parametri Modello'!$B$19:$B$22,MATCH($B4,'Parametri Modello'!$A$19:$A$22,0)))*'Parametri Modello'!$B$9))))*(1+IF('Parametri Modello'!$B$27="Si",MAX(-'Parametri Modello'!$B$28,MIN('Parametri Modello'!$B$28*1.5,IF(OR(INDEX('Parametri Modello'!$F$32:$F$35,MATCH($B4,'Parametri Modello'!$A$32:$A$35,0))="",INDEX('Parametri Modello'!$F$32:$F$35,MATCH($B4,'Parametri Modello'!$A$32:$A$35,0))=0),0,(1/INDEX('Parametri Modello'!$F$32:$F$35,MATCH($B4,'Parametri Modello'!$A$32:$A$35,0))-1)*'Parametri Modello'!$B$28))),0)))*(1-INDEX('Parametri Modello'!$B$12:$B$15,MATCH($B4,'Parametri Modello'!$A$12:$A$15,0)))),0),"") -> 186 | H4: =IFERROR(ROUND((IF($V4<=INDEX('Parametri Modello'!$C$57:$C$60,MATCH($B4,'Parametri Modello'!$A$57:$A$60,0)),IF(INDEX('Parametri Modello'!$E$57:$E$60,MATCH($B4,'Parametri Modello'!$A$57:$A$60,0))=0,0,($O4/INDEX('Parametri Modello'!$E$57:$E$60,MATCH($B4,'Parametri Modello'!$A$57:$A$60,0)))*(INDEX('Parametri Modello'!$D$57:$D$60,MATCH($B4,'Parametri Modello'!$A$57:$A$60,0))*(INDEX('Parametri Modello'!$B$50:$B$53,MATCH($B4,'Parametri Modello'!$A$50:$A$53,0))*'Parametri Modello'!$B$44))),IF(INDEX('Parametri Modello'!$F$57:$F$60,MATCH($B4,'Parametri Modello'!$A$57:$A$60,0))=0,0,($O4/INDEX('Parametri Modello'!$F$57:$F$60,MATCH($B4,'Parametri Modello'!$A$57:$A$60,0)))*((1-INDEX('Parametri Modello'!$D$57:$D$60,MATCH($B4,'Parametri Modello'!$A$57:$A$60,0)))*(INDEX('Parametri Modello'!$B$50:$B$53,MATCH($B4,'Parametri Modello'!$A$50:$A$53,0))*'Parametri Modello'!$B$44))))*(1+IF(IF($B4="D",'Info Lega'!$B$25,IF($B4="C",'Info Lega'!$B$26,"No"))="Si",'Parametri Modello'!$B$5,0))*(1+MAX(-0.25,MIN(0.25,IF(OR($T4="",$I4="",$I4=0,INDEX('Parametri Modello'!$B$19:$B$22,MATCH($B4,'Parametri Modello'!$A$19:$A$22,0))="",INDEX('Parametri Modello'!$B$19:$B$22,MATCH($B4,'Parametri Modello'!$A$19:$A$22,0))=0),0,(($T4-INDEX('Parametri Modello'!$B$19:$B$22,MATCH($B4,'Parametri Modello'!$A$19:$A$22,0)))/INDEX('Parametri Modello'!$B$19:$B$22,MATCH($B4,'Parametri Modello'!$A$19:$A$22,0)))*'Parametri Modello'!$B$9))))*(1+IF('Parametri Modello'!$B$27="Si",MAX(-'Parametri Modello'!$B$28,MIN('Parametri Modello'!$B$28*1.5,IF(OR(INDEX('Parametri Modello'!$F$32:$F$35,MATCH($B4,'Parametri Modello'!$A$32:$A$35,0))="",INDEX('Parametri Modello'!$F$32:$F$35,MATCH($B4,'Parametri Modello'!$A$32:$A$35,0))=0),0,(1/INDEX('Parametri Modello'!$F$32:$F$35,MATCH($B4,'Parametri Modello'!$A$32:$A$35,0))-1)*'Parametri Modello'!$B$28))),0)))*(1+INDEX('Parametri Modello'!$B$12:$B$15,MATCH($B4,'Parametri Modello'!$A$12:$A$15,0))),0),"") -> 346 | I4: =IFERROR(INDEX('Input Statistiche 2025_26'!$F$3:$F$665,MATCH($A4,'Input Statistiche 2025_26'!$A$3:$A$665,0)),"") -> 29 | J4: =IFERROR(IF($I4="","",MAX(0,38-$I4)),"") -> 9 | K4: =IFERROR(INDEX('Input Statistiche 2025_26'!$I$3:$I$665,MATCH($A4,'Input Statistiche 2025_26'!$A$3:$A$665,0)),"") -> 13 | L4: =IFERROR(INDEX('Input Statistiche 2025_26'!$O$3:$O$665,MATCH($A4,'Input Statistiche 2025_26'!$A$3:$A$665,0)),"") -> 6 | N4: =IFERROR(INDEX('Input Giocatori 2026_27'!$E$3:$E$493,MATCH($A4,'Input Giocatori 2026_27'!$A$3:$A$493,0)),"") -> 29 | O4: =IFERROR(INDEX('Input Giocatori 2026_27'!$G$3:$G$493,MATCH($A4,'Input Giocatori 2026_27'!$A$3:$A$493,0)),"") -> 280 | P4: =IFERROR(IF($O4="","",IF((1-(COUNTIFS($B$2:$B$492,$B4,$O$2:$O$492,">"&$O4)+1-1)/COUNTIF($B$2:$B$492,$B4))>='Parametri Modello'!$B$63,"Top",IF((1-(COUNTIFS($B$2:$B$492,$B4,$O$2:$O$492,">"&$O4)+1-1)/COUNTIF($B$2:$B$492,$B4))>='Parametri Modello'!$B$64,"Buono",IF((1-(COUNTIFS($B$2:$B$492,$B4,$O$2:$O$492,">"&$O4)+1-1)/COUNTIF($B$2:$B$492,$B4))>='Parametri Modello'!$B$65,"Nella Media","Scommessa/Riserva")))),"") -> Top | Q4: =IF(AND($D4="",$N4>1),SUMPRODUCT(($D$2:$D4="")*($N$2:$N4>1)),"") -> 3 | R4: =IF($D4='Info Lega'!$B$28,COUNTIFS($D$2:$D4,'Info Lega'!$B$28),"") | S4: =IFERROR(INDEX('Input Statistiche 2025_26'!$G$3:$G$665,MATCH($A4,'Input Statistiche 2025_26'!$A$3:$A$665,0)),"") -> 6.43 | T4: =IFERROR(INDEX('Input Statistiche 2025_26'!$H$3:$H$665,MATCH($A4,'Input Statistiche 2025_26'!$A$3:$A$665,0)),"") -> 7.95 | U4: =IF(OR('La Mia Rosa'!$O$12="",$D4<>""),"",IF($F4<='La Mia Rosa'!$O$12*'Parametri Modello'!$B$24,"OK",IF($F4<='La Mia Rosa'!$O$12*'Parametri Modello'!$B$25,"Attenzione","Rischio Alto"))) -> Rischio Alto | V4: =IFERROR(COUNTIFS($B$2:$B$492,$B4,$O$2:$O$492,">"&$O4)+1,"") -> 3 | W4: ='Info Lega'!$B$4-SUMIFS($M$2:$M$492,$D$2:$D$492,'Info Lega'!$B$28) -> 1000 | X4: =('Info Lega'!$B$5-COUNTIFS($D$2:$D$492,'Info Lega'!$B$28,$B$2:$B$492,"P"))+('Info Lega'!$B$6-COUNTIFS($D$2:$D$492,'Info Lega'!$B$28,$B$2:$B$492,"D"))+('Info Lega'!$B$7-COUNTIFS($D$2:$D$492,'Info Lega'!$B$28,$B$2:$B$492,"C"))+('Info Lega'!$B$8-COUNTIFS($D$2:$D$492,'Info Lega'!$B$28,$B$2:$B$492,"A")) -> 25 | Y4: =X4*'Parametri Modello'!$B$30 -> 25 | Z4: =MAX(0,W4-Y4) -> 975 | AA4: =MIN(F4,Z4) -> 298 | AC4: =IF($AB4="","",IF($AB4>$AA4,"PASS",IF($AB4<=$AA4*(1-'Parametri Modello'!$B$68),"BID","ATTENZIONE"))) | AD4: =IF(I4="","",ROUND(100*(1-EXP(-I4/30)),0)) -> 62 | AE4: =IFERROR(INDEX('Stato Asta'!$G$9:$G$12,MATCH($B4,'Stato Asta'!$A$9:$A$12,0)),"") -> 🔴 Non aspettare | AF4: =IFERROR(IF($V4<=INDEX('Parametri Modello'!$C$57:$C$60,MATCH($B4,'Parametri Modello'!$A$57:$A$60,0)),"Titolare","Riserva"),"") -> Titolare | AG4: =IFERROR(INDEX('Pressione Competitiva'!$F$3:$F$6,MATCH($B4,'Pressione Competitiva'!$B$3:$B$6,0)),"") -> 🔴 Molto Alta | AH4: =IF($AB4="","",$AA4-$AB4) | AI4: =IFERROR(IF($AH4="","",IF($AH4>=$AA4*'Parametri Modello'!$B$68,"🟢 Opportunita'",IF($AH4<=$AA4*'Parametri Modello'!$B$69,"🔴 Sovrapprezzo","🟡 Prezzo Corretto"))),"") | AJ4: =IF($AB4="","",IF($AC4="PASS","Prezzo sopra la tua Offerta Max Dinamica ("&$AA4&" cr).",IF($AC4="BID","Margine ampio sul tuo tetto (+"&($AA4-$AB4)&" cr).","Margine ridotto: sei vicino al tuo tetto ("&($AA4-$AB4)&" cr residui)."))) | AK4: =IF(AND($D4="",$N4>1),COUNTIFS($B$2:$B$492,$B4,$P$2:$P$492,$P4,$D$2:$D$492,"",$N$2:$N$492,">1",$O$2:$O$492,">"&$O4)+1,"") -> 3 | AL4: =IF($AK4="","",$B4&"|"&$P4&"|"&$AK4) -> A|Top|3
A5: 6052 | B5: A | C5: Hojlund | E5: =IF(COUNTIF('Info Strategia'!$D$2:$D$51,$C5)>0,"SI","NO") -> NO | F5: =IFERROR(ROUND(($G5+($H5-$G5)*'Info Strategia'!$B$6)*(1+IF($E5="SI",'Parametri Modello'!$B$7*'Info Strategia'!$B$6,0)),0),"") -> 284 | G5: =IFERROR(ROUND(MAX(1,(IF($V5<=INDEX('Parametri Modello'!$C$57:$C$60,MATCH($B5,'Parametri Modello'!$A$57:$A$60,0)),IF(INDEX('Parametri Modello'!$E$57:$E$60,MATCH($B5,'Parametri Modello'!$A$57:$A$60,0))=0,0,($O5/INDEX('Parametri Modello'!$E$57:$E$60,MATCH($B5,'Parametri Modello'!$A$57:$A$60,0)))*(INDEX('Parametri Modello'!$D$57:$D$60,MATCH($B5,'Parametri Modello'!$A$57:$A$60,0))*(INDEX('Parametri Modello'!$B$50:$B$53,MATCH($B5,'Parametri Modello'!$A$50:$A$53,0))*'Parametri Modello'!$B$44))),IF(INDEX('Parametri Modello'!$F$57:$F$60,MATCH($B5,'Parametri Modello'!$A$57:$A$60,0))=0,0,($O5/INDEX('Parametri Modello'!$F$57:$F$60,MATCH($B5,'Parametri Modello'!$A$57:$A$60,0)))*((1-INDEX('Parametri Modello'!$D$57:$D$60,MATCH($B5,'Parametri Modello'!$A$57:$A$60,0)))*(INDEX('Parametri Modello'!$B$50:$B$53,MATCH($B5,'Parametri Modello'!$A$50:$A$53,0))*'Parametri Modello'!$B$44))))*(1+IF(IF($B5="D",'Info Lega'!$B$25,IF($B5="C",'Info Lega'!$B$26,"No"))="Si",'Parametri Modello'!$B$5,0))*(1+MAX(-0.25,MIN(0.25,IF(OR($T5="",$I5="",$I5=0,INDEX('Parametri Modello'!$B$19:$B$22,MATCH($B5,'Parametri Modello'!$A$19:$A$22,0))="",INDEX('Parametri Modello'!$B$19:$B$22,MATCH($B5,'Parametri Modello'!$A$19:$A$22,0))=0),0,(($T5-INDEX('Parametri Modello'!$B$19:$B$22,MATCH($B5,'Parametri Modello'!$A$19:$A$22,0)))/INDEX('Parametri Modello'!$B$19:$B$22,MATCH($B5,'Parametri Modello'!$A$19:$A$22,0)))*'Parametri Modello'!$B$9))))*(1+IF('Parametri Modello'!$B$27="Si",MAX(-'Parametri Modello'!$B$28,MIN('Parametri Modello'!$B$28*1.5,IF(OR(INDEX('Parametri Modello'!$F$32:$F$35,MATCH($B5,'Parametri Modello'!$A$32:$A$35,0))="",INDEX('Parametri Modello'!$F$32:$F$35,MATCH($B5,'Parametri Modello'!$A$32:$A$35,0))=0),0,(1/INDEX('Parametri Modello'!$F$32:$F$35,MATCH($B5,'Parametri Modello'!$A$32:$A$35,0))-1)*'Parametri Modello'!$B$28))),0)))*(1-INDEX('Parametri Modello'!$B$12:$B$15,MATCH($B5,'Parametri Modello'!$A$12:$A$15,0)))),0),"") -> 178 | H5: =IFERROR(ROUND((IF($V5<=INDEX('Parametri Modello'!$C$57:$C$60,MATCH($B5,'Parametri Modello'!$A$57:$A$60,0)),IF(INDEX('Parametri Modello'!$E$57:$E$60,MATCH($B5,'Parametri Modello'!$A$57:$A$60,0))=0,0,($O5/INDEX('Parametri Modello'!$E$57:$E$60,MATCH($B5,'Parametri Modello'!$A$57:$A$60,0)))*(INDEX('Parametri Modello'!$D$57:$D$60,MATCH($B5,'Parametri Modello'!$A$57:$A$60,0))*(INDEX('Parametri Modello'!$B$50:$B$53,MATCH($B5,'Parametri Modello'!$A$50:$A$53,0))*'Parametri Modello'!$B$44))),IF(INDEX('Parametri Modello'!$F$57:$F$60,MATCH($B5,'Parametri Modello'!$A$57:$A$60,0))=0,0,($O5/INDEX('Parametri Modello'!$F$57:$F$60,MATCH($B5,'Parametri Modello'!$A$57:$A$60,0)))*((1-INDEX('Parametri Modello'!$D$57:$D$60,MATCH($B5,'Parametri Modello'!$A$57:$A$60,0)))*(INDEX('Parametri Modello'!$B$50:$B$53,MATCH($B5,'Parametri Modello'!$A$50:$A$53,0))*'Parametri Modello'!$B$44))))*(1+IF(IF($B5="D",'Info Lega'!$B$25,IF($B5="C",'Info Lega'!$B$26,"No"))="Si",'Parametri Modello'!$B$5,0))*(1+MAX(-0.25,MIN(0.25,IF(OR($T5="",$I5="",$I5=0,INDEX('Parametri Modello'!$B$19:$B$22,MATCH($B5,'Parametri Modello'!$A$19:$A$22,0))="",INDEX('Parametri Modello'!$B$19:$B$22,MATCH($B5,'Parametri Modello'!$A$19:$A$22,0))=0),0,(($T5-INDEX('Parametri Modello'!$B$19:$B$22,MATCH($B5,'Parametri Modello'!$A$19:$A$22,0)))/INDEX('Parametri Modello'!$B$19:$B$22,MATCH($B5,'Parametri Modello'!$A$19:$A$22,0)))*'Parametri Modello'!$B$9))))*(1+IF('Parametri Modello'!$B$27="Si",MAX(-'Parametri Modello'!$B$28,MIN('Parametri Modello'!$B$28*1.5,IF(OR(INDEX('Parametri Modello'!$F$32:$F$35,MATCH($B5,'Parametri Modello'!$A$32:$A$35,0))="",INDEX('Parametri Modello'!$F$32:$F$35,MATCH($B5,'Parametri Modello'!$A$32:$A$35,0))=0),0,(1/INDEX('Parametri Modello'!$F$32:$F$35,MATCH($B5,'Parametri Modello'!$A$32:$A$35,0))-1)*'Parametri Modello'!$B$28))),0)))*(1+INDEX('Parametri Modello'!$B$12:$B$15,MATCH($B5,'Parametri Modello'!$A$12:$A$15,0))),0),"") -> 330 | I5: =IFERROR(INDEX('Input Statistiche 2025_26'!$F$3:$F$665,MATCH($A5,'Input Statistiche 2025_26'!$A$3:$A$665,0)),"") -> 33 | J5: =IFERROR(IF($I5="","",MAX(0,38-$I5)),"") -> 5 | K5: =IFERROR(INDEX('Input Statistiche 2025_26'!$I$3:$I$665,MATCH($A5,'Input Statistiche 2025_26'!$A$3:$A$665,0)),"") -> 12 | L5: =IFERROR(INDEX('Input Statistiche 2025_26'!$O$3:$O$665,MATCH($A5,'Input Statistiche 2025_26'!$A$3:$A$665,0)),"") -> 5 | N5: =IFERROR(INDEX('Input Giocatori 2026_27'!$E$3:$E$493,MATCH($A5,'Input Giocatori 2026_27'!$A$3:$A$493,0)),"") -> 28 | O5: =IFERROR(INDEX('Input Giocatori 2026_27'!$G$3:$G$493,MATCH($A5,'Input Giocatori 2026_27'!$A$3:$A$493,0)),"") -> 271 | P5: =IFERROR(IF($O5="","",IF((1-(COUNTIFS($B$2:$B$492,$B5,$O$2:$O$492,">"&$O5)+1-1)/COUNTIF($B$2:$B$492,$B5))>='Parametri Modello'!$B$63,"Top",IF((1-(COUNTIFS($B$2:$B$492,$B5,$O$2:$O$492,">"&$O5)+1-1)/COUNTIF($B$2:$B$492,$B5))>='Parametri Modello'!$B$64,"Buono",IF((1-(COUNTIFS($B$2:$B$492,$B5,$O$2:$O$492,">"&$O5)+1-1)/COUNTIF($B$2:$B$492,$B5))>='Parametri Modello'!$B$65,"Nella Media","Scommessa/Riserva")))),"") -> Top | Q5: =IF(AND($D5="",$N5>1),SUMPRODUCT(($D$2:$D5="")*($N$2:$N5>1)),"") -> 4 | R5: =IF($D5='Info Lega'!$B$28,COUNTIFS($D$2:$D5,'Info Lega'!$B$28),"") | S5: =IFERROR(INDEX('Input Statistiche 2025_26'!$G$3:$G$665,MATCH($A5,'Input Statistiche 2025_26'!$A$3:$A$665,0)),"") -> 6.21 | T5: =IFERROR(INDEX('Input Statistiche 2025_26'!$H$3:$H$665,MATCH($A5,'Input Statistiche 2025_26'!$A$3:$A$665,0)),"") -> 7.44 | U5: =IF(OR('La Mia Rosa'!$O$12="",$D5<>""),"",IF($F5<='La Mia Rosa'!$O$12*'Parametri Modello'!$B$24,"OK",IF($F5<='La Mia Rosa'!$O$12*'Parametri Modello'!$B$25,"Attenzione","Rischio Alto"))) -> Rischio Alto | V5: =IFERROR(COUNTIFS($B$2:$B$492,$B5,$O$2:$O$492,">"&$O5)+1,"") -> 4 | W5: ='Info Lega'!$B$4-SUMIFS($M$2:$M$492,$D$2:$D$492,'Info Lega'!$B$28) -> 1000 | X5: =('Info Lega'!$B$5-COUNTIFS($D$2:$D$492,'Info Lega'!$B$28,$B$2:$B$492,"P"))+('Info Lega'!$B$6-COUNTIFS($D$2:$D$492,'Info Lega'!$B$28,$B$2:$B$492,"D"))+('Info Lega'!$B$7-COUNTIFS($D$2:$D$492,'Info Lega'!$B$28,$B$2:$B$492,"C"))+('Info Lega'!$B$8-COUNTIFS($D$2:$D$492,'Info Lega'!$B$28,$B$2:$B$492,"A")) -> 25 | Y5: =X5*'Parametri Modello'!$B$30 -> 25 | Z5: =MAX(0,W5-Y5) -> 975 | AA5: =MIN(F5,Z5) -> 284 | AC5: =IF($AB5="","",IF($AB5>$AA5,"PASS",IF($AB5<=$AA5*(1-'Parametri Modello'!$B$68),"BID","ATTENZIONE"))) | AD5: =IF(I5="","",ROUND(100*(1-EXP(-I5/30)),0)) -> 67 | AE5: =IFERROR(INDEX('Stato Asta'!$G$9:$G$12,MATCH($B5,'Stato Asta'!$A$9:$A$12,0)),"") -> 🔴 Non aspettare | AF5: =IFERROR(IF($V5<=INDEX('Parametri Modello'!$C$57:$C$60,MATCH($B5,'Parametri Modello'!$A$57:$A$60,0)),"Titolare","Riserva"),"") -> Titolare | AG5: =IFERROR(INDEX('Pressione Competitiva'!$F$3:$F$6,MATCH($B5,'Pressione Competitiva'!$B$3:$B$6,0)),"") -> 🔴 Molto Alta | AH5: =IF($AB5="","",$AA5-$AB5) | AI5: =IFERROR(IF($AH5="","",IF($AH5>=$AA5*'Parametri Modello'!$B$68,"🟢 Opportunita'",IF($AH5<=$AA5*'Parametri Modello'!$B$69,"🔴 Sovrapprezzo","🟡 Prezzo Corretto"))),"") | AJ5: =IF($AB5="","",IF($AC5="PASS","Prezzo sopra la tua Offerta Max Dinamica ("&$AA5&" cr).",IF($AC5="BID","Margine ampio sul tuo tetto (+"&($AA5-$AB5)&" cr).","Margine ridotto: sei vicino al tuo tetto ("&($AA5-$AB5)&" cr residui)."))) | AK5: =IF(AND($D5="",$N5>1),COUNTIFS($B$2:$B$492,$B5,$P$2:$P$492,$P5,$D$2:$D$492,"",$N$2:$N$492,">1",$O$2:$O$492,">"&$O5)+1,"") -> 4 | AL5: =IF($AK5="","",$B5&"|"&$P5&"|"&$AK5) -> A|Top|4
A6: 254 | B6: D | C6: Dimarco | E6: =IF(COUNTIF('Info Strategia'!$D$2:$D$51,$C6)>0,"SI","NO") -> NO | F6: =IFERROR(ROUND(($G6+($H6-$G6)*'Info Strategia'!$B$6)*(1+IF($E6="SI",'Parametri Modello'!$B$7*'Info Strategia'!$B$6,0)),0),"") -> 190 | G6: =IFERROR(ROUND(MAX(1,(IF($V6<=INDEX('Parametri Modello'!$C$57:$C$60,MATCH($B6,'Parametri Modello'!$A$57:$A$60,0)),IF(INDEX('Parametri Modello'!$E$57:$E$60,MATCH($B6,'Parametri Modello'!$A$57:$A$60,0))=0,0,($O6/INDEX('Parametri Modello'!$E$57:$E$60,MATCH($B6,'Parametri Modello'!$A$57:$A$60,0)))*(INDEX('Parametri Modello'!$D$57:$D$60,MATCH($B6,'Parametri Modello'!$A$57:$A$60,0))*(INDEX('Parametri Modello'!$B$50:$B$53,MATCH($B6,'Parametri Modello'!$A$50:$A$53,0))*'Parametri Modello'!$B$44))),IF(INDEX('Parametri Modello'!$F$57:$F$60,MATCH($B6,'Parametri Modello'!$A$57:$A$60,0))=0,0,($O6/INDEX('Parametri Modello'!$F$57:$F$60,MATCH($B6,'Parametri Modello'!$A$57:$A$60,0)))*((1-INDEX('Parametri Modello'!$D$57:$D$60,MATCH($B6,'Parametri Modello'!$A$57:$A$60,0)))*(INDEX('Parametri Modello'!$B$50:$B$53,MATCH($B6,'Parametri Modello'!$A$50:$A$53,0))*'Parametri Modello'!$B$44))))*(1+IF(IF($B6="D",'Info Lega'!$B$25,IF($B6="C",'Info Lega'!$B$26,"No"))="Si",'Parametri Modello'!$B$5,0))*(1+MAX(-0.25,MIN(0.25,IF(OR($T6="",$I6="",$I6=0,INDEX('Parametri Modello'!$B$19:$B$22,MATCH($B6,'Parametri Modello'!$A$19:$A$22,0))="",INDEX('Parametri Modello'!$B$19:$B$22,MATCH($B6,'Parametri Modello'!$A$19:$A$22,0))=0),0,(($T6-INDEX('Parametri Modello'!$B$19:$B$22,MATCH($B6,'Parametri Modello'!$A$19:$A$22,0)))/INDEX('Parametri Modello'!$B$19:$B$22,MATCH($B6,'Parametri Modello'!$A$19:$A$22,0)))*'Parametri Modello'!$B$9))))*(1+IF('Parametri Modello'!$B$27="Si",MAX(-'Parametri Modello'!$B$28,MIN('Parametri Modello'!$B$28*1.5,IF(OR(INDEX('Parametri Modello'!$F$32:$F$35,MATCH($B6,'Parametri Modello'!$A$32:$A$35,0))="",INDEX('Parametri Modello'!$F$32:$F$35,MATCH($B6,'Parametri Modello'!$A$32:$A$35,0))=0),0,(1/INDEX('Parametri Modello'!$F$32:$F$35,MATCH($B6,'Parametri Modello'!$A$32:$A$35,0))-1)*'Parametri Modello'!$B$28))),0)))*(1-INDEX('Parametri Modello'!$B$12:$B$15,MATCH($B6,'Parametri Modello'!$A$12:$A$15,0)))),0),"") -> 141 | H6: =IFERROR(ROUND((IF($V6<=INDEX('Parametri Modello'!$C$57:$C$60,MATCH($B6,'Parametri Modello'!$A$57:$A$60,0)),IF(INDEX('Parametri Modello'!$E$57:$E$60,MATCH($B6,'Parametri Modello'!$A$57:$A$60,0))=0,0,($O6/INDEX('Parametri Modello'!$E$57:$E$60,MATCH($B6,'Parametri Modello'!$A$57:$A$60,0)))*(INDEX('Parametri Modello'!$D$57:$D$60,MATCH($B6,'Parametri Modello'!$A$57:$A$60,0))*(INDEX('Parametri Modello'!$B$50:$B$53,MATCH($B6,'Parametri Modello'!$A$50:$A$53,0))*'Parametri Modello'!$B$44))),IF(INDEX('Parametri Modello'!$F$57:$F$60,MATCH($B6,'Parametri Modello'!$A$57:$A$60,0))=0,0,($O6/INDEX('Parametri Modello'!$F$57:$F$60,MATCH($B6,'Parametri Modello'!$A$57:$A$60,0)))*((1-INDEX('Parametri Modello'!$D$57:$D$60,MATCH($B6,'Parametri Modello'!$A$57:$A$60,0)))*(INDEX('Parametri Modello'!$B$50:$B$53,MATCH($B6,'Parametri Modello'!$A$50:$A$53,0))*'Parametri Modello'!$B$44))))*(1+IF(IF($B6="D",'Info Lega'!$B$25,IF($B6="C",'Info Lega'!$B$26,"No"))="Si",'Parametri Modello'!$B$5,0))*(1+MAX(-0.25,MIN(0.25,IF(OR($T6="",$I6="",$I6=0,INDEX('Parametri Modello'!$B$19:$B$22,MATCH($B6,'Parametri Modello'!$A$19:$A$22,0))="",INDEX('Parametri Modello'!$B$19:$B$22,MATCH($B6,'Parametri Modello'!$A$19:$A$22,0))=0),0,(($T6-INDEX('Parametri Modello'!$B$19:$B$22,MATCH($B6,'Parametri Modello'!$A$19:$A$22,0)))/INDEX('Parametri Modello'!$B$19:$B$22,MATCH($B6,'Parametri Modello'!$A$19:$A$22,0)))*'Parametri Modello'!$B$9))))*(1+IF('Parametri Modello'!$B$27="Si",MAX(-'Parametri Modello'!$B$28,MIN('Parametri Modello'!$B$28*1.5,IF(OR(INDEX('Parametri Modello'!$F$32:$F$35,MATCH($B6,'Parametri Modello'!$A$32:$A$35,0))="",INDEX('Parametri Modello'!$F$32:$F$35,MATCH($B6,'Parametri Modello'!$A$32:$A$35,0))=0),0,(1/INDEX('Parametri Modello'!$F$32:$F$35,MATCH($B6,'Parametri Modello'!$A$32:$A$35,0))-1)*'Parametri Modello'!$B$28))),0)))*(1+INDEX('Parametri Modello'!$B$12:$B$15,MATCH($B6,'Parametri Modello'!$A$12:$A$15,0))),0),"") -> 211 | I6: =IFERROR(INDEX('Input Statistiche 2025_26'!$F$3:$F$665,MATCH($A6,'Input Statistiche 2025_26'!$A$3:$A$665,0)),"") -> 35 | J6: =IFERROR(IF($I6="","",MAX(0,38-$I6)),"") -> 3 | K6: =IFERROR(INDEX('Input Statistiche 2025_26'!$I$3:$I$665,MATCH($A6,'Input Statistiche 2025_26'!$A$3:$A$665,0)),"") -> 7 | L6: =IFERROR(INDEX('Input Statistiche 2025_26'!$O$3:$O$665,MATCH($A6,'Input Statistiche 2025_26'!$A$3:$A$665,0)),"") -> 17 | N6: =IFERROR(INDEX('Input Giocatori 2026_27'!$E$3:$E$493,MATCH($A6,'Input Giocatori 2026_27'!$A$3:$A$493,0)),"") -> 32 | O6: =IFERROR(INDEX('Input Giocatori 2026_27'!$G$3:$G$493,MATCH($A6,'Input Giocatori 2026_27'!$A$3:$A$493,0)),"") -> 265 | P6: =IFERROR(IF($O6="","",IF((1-(COUNTIFS($B$2:$B$492,$B6,$O$2:$O$492,">"&$O6)+1-1)/COUNTIF($B$2:$B$492,$B6))>='Parametri Modello'!$B$63,"Top",IF((1-(COUNTIFS($B$2:$B$492,$B6,$O$2:$O$492,">"&$O6)+1-1)/COUNTIF($B$2:$B$492,$B6))>='Parametri Modello'!$B$64,"Buono",IF((1-(COUNTIFS($B$2:$B$492,$B6,$O$2:$O$492,">"&$O6)+1-1)/COUNTIF($B$2:$B$492,$B6))>='Parametri Modello'!$B$65,"Nella Media","Scommessa/Riserva")))),"") -> Top | Q6: =IF(AND($D6="",$N6>1),SUMPRODUCT(($D$2:$D6="")*($N$2:$N6>1)),"") -> 5 | R6: =IF($D6='Info Lega'!$B$28,COUNTIFS($D$2:$D6,'Info Lega'!$B$28),"") | S6: =IFERROR(INDEX('Input Statistiche 2025_26'!$G$3:$G$665,MATCH($A6,'Input Statistiche 2025_26'!$A$3:$A$665,0)),"") -> 6.6 | T6: =IFERROR(INDEX('Input Statistiche 2025_26'!$H$3:$H$665,MATCH($A6,'Input Statistiche 2025_26'!$A$3:$A$665,0)),"") -> 7.64 | U6: =IF(OR('La Mia Rosa'!$O$12="",$D6<>""),"",IF($F6<='La Mia Rosa'!$O$12*'Parametri Modello'!$B$24,"OK",IF($F6<='La Mia Rosa'!$O$12*'Parametri Modello'!$B$25,"Attenzione","Rischio Alto"))) -> Rischio Alto | V6: =IFERROR(COUNTIFS($B$2:$B$492,$B6,$O$2:$O$492,">"&$O6)+1,"") -> 1 | W6: ='Info Lega'!$B$4-SUMIFS($M$2:$M$492,$D$2:$D$492,'Info Lega'!$B$28) -> 1000 | X6: =('Info Lega'!$B$5-COUNTIFS($D$2:$D$492,'Info Lega'!$B$28,$B$2:$B$492,"P"))+('Info Lega'!$B$6-COUNTIFS($D$2:$D$492,'Info Lega'!$B$28,$B$2:$B$492,"D"))+('Info Lega'!$B$7-COUNTIFS($D$2:$D$492,'Info Lega'!$B$28,$B$2:$B$492,"C"))+('Info Lega'!$B$8-COUNTIFS($D$2:$D$492,'Info Lega'!$B$28,$B$2:$B$492,"A")) -> 25 | Y6: =X6*'Parametri Modello'!$B$30 -> 25 | Z6: =MAX(0,W6-Y6) -> 975 | AA6: =MIN(F6,Z6) -> 190 | AC6: =IF($AB6="","",IF($AB6>$AA6,"PASS",IF($AB6<=$AA6*(1-'Parametri Modello'!$B$68),"BID","ATTENZIONE"))) | AD6: =IF(I6="","",ROUND(100*(1-EXP(-I6/30)),0)) -> 69 | AE6: =IFERROR(INDEX('Stato Asta'!$G$9:$G$12,MATCH($B6,'Stato Asta'!$A$9:$A$12,0)),"") -> 🔴 Non aspettare | AF6: =IFERROR(IF($V6<=INDEX('Parametri Modello'!$C$57:$C$60,MATCH($B6,'Parametri Modello'!$A$57:$A$60,0)),"Titolare","Riserva"),"") -> Titolare | AG6: =IFERROR(INDEX('Pressione Competitiva'!$F$3:$F$6,MATCH($B6,'Pressione Competitiva'!$B$3:$B$6,0)),"") -> 🔴 Molto Alta | AH6: =IF($AB6="","",$AA6-$AB6) | AI6: =IFERROR(IF($AH6="","",IF($AH6>=$AA6*'Parametri Modello'!$B$68,"🟢 Opportunita'",IF($AH6<=$AA6*'Parametri Modello'!$B$69,"🔴 Sovrapprezzo","🟡 Prezzo Corretto"))),"") | AJ6: =IF($AB6="","",IF($AC6="PASS","Prezzo sopra la tua Offerta Max Dinamica ("&$AA6&" cr).",IF($AC6="BID","Margine ampio sul tuo tetto (+"&($AA6-$AB6)&" cr).","Margine ridotto: sei vicino al tuo tetto ("&($AA6-$AB6)&" cr residui)."))) | AK6: =IF(AND($D6="",$N6>1),COUNTIFS($B$2:$B$492,$B6,$P$2:$P$492,$P6,$D$2:$D$492,"",$N$2:$N$492,">1",$O$2:$O$492,">"&$O6)+1,"") -> 1 | AL6: =IF($AK6="","",$B6&"|"&$P6&"|"&$AK6) -> D|Top|1
A7: 6875 | B7: C | C7: Paz N. | E7: =IF(COUNTIF('Info Strategia'!$D$2:$D$51,$C7)>0,"SI","NO") -> NO | F7: =IFERROR(ROUND(($G7+($H7-$G7)*'Info Strategia'!$B$6)*(1+IF($E7="SI",'Parametri Modello'!$B$7*'Info Strategia'!$B$6,0)),0),"") -> 171 | G7: =IFERROR(ROUND(MAX(1,(IF($V7<=INDEX('Parametri Modello'!$C$57:$C$60,MATCH($B7,'Parametri Modello'!$A$57:$A$60,0)),IF(INDEX('Parametri Modello'!$E$57:$E$60,MATCH($B7,'Parametri Modello'!$A$57:$A$60,0))=0,0,($O7/INDEX('Parametri Modello'!$E$57:$E$60,MATCH($B7,'Parametri Modello'!$A$57:$A$60,0)))*(INDEX('Parametri Modello'!$D$57:$D$60,MATCH($B7,'Parametri Modello'!$A$57:$A$60,0))*(INDEX('Parametri Modello'!$B$50:$B$53,MATCH($B7,'Parametri Modello'!$A$50:$A$53,0))*'Parametri Modello'!$B$44))),IF(INDEX('Parametri Modello'!$F$57:$F$60,MATCH($B7,'Parametri Modello'!$A$57:$A$60,0))=0,0,($O7/INDEX('Parametri Modello'!$F$57:$F$60,MATCH($B7,'Parametri Modello'!$A$57:$A$60,0)))*((1-INDEX('Parametri Modello'!$D$57:$D$60,MATCH($B7,'Parametri Modello'!$A$57:$A$60,0)))*(INDEX('Parametri Modello'!$B$50:$B$53,MATCH($B7,'Parametri Modello'!$A$50:$A$53,0))*'Parametri Modello'!$B$44))))*(1+IF(IF($B7="D",'Info Lega'!$B$25,IF($B7="C",'Info Lega'!$B$26,"No"))="Si",'Parametri Modello'!$B$5,0))*(1+MAX(-0.25,MIN(0.25,IF(OR($T7="",$I7="",$I7=0,INDEX('Parametri Modello'!$B$19:$B$22,MATCH($B7,'Parametri Modello'!$A$19:$A$22,0))="",INDEX('Parametri Modello'!$B$19:$B$22,MATCH($B7,'Parametri Modello'!$A$19:$A$22,0))=0),0,(($T7-INDEX('Parametri Modello'!$B$19:$B$22,MATCH($B7,'Parametri Modello'!$A$19:$A$22,0)))/INDEX('Parametri Modello'!$B$19:$B$22,MATCH($B7,'Parametri Modello'!$A$19:$A$22,0)))*'Parametri Modello'!$B$9))))*(1+IF('Parametri Modello'!$B$27="Si",MAX(-'Parametri Modello'!$B$28,MIN('Parametri Modello'!$B$28*1.5,IF(OR(INDEX('Parametri Modello'!$F$32:$F$35,MATCH($B7,'Parametri Modello'!$A$32:$A$35,0))="",INDEX('Parametri Modello'!$F$32:$F$35,MATCH($B7,'Parametri Modello'!$A$32:$A$35,0))=0),0,(1/INDEX('Parametri Modello'!$F$32:$F$35,MATCH($B7,'Parametri Modello'!$A$32:$A$35,0))-1)*'Parametri Modello'!$B$28))),0)))*(1-INDEX('Parametri Modello'!$B$12:$B$15,MATCH($B7,'Parametri Modello'!$A$12:$A$15,0)))),0),"") -> 116 | H7: =IFERROR(ROUND((IF($V7<=INDEX('Parametri Modello'!$C$57:$C$60,MATCH($B7,'Parametri Modello'!$A$57:$A$60,0)),IF(INDEX('Parametri Modello'!$E$57:$E$60,MATCH($B7,'Parametri Modello'!$A$57:$A$60,0))=0,0,($O7/INDEX('Parametri Modello'!$E$57:$E$60,MATCH($B7,'Parametri Modello'!$A$57:$A$60,0)))*(INDEX('Parametri Modello'!$D$57:$D$60,MATCH($B7,'Parametri Modello'!$A$57:$A$60,0))*(INDEX('Parametri Modello'!$B$50:$B$53,MATCH($B7,'Parametri Modello'!$A$50:$A$53,0))*'Parametri Modello'!$B$44))),IF(INDEX('Parametri Modello'!$F$57:$F$60,MATCH($B7,'Parametri Modello'!$A$57:$A$60,0))=0,0,($O7/INDEX('Parametri Modello'!$F$57:$F$60,MATCH($B7,'Parametri Modello'!$A$57:$A$60,0)))*((1-INDEX('Parametri Modello'!$D$57:$D$60,MATCH($B7,'Parametri Modello'!$A$57:$A$60,0)))*(INDEX('Parametri Modello'!$B$50:$B$53,MATCH($B7,'Parametri Modello'!$A$50:$A$53,0))*'Parametri Modello'!$B$44))))*(1+IF(IF($B7="D",'Info Lega'!$B$25,IF($B7="C",'Info Lega'!$B$26,"No"))="Si",'Parametri Modello'!$B$5,0))*(1+MAX(-0.25,MIN(0.25,IF(OR($T7="",$I7="",$I7=0,INDEX('Parametri Modello'!$B$19:$B$22,MATCH($B7,'Parametri Modello'!$A$19:$A$22,0))="",INDEX('Parametri Modello'!$B$19:$B$22,MATCH($B7,'Parametri Modello'!$A$19:$A$22,0))=0),0,(($T7-INDEX('Parametri Modello'!$B$19:$B$22,MATCH($B7,'Parametri Modello'!$A$19:$A$22,0)))/INDEX('Parametri Modello'!$B$19:$B$22,MATCH($B7,'Parametri Modello'!$A$19:$A$22,0)))*'Parametri Modello'!$B$9))))*(1+IF('Parametri Modello'!$B$27="Si",MAX(-'Parametri Modello'!$B$28,MIN('Parametri Modello'!$B$28*1.5,IF(OR(INDEX('Parametri Modello'!$F$32:$F$35,MATCH($B7,'Parametri Modello'!$A$32:$A$35,0))="",INDEX('Parametri Modello'!$F$32:$F$35,MATCH($B7,'Parametri Modello'!$A$32:$A$35,0))=0),0,(1/INDEX('Parametri Modello'!$F$32:$F$35,MATCH($B7,'Parametri Modello'!$A$32:$A$35,0))-1)*'Parametri Modello'!$B$28))),0)))*(1+INDEX('Parametri Modello'!$B$12:$B$15,MATCH($B7,'Parametri Modello'!$A$12:$A$15,0))),0),"") -> 194 | I7: =IFERROR(INDEX('Input Statistiche 2025_26'!$F$3:$F$665,MATCH($A7,'Input Statistiche 2025_26'!$A$3:$A$665,0)),"") -> 35 | J7: =IFERROR(IF($I7="","",MAX(0,38-$I7)),"") -> 3 | K7: =IFERROR(INDEX('Input Statistiche 2025_26'!$I$3:$I$665,MATCH($A7,'Input Statistiche 2025_26'!$A$3:$A$665,0)),"") -> 12 | L7: =IFERROR(INDEX('Input Statistiche 2025_26'!$O$3:$O$665,MATCH($A7,'Input Statistiche 2025_26'!$A$3:$A$665,0)),"") -> 5 | N7: =IFERROR(INDEX('Input Giocatori 2026_27'!$E$3:$E$493,MATCH($A7,'Input Giocatori 2026_27'!$A$3:$A$493,0)),"") -> 30 | O7: =IFERROR(INDEX('Input Giocatori 2026_27'!$G$3:$G$493,MATCH($A7,'Input Giocatori 2026_27'!$A$3:$A$493,0)),"") -> 250 | P7: =IFERROR(IF($O7="","",IF((1-(COUNTIFS($B$2:$B$492,$B7,$O$2:$O$492,">"&$O7)+1-1)/COUNTIF($B$2:$B$492,$B7))>='Parametri Modello'!$B$63,"Top",IF((1-(COUNTIFS($B$2:$B$492,$B7,$O$2:$O$492,">"&$O7)+1-1)/COUNTIF($B$2:$B$492,$B7))>='Parametri Modello'!$B$64,"Buono",IF((1-(COUNTIFS($B$2:$B$492,$B7,$O$2:$O$492,">"&$O7)+1-1)/COUNTIF($B$2:$B$492,$B7))>='Parametri Modello'!$B$65,"Nella Media","Scommessa/Riserva")))),"") -> Top | Q7: =IF(AND($D7="",$N7>1),SUMPRODUCT(($D$2:$D7="")*($N$2:$N7>1)),"") -> 6 | R7: =IF($D7='Info Lega'!$B$28,COUNTIFS($D$2:$D7,'Info Lega'!$B$28),"") | S7: =IFERROR(INDEX('Input Statistiche 2025_26'!$G$3:$G$665,MATCH($A7,'Input Statistiche 2025_26'!$A$3:$A$665,0)),"") -> 6.37 | T7: =IFERROR(INDEX('Input Statistiche 2025_26'!$H$3:$H$665,MATCH($A7,'Input Statistiche 2025_26'!$A$3:$A$665,0)),"") -> 7.3 | U7: =IF(OR('La Mia Rosa'!$O$12="",$D7<>""),"",IF($F7<='La Mia Rosa'!$O$12*'Parametri Modello'!$B$24,"OK",IF($F7<='La Mia Rosa'!$O$12*'Parametri Modello'!$B$25,"Attenzione","Rischio Alto"))) -> Rischio Alto | V7: =IFERROR(COUNTIFS($B$2:$B$492,$B7,$O$2:$O$492,">"&$O7)+1,"") -> 1 | W7: ='Info Lega'!$B$4-SUMIFS($M$2:$M$492,$D$2:$D$492,'Info Lega'!$B$28) -> 1000 | X7: =('Info Lega'!$B$5-COUNTIFS($D$2:$D$492,'Info Lega'!$B$28,$B$2:$B$492,"P"))+('Info Lega'!$B$6-COUNTIFS($D$2:$D$492,'Info Lega'!$B$28,$B$2:$B$492,"D"))+('Info Lega'!$B$7-COUNTIFS($D$2:$D$492,'Info Lega'!$B$28,$B$2:$B$492,"C"))+('Info Lega'!$B$8-COUNTIFS($D$2:$D$492,'Info Lega'!$B$28,$B$2:$B$492,"A")) -> 25 | Y7: =X7*'Parametri Modello'!$B$30 -> 25 | Z7: =MAX(0,W7-Y7) -> 975 | AA7: =MIN(F7,Z7) -> 171 | AC7: =IF($AB7="","",IF($AB7>$AA7,"PASS",IF($AB7<=$AA7*(1-'Parametri Modello'!$B$68),"BID","ATTENZIONE"))) | AD7: =IF(I7="","",ROUND(100*(1-EXP(-I7/30)),0)) -> 69 | AE7: =IFERROR(INDEX('Stato Asta'!$G$9:$G$12,MATCH($B7,'Stato Asta'!$A$9:$A$12,0)),"") -> 🔴 Non aspettare | AF7: =IFERROR(IF($V7<=INDEX('Parametri Modello'!$C$57:$C$60,MATCH($B7,'Parametri Modello'!$A$57:$A$60,0)),"Titolare","Riserva"),"") -> Titolare | AG7: =IFERROR(INDEX('Pressione Competitiva'!$F$3:$F$6,MATCH($B7,'Pressione Competitiva'!$B$3:$B$6,0)),"") -> 🔴 Molto Alta | AH7: =IF($AB7="","",$AA7-$AB7) | AI7: =IFERROR(IF($AH7="","",IF($AH7>=$AA7*'Parametri Modello'!$B$68,"🟢 Opportunita'",IF($AH7<=$AA7*'Parametri Modello'!$B$69,"🔴 Sovrapprezzo","🟡 Prezzo Corretto"))),"") | AJ7: =IF($AB7="","",IF($AC7="PASS","Prezzo sopra la tua Offerta Max Dinamica ("&$AA7&" cr).",IF($AC7="BID","Margine ampio sul tuo tetto (+"&($AA7-$AB7)&" cr).","Margine ridotto: sei vicino al tuo tetto ("&($AA7-$AB7)&" cr residui)."))) | AK7: =IF(AND($D7="",$N7>1),COUNTIFS($B$2:$B$492,$B7,$P$2:$P$492,$P7,$D$2:$D$492,"",$N$2:$N$492,">1",$O$2:$O$492,">"&$O7)+1,"") -> 1 | AL7: =IF($AK7="","",$B7&"|"&$P7&"|"&$AK7) -> C|Top|1
A8: 4777 | B8: C | C8: McTominay | E8: =IF(COUNTIF('Info Strategia'!$D$2:$D$51,$C8)>0,"SI","NO") -> NO | F8: =IFERROR(ROUND(($G8+($H8-$G8)*'Info Strategia'!$B$6)*(1+IF($E8="SI",'Parametri Modello'!$B$7*'Info Strategia'!$B$6,0)),0),"") -> 164 | G8: =IFERROR(ROUND(MAX(1,(IF($V8<=INDEX('Parametri Modello'!$C$57:$C$60,MATCH($B8,'Parametri Modello'!$A$57:$A$60,0)),IF(INDEX('Parametri Modello'!$E$57:$E$60,MATCH($B8,'Parametri Modello'!$A$57:$A$60,0))=0,0,($O8/INDEX('Parametri Modello'!$E$57:$E$60,MATCH($B8,'Parametri Modello'!$A$57:$A$60,0)))*(INDEX('Parametri Modello'!$D$57:$D$60,MATCH($B8,'Parametri Modello'!$A$57:$A$60,0))*(INDEX('Parametri Modello'!$B$50:$B$53,MATCH($B8,'Parametri Modello'!$A$50:$A$53,0))*'Parametri Modello'!$B$44))),IF(INDEX('Parametri Modello'!$F$57:$F$60,MATCH($B8,'Parametri Modello'!$A$57:$A$60,0))=0,0,($O8/INDEX('Parametri Modello'!$F$57:$F$60,MATCH($B8,'Parametri Modello'!$A$57:$A$60,0)))*((1-INDEX('Parametri Modello'!$D$57:$D$60,MATCH($B8,'Parametri Modello'!$A$57:$A$60,0)))*(INDEX('Parametri Modello'!$B$50:$B$53,MATCH($B8,'Parametri Modello'!$A$50:$A$53,0))*'Parametri Modello'!$B$44))))*(1+IF(IF($B8="D",'Info Lega'!$B$25,IF($B8="C",'Info Lega'!$B$26,"No"))="Si",'Parametri Modello'!$B$5,0))*(1+MAX(-0.25,MIN(0.25,IF(OR($T8="",$I8="",$I8=0,INDEX('Parametri Modello'!$B$19:$B$22,MATCH($B8,'Parametri Modello'!$A$19:$A$22,0))="",INDEX('Parametri Modello'!$B$19:$B$22,MATCH($B8,'Parametri Modello'!$A$19:$A$22,0))=0),0,(($T8-INDEX('Parametri Modello'!$B$19:$B$22,MATCH($B8,'Parametri Modello'!$A$19:$A$22,0)))/INDEX('Parametri Modello'!$B$19:$B$22,MATCH($B8,'Parametri Modello'!$A$19:$A$22,0)))*'Parametri Modello'!$B$9))))*(1+IF('Parametri Modello'!$B$27="Si",MAX(-'Parametri Modello'!$B$28,MIN('Parametri Modello'!$B$28*1.5,IF(OR(INDEX('Parametri Modello'!$F$32:$F$35,MATCH($B8,'Parametri Modello'!$A$32:$A$35,0))="",INDEX('Parametri Modello'!$F$32:$F$35,MATCH($B8,'Parametri Modello'!$A$32:$A$35,0))=0),0,(1/INDEX('Parametri Modello'!$F$32:$F$35,MATCH($B8,'Parametri Modello'!$A$32:$A$35,0))-1)*'Parametri Modello'!$B$28))),0)))*(1-INDEX('Parametri Modello'!$B$12:$B$15,MATCH($B8,'Parametri Modello'!$A$12:$A$15,0)))),0),"") -> 112 | H8: =IFERROR(ROUND((IF($V8<=INDEX('Parametri Modello'!$C$57:$C$60,MATCH($B8,'Parametri Modello'!$A$57:$A$60,0)),IF(INDEX('Parametri Modello'!$E$57:$E$60,MATCH($B8,'Parametri Modello'!$A$57:$A$60,0))=0,0,($O8/INDEX('Parametri Modello'!$E$57:$E$60,MATCH($B8,'Parametri Modello'!$A$57:$A$60,0)))*(INDEX('Parametri Modello'!$D$57:$D$60,MATCH($B8,'Parametri Modello'!$A$57:$A$60,0))*(INDEX('Parametri Modello'!$B$50:$B$53,MATCH($B8,'Parametri Modello'!$A$50:$A$53,0))*'Parametri Modello'!$B$44))),IF(INDEX('Parametri Modello'!$F$57:$F$60,MATCH($B8,'Parametri Modello'!$A$57:$A$60,0))=0,0,($O8/INDEX('Parametri Modello'!$F$57:$F$60,MATCH($B8,'Parametri Modello'!$A$57:$A$60,0)))*((1-INDEX('Parametri Modello'!$D$57:$D$60,MATCH($B8,'Parametri Modello'!$A$57:$A$60,0)))*(INDEX('Parametri Modello'!$B$50:$B$53,MATCH($B8,'Parametri Modello'!$A$50:$A$53,0))*'Parametri Modello'!$B$44))))*(1+IF(IF($B8="D",'Info Lega'!$B$25,IF($B8="C",'Info Lega'!$B$26,"No"))="Si",'Parametri Modello'!$B$5,0))*(1+MAX(-0.25,MIN(0.25,IF(OR($T8="",$I8="",$I8=0,INDEX('Parametri Modello'!$B$19:$B$22,MATCH($B8,'Parametri Modello'!$A$19:$A$22,0))="",INDEX('Parametri Modello'!$B$19:$B$22,MATCH($B8,'Parametri Modello'!$A$19:$A$22,0))=0),0,(($T8-INDEX('Parametri Modello'!$B$19:$B$22,MATCH($B8,'Parametri Modello'!$A$19:$A$22,0)))/INDEX('Parametri Modello'!$B$19:$B$22,MATCH($B8,'Parametri Modello'!$A$19:$A$22,0)))*'Parametri Modello'!$B$9))))*(1+IF('Parametri Modello'!$B$27="Si",MAX(-'Parametri Modello'!$B$28,MIN('Parametri Modello'!$B$28*1.5,IF(OR(INDEX('Parametri Modello'!$F$32:$F$35,MATCH($B8,'Parametri Modello'!$A$32:$A$35,0))="",INDEX('Parametri Modello'!$F$32:$F$35,MATCH($B8,'Parametri Modello'!$A$32:$A$35,0))=0),0,(1/INDEX('Parametri Modello'!$F$32:$F$35,MATCH($B8,'Parametri Modello'!$A$32:$A$35,0))-1)*'Parametri Modello'!$B$28))),0)))*(1+INDEX('Parametri Modello'!$B$12:$B$15,MATCH($B8,'Parametri Modello'!$A$12:$A$15,0))),0),"") -> 186 | I8: =IFERROR(INDEX('Input Statistiche 2025_26'!$F$3:$F$665,MATCH($A8,'Input Statistiche 2025_26'!$A$3:$A$665,0)),"") -> 33 | J8: =IFERROR(IF($I8="","",MAX(0,38-$I8)),"") -> 5 | K8: =IFERROR(INDEX('Input Statistiche 2025_26'!$I$3:$I$665,MATCH($A8,'Input Statistiche 2025_26'!$A$3:$A$665,0)),"") -> 10 | L8: =IFERROR(INDEX('Input Statistiche 2025_26'!$O$3:$O$665,MATCH($A8,'Input Statistiche 2025_26'!$A$3:$A$665,0)),"") -> 2 | N8: =IFERROR(INDEX('Input Giocatori 2026_27'!$E$3:$E$493,MATCH($A8,'Input Giocatori 2026_27'!$A$3:$A$493,0)),"") -> 28 | O8: =IFERROR(INDEX('Input Giocatori 2026_27'!$G$3:$G$493,MATCH($A8,'Input Giocatori 2026_27'!$A$3:$A$493,0)),"") -> 240 | P8: =IFERROR(IF($O8="","",IF((1-(COUNTIFS($B$2:$B$492,$B8,$O$2:$O$492,">"&$O8)+1-1)/COUNTIF($B$2:$B$492,$B8))>='Parametri Modello'!$B$63,"Top",IF((1-(COUNTIFS($B$2:$B$492,$B8,$O$2:$O$492,">"&$O8)+1-1)/COUNTIF($B$2:$B$492,$B8))>='Parametri Modello'!$B$64,"Buono",IF((1-(COUNTIFS($B$2:$B$492,$B8,$O$2:$O$492,">"&$O8)+1-1)/COUNTIF($B$2:$B$492,$B8))>='Parametri Modello'!$B$65,"Nella Media","Scommessa/Riserva")))),"") -> Top | Q8: =IF(AND($D8="",$N8>1),SUMPRODUCT(($D$2:$D8="")*($N$2:$N8>1)),"") -> 7 | R8: =IF($D8='Info Lega'!$B$28,COUNTIFS($D$2:$D8,'Info Lega'!$B$28),"") | S8: =IFERROR(INDEX('Input Statistiche 2025_26'!$G$3:$G$665,MATCH($A8,'Input Statistiche 2025_26'!$A$3:$A$665,0)),"") -> 6.39 | T8: =IFERROR(INDEX('Input Statistiche 2025_26'!$H$3:$H$665,MATCH($A8,'Input Statistiche 2025_26'!$A$3:$A$665,0)),"") -> 7.26 | U8: =IF(OR('La Mia Rosa'!$O$12="",$D8<>""),"",IF($F8<='La Mia Rosa'!$O$12*'Parametri Modello'!$B$24,"OK",IF($F8<='La Mia Rosa'!$O$12*'Parametri Modello'!$B$25,"Attenzione","Rischio Alto"))) -> Rischio Alto | V8: =IFERROR(COUNTIFS($B$2:$B$492,$B8,$O$2:$O$492,">"&$O8)+1,"") -> 2 | W8: ='Info Lega'!$B$4-SUMIFS($M$2:$M$492,$D$2:$D$492,'Info Lega'!$B$28) -> 1000 | X8: =('Info Lega'!$B$5-COUNTIFS($D$2:$D$492,'Info Lega'!$B$28,$B$2:$B$492,"P"))+('Info Lega'!$B$6-COUNTIFS($D$2:$D$492,'Info Lega'!$B$28,$B$2:$B$492,"D"))+('Info Lega'!$B$7-COUNTIFS($D$2:$D$492,'Info Lega'!$B$28,$B$2:$B$492,"C"))+('Info Lega'!$B$8-COUNTIFS($D$2:$D$492,'Info Lega'!$B$28,$B$2:$B$492,"A")) -> 25 | Y8: =X8*'Parametri Modello'!$B$30 -> 25 | Z8: =MAX(0,W8-Y8) -> 975 | AA8: =MIN(F8,Z8) -> 164 | AC8: =IF($AB8="","",IF($AB8>$AA8,"PASS",IF($AB8<=$AA8*(1-'Parametri Modello'!$B$68),"BID","ATTENZIONE"))) | AD8: =IF(I8="","",ROUND(100*(1-EXP(-I8/30)),0)) -> 67 | AE8: =IFERROR(INDEX('Stato Asta'!$G$9:$G$12,MATCH($B8,'Stato Asta'!$A$9:$A$12,0)),"") -> 🔴 Non aspettare | AF8: =IFERROR(IF($V8<=INDEX('Parametri Modello'!$C$57:$C$60,MATCH($B8,'Parametri Modello'!$A$57:$A$60,0)),"Titolare","Riserva"),"") -> Titolare | AG8: =IFERROR(INDEX('Pressione Competitiva'!$F$3:$F$6,MATCH($B8,'Pressione Competitiva'!$B$3:$B$6,0)),"") -> 🔴 Molto Alta | AH8: =IF($AB8="","",$AA8-$AB8) | AI8: =IFERROR(IF($AH8="","",IF($AH8>=$AA8*'Parametri Modello'!$B$68,"🟢 Opportunita'",IF($AH8<=$AA8*'Parametri Modello'!$B$69,"🔴 Sovrapprezzo","🟡 Prezzo Corretto"))),"") | AJ8: =IF($AB8="","",IF($AC8="PASS","Prezzo sopra la tua Offerta Max Dinamica ("&$AA8&" cr).",IF($AC8="BID","Margine ampio sul tuo tetto (+"&($AA8-$AB8)&" cr).","Margine ridotto: sei vicino al tuo tetto ("&($AA8-$AB8)&" cr residui)."))) | AK8: =IF(AND($D8="",$N8>1),COUNTIFS($B$2:$B$492,$B8,$P$2:$P$492,$P8,$D$2:$D$492,"",$N$2:$N$492,">1",$O$2:$O$492,">"&$O8)+1,"") -> 2 | AL8: =IF($AK8="","",$B8&"|"&$P8&"|"&$AK8) -> C|Top|2
A9: 6397 | B9: A | C9: Ramos G. | E9: =IF(COUNTIF('Info Strategia'!$D$2:$D$51,$C9)>0,"SI","NO") -> NO | F9: =IFERROR(ROUND(($G9+($H9-$G9)*'Info Strategia'!$B$6)*(1+IF($E9="SI",'Parametri Modello'!$B$7*'Info Strategia'!$B$6,0)),0),"") -> 246 | G9: =IFERROR(ROUND(MAX(1,(IF($V9<=INDEX('Parametri Modello'!$C$57:$C$60,MATCH($B9,'Parametri Modello'!$A$57:$A$60,0)),IF(INDEX('Parametri Modello'!$E$57:$E$60,MATCH($B9,'Parametri Modello'!$A$57:$A$60,0))=0,0,($O9/INDEX('Parametri Modello'!$E$57:$E$60,MATCH($B9,'Parametri Modello'!$A$57:$A$60,0)))*(INDEX('Parametri Modello'!$D$57:$D$60,MATCH($B9,'Parametri Modello'!$A$57:$A$60,0))*(INDEX('Parametri Modello'!$B$50:$B$53,MATCH($B9,'Parametri Modello'!$A$50:$A$53,0))*'Parametri Modello'!$B$44))),IF(INDEX('Parametri Modello'!$F$57:$F$60,MATCH($B9,'Parametri Modello'!$A$57:$A$60,0))=0,0,($O9/INDEX('Parametri Modello'!$F$57:$F$60,MATCH($B9,'Parametri Modello'!$A$57:$A$60,0)))*((1-INDEX('Parametri Modello'!$D$57:$D$60,MATCH($B9,'Parametri Modello'!$A$57:$A$60,0)))*(INDEX('Parametri Modello'!$B$50:$B$53,MATCH($B9,'Parametri Modello'!$A$50:$A$53,0))*'Parametri Modello'!$B$44))))*(1+IF(IF($B9="D",'Info Lega'!$B$25,IF($B9="C",'Info Lega'!$B$26,"No"))="Si",'Parametri Modello'!$B$5,0))*(1+MAX(-0.25,MIN(0.25,IF(OR($T9="",$I9="",$I9=0,INDEX('Parametri Modello'!$B$19:$B$22,MATCH($B9,'Parametri Modello'!$A$19:$A$22,0))="",INDEX('Parametri Modello'!$B$19:$B$22,MATCH($B9,'Parametri Modello'!$A$19:$A$22,0))=0),0,(($T9-INDEX('Parametri Modello'!$B$19:$B$22,MATCH($B9,'Parametri Modello'!$A$19:$A$22,0)))/INDEX('Parametri Modello'!$B$19:$B$22,MATCH($B9,'Parametri Modello'!$A$19:$A$22,0)))*'Parametri Modello'!$B$9))))*(1+IF('Parametri Modello'!$B$27="Si",MAX(-'Parametri Modello'!$B$28,MIN('Parametri Modello'!$B$28*1.5,IF(OR(INDEX('Parametri Modello'!$F$32:$F$35,MATCH($B9,'Parametri Modello'!$A$32:$A$35,0))="",INDEX('Parametri Modello'!$F$32:$F$35,MATCH($B9,'Parametri Modello'!$A$32:$A$35,0))=0),0,(1/INDEX('Parametri Modello'!$F$32:$F$35,MATCH($B9,'Parametri Modello'!$A$32:$A$35,0))-1)*'Parametri Modello'!$B$28))),0)))*(1-INDEX('Parametri Modello'!$B$12:$B$15,MATCH($B9,'Parametri Modello'!$A$12:$A$15,0)))),0),"") -> 154 | H9: =IFERROR(ROUND((IF($V9<=INDEX('Parametri Modello'!$C$57:$C$60,MATCH($B9,'Parametri Modello'!$A$57:$A$60,0)),IF(INDEX('Parametri Modello'!$E$57:$E$60,MATCH($B9,'Parametri Modello'!$A$57:$A$60,0))=0,0,($O9/INDEX('Parametri Modello'!$E$57:$E$60,MATCH($B9,'Parametri Modello'!$A$57:$A$60,0)))*(INDEX('Parametri Modello'!$D$57:$D$60,MATCH($B9,'Parametri Modello'!$A$57:$A$60,0))*(INDEX('Parametri Modello'!$B$50:$B$53,MATCH($B9,'Parametri Modello'!$A$50:$A$53,0))*'Parametri Modello'!$B$44))),IF(INDEX('Parametri Modello'!$F$57:$F$60,MATCH($B9,'Parametri Modello'!$A$57:$A$60,0))=0,0,($O9/INDEX('Parametri Modello'!$F$57:$F$60,MATCH($B9,'Parametri Modello'!$A$57:$A$60,0)))*((1-INDEX('Parametri Modello'!$D$57:$D$60,MATCH($B9,'Parametri Modello'!$A$57:$A$60,0)))*(INDEX('Parametri Modello'!$B$50:$B$53,MATCH($B9,'Parametri Modello'!$A$50:$A$53,0))*'Parametri Modello'!$B$44))))*(1+IF(IF($B9="D",'Info Lega'!$B$25,IF($B9="C",'Info Lega'!$B$26,"No"))="Si",'Parametri Modello'!$B$5,0))*(1+MAX(-0.25,MIN(0.25,IF(OR($T9="",$I9="",$I9=0,INDEX('Parametri Modello'!$B$19:$B$22,MATCH($B9,'Parametri Modello'!$A$19:$A$22,0))="",INDEX('Parametri Modello'!$B$19:$B$22,MATCH($B9,'Parametri Modello'!$A$19:$A$22,0))=0),0,(($T9-INDEX('Parametri Modello'!$B$19:$B$22,MATCH($B9,'Parametri Modello'!$A$19:$A$22,0)))/INDEX('Parametri Modello'!$B$19:$B$22,MATCH($B9,'Parametri Modello'!$A$19:$A$22,0)))*'Parametri Modello'!$B$9))))*(1+IF('Parametri Modello'!$B$27="Si",MAX(-'Parametri Modello'!$B$28,MIN('Parametri Modello'!$B$28*1.5,IF(OR(INDEX('Parametri Modello'!$F$32:$F$35,MATCH($B9,'Parametri Modello'!$A$32:$A$35,0))="",INDEX('Parametri Modello'!$F$32:$F$35,MATCH($B9,'Parametri Modello'!$A$32:$A$35,0))=0),0,(1/INDEX('Parametri Modello'!$F$32:$F$35,MATCH($B9,'Parametri Modello'!$A$32:$A$35,0))-1)*'Parametri Modello'!$B$28))),0)))*(1+INDEX('Parametri Modello'!$B$12:$B$15,MATCH($B9,'Parametri Modello'!$A$12:$A$15,0))),0),"") -> 286 | I9: =IFERROR(INDEX('Input Statistiche 2025_26'!$F$3:$F$665,MATCH($A9,'Input Statistiche 2025_26'!$A$3:$A$665,0)),"") | J9: =IFERROR(IF($I9="","",MAX(0,38-$I9)),"") | K9: =IFERROR(INDEX('Input Statistiche 2025_26'!$I$3:$I$665,MATCH($A9,'Input Statistiche 2025_26'!$A$3:$A$665,0)),"") | L9: =IFERROR(INDEX('Input Statistiche 2025_26'!$O$3:$O$665,MATCH($A9,'Input Statistiche 2025_26'!$A$3:$A$665,0)),"") | N9: =IFERROR(INDEX('Input Giocatori 2026_27'!$E$3:$E$493,MATCH($A9,'Input Giocatori 2026_27'!$A$3:$A$493,0)),"") -> 27 | O9: =IFERROR(INDEX('Input Giocatori 2026_27'!$G$3:$G$493,MATCH($A9,'Input Giocatori 2026_27'!$A$3:$A$493,0)),"") -> 240 | P9: =IFERROR(IF($O9="","",IF((1-(COUNTIFS($B$2:$B$492,$B9,$O$2:$O$492,">"&$O9)+1-1)/COUNTIF($B$2:$B$492,$B9))>='Parametri Modello'!$B$63,"Top",IF((1-(COUNTIFS($B$2:$B$492,$B9,$O$2:$O$492,">"&$O9)+1-1)/COUNTIF($B$2:$B$492,$B9))>='Parametri Modello'!$B$64,"Buono",IF((1-(COUNTIFS($B$2:$B$492,$B9,$O$2:$O$492,">"&$O9)+1-1)/COUNTIF($B$2:$B$492,$B9))>='Parametri Modello'!$B$65,"Nella Media","Scommessa/Riserva")))),"") -> Top | Q9: =IF(AND($D9="",$N9>1),SUMPRODUCT(($D$2:$D9="")*($N$2:$N9>1)),"") -> 8 | R9: =IF($D9='Info Lega'!$B$28,COUNTIFS($D$2:$D9,'Info Lega'!$B$28),"") | S9: =IFERROR(INDEX('Input Statistiche 2025_26'!$G$3:$G$665,MATCH($A9,'Input Statistiche 2025_26'!$A$3:$A$665,0)),"") | T9: =IFERROR(INDEX('Input Statistiche 2025_26'!$H$3:$H$665,MATCH($A9,'Input Statistiche 2025_26'!$A$3:$A$665,0)),"") | U9: =IF(OR('La Mia Rosa'!$O$12="",$D9<>""),"",IF($F9<='La Mia Rosa'!$O$12*'Parametri Modello'!$B$24,"OK",IF($F9<='La Mia Rosa'!$O$12*'Parametri Modello'!$B$25,"Attenzione","Rischio Alto"))) -> Rischio Alto | V9: =IFERROR(COUNTIFS($B$2:$B$492,$B9,$O$2:$O$492,">"&$O9)+1,"") -> 5 | W9: ='Info Lega'!$B$4-SUMIFS($M$2:$M$492,$D$2:$D$492,'Info Lega'!$B$28) -> 1000 | X9: =('Info Lega'!$B$5-COUNTIFS($D$2:$D$492,'Info Lega'!$B$28,$B$2:$B$492,"P"))+('Info Lega'!$B$6-COUNTIFS($D$2:$D$492,'Info Lega'!$B$28,$B$2:$B$492,"D"))+('Info Lega'!$B$7-COUNTIFS($D$2:$D$492,'Info Lega'!$B$28,$B$2:$B$492,"C"))+('Info Lega'!$B$8-COUNTIFS($D$2:$D$492,'Info Lega'!$B$28,$B$2:$B$492,"A")) -> 25 | Y9: =X9*'Parametri Modello'!$B$30 -> 25 | Z9: =MAX(0,W9-Y9) -> 975 | AA9: =MIN(F9,Z9) -> 246 | AC9: =IF($AB9="","",IF($AB9>$AA9,"PASS",IF($AB9<=$AA9*(1-'Parametri Modello'!$B$68),"BID","ATTENZIONE"))) | AD9: =IF(I9="","",ROUND(100*(1-EXP(-I9/30)),0)) | AE9: =IFERROR(INDEX('Stato Asta'!$G$9:$G$12,MATCH($B9,'Stato Asta'!$A$9:$A$12,0)),"") -> 🔴 Non aspettare | AF9: =IFERROR(IF($V9<=INDEX('Parametri Modello'!$C$57:$C$60,MATCH($B9,'Parametri Modello'!$A$57:$A$60,0)),"Titolare","Riserva"),"") -> Titolare | AG9: =IFERROR(INDEX('Pressione Competitiva'!$F$3:$F$6,MATCH($B9,'Pressione Competitiva'!$B$3:$B$6,0)),"") -> 🔴 Molto Alta | AH9: =IF($AB9="","",$AA9-$AB9) | AI9: =IFERROR(IF($AH9="","",IF($AH9>=$AA9*'Parametri Modello'!$B$68,"🟢 Opportunita'",IF($AH9<=$AA9*'Parametri Modello'!$B$69,"🔴 Sovrapprezzo","🟡 Prezzo Corretto"))),"") | AJ9: =IF($AB9="","",IF($AC9="PASS","Prezzo sopra la tua Offerta Max Dinamica ("&$AA9&" cr).",IF($AC9="BID","Margine ampio sul tuo tetto (+"&($AA9-$AB9)&" cr).","Margine ridotto: sei vicino al tuo tetto ("&($AA9-$AB9)&" cr residui)."))) | AK9: =IF(AND($D9="",$N9>1),COUNTIFS($B$2:$B$492,$B9,$P$2:$P$492,$P9,$D$2:$D$492,"",$N$2:$N$492,">1",$O$2:$O$492,">"&$O9)+1,"") -> 5 | AL9: =IF($AK9="","",$B9&"|"&$P9&"|"&$AK9) -> A|Top|5
A10: 2194 | B10: C | C10: Calhanoglu | E10: =IF(COUNTIF('Info Strategia'!$D$2:$D$51,$C10)>0,"SI","NO") -> NO | F10: =IFERROR(ROUND(($G10+($H10-$G10)*'Info Strategia'!$B$6)*(1+IF($E10="SI",'Parametri Modello'!$B$7*'Info Strategia'!$B$6,0)),0),"") -> 158 | G10: =IFERROR(ROUND(MAX(1,(IF($V10<=INDEX('Parametri Modello'!$C$57:$C$60,MATCH($B10,'Parametri Modello'!$A$57:$A$60,0)),IF(INDEX('Parametri Modello'!$E$57:$E$60,MATCH($B10,'Parametri Modello'!$A$57:$A$60,0))=0,0,($O10/INDEX('Parametri Modello'!$E$57:$E$60,MATCH($B10,'Parametri Modello'!$A$57:$A$60,0)))*(INDEX('Parametri Modello'!$D$57:$D$60,MATCH($B10,'Parametri Modello'!$A$57:$A$60,0))*(INDEX('Parametri Modello'!$B$50:$B$53,MATCH($B10,'Parametri Modello'!$A$50:$A$53,0))*'Parametri Modello'!$B$44))),IF(INDEX('Parametri Modello'!$F$57:$F$60,MATCH($B10,'Parametri Modello'!$A$57:$A$60,0))=0,0,($O10/INDEX('Parametri Modello'!$F$57:$F$60,MATCH($B10,'Parametri Modello'!$A$57:$A$60,0)))*((1-INDEX('Parametri Modello'!$D$57:$D$60,MATCH($B10,'Parametri Modello'!$A$57:$A$60,0)))*(INDEX('Parametri Modello'!$B$50:$B$53,MATCH($B10,'Parametri Modello'!$A$50:$A$53,0))*'Parametri Modello'!$B$44))))*(1+IF(IF($B10="D",'Info Lega'!$B$25,IF($B10="C",'Info Lega'!$B$26,"No"))="Si",'Parametri Modello'!$B$5,0))*(1+MAX(-0.25,MIN(0.25,IF(OR($T10="",$I10="",$I10=0,INDEX('Parametri Modello'!$B$19:$B$22,MATCH($B10,'Parametri Modello'!$A$19:$A$22,0))="",INDEX('Parametri Modello'!$B$19:$B$22,MATCH($B10,'Parametri Modello'!$A$19:$A$22,0))=0),0,(($T10-INDEX('Parametri Modello'!$B$19:$B$22,MATCH($B10,'Parametri Modello'!$A$19:$A$22,0)))/INDEX('Parametri Modello'!$B$19:$B$22,MATCH($B10,'Parametri Modello'!$A$19:$A$22,0)))*'Parametri Modello'!$B$9))))*(1+IF('Parametri Modello'!$B$27="Si",MAX(-'Parametri Modello'!$B$28,MIN('Parametri Modello'!$B$28*1.5,IF(OR(INDEX('Parametri Modello'!$F$32:$F$35,MATCH($B10,'Parametri Modello'!$A$32:$A$35,0))="",INDEX('Parametri Modello'!$F$32:$F$35,MATCH($B10,'Parametri Modello'!$A$32:$A$35,0))=0),0,(1/INDEX('Parametri Modello'!$F$32:$F$35,MATCH($B10,'Parametri Modello'!$A$32:$A$35,0))-1)*'Parametri Modello'!$B$28))),0)))*(1-INDEX('Parametri Modello'!$B$12:$B$15,MATCH($B10,'Parametri Modello'!$A$12:$A$15,0)))),0),"") -> 108 | H10: =IFERROR(ROUND((IF($V10<=INDEX('Parametri Modello'!$C$57:$C$60,MATCH($B10,'Parametri Modello'!$A$57:$A$60,0)),IF(INDEX('Parametri Modello'!$E$57:$E$60,MATCH($B10,'Parametri Modello'!$A$57:$A$60,0))=0,0,($O10/INDEX('Parametri Modello'!$E$57:$E$60,MATCH($B10,'Parametri Modello'!$A$57:$A$60,0)))*(INDEX('Parametri Modello'!$D$57:$D$60,MATCH($B10,'Parametri Modello'!$A$57:$A$60,0))*(INDEX('Parametri Modello'!$B$50:$B$53,MATCH($B10,'Parametri Modello'!$A$50:$A$53,0))*'Parametri Modello'!$B$44))),IF(INDEX('Parametri Modello'!$F$57:$F$60,MATCH($B10,'Parametri Modello'!$A$57:$A$60,0))=0,0,($O10/INDEX('Parametri Modello'!$F$57:$F$60,MATCH($B10,'Parametri Modello'!$A$57:$A$60,0)))*((1-INDEX('Parametri Modello'!$D$57:$D$60,MATCH($B10,'Parametri Modello'!$A$57:$A$60,0)))*(INDEX('Parametri Modello'!$B$50:$B$53,MATCH($B10,'Parametri Modello'!$A$50:$A$53,0))*'Parametri Modello'!$B$44))))*(1+IF(IF($B10="D",'Info Lega'!$B$25,IF($B10="C",'Info Lega'!$B$26,"No"))="Si",'Parametri Modello'!$B$5,0))*(1+MAX(-0.25,MIN(0.25,IF(OR($T10="",$I10="",$I10=0,INDEX('Parametri Modello'!$B$19:$B$22,MATCH($B10,'Parametri Modello'!$A$19:$A$22,0))="",INDEX('Parametri Modello'!$B$19:$B$22,MATCH($B10,'Parametri Modello'!$A$19:$A$22,0))=0),0,(($T10-INDEX('Parametri Modello'!$B$19:$B$22,MATCH($B10,'Parametri Modello'!$A$19:$A$22,0)))/INDEX('Parametri Modello'!$B$19:$B$22,MATCH($B10,'Parametri Modello'!$A$19:$A$22,0)))*'Parametri Modello'!$B$9))))*(1+IF('Parametri Modello'!$B$27="Si",MAX(-'Parametri Modello'!$B$28,MIN('Parametri Modello'!$B$28*1.5,IF(OR(INDEX('Parametri Modello'!$F$32:$F$35,MATCH($B10,'Parametri Modello'!$A$32:$A$35,0))="",INDEX('Parametri Modello'!$F$32:$F$35,MATCH($B10,'Parametri Modello'!$A$32:$A$35,0))=0),0,(1/INDEX('Parametri Modello'!$F$32:$F$35,MATCH($B10,'Parametri Modello'!$A$32:$A$35,0))-1)*'Parametri Modello'!$B$28))),0)))*(1+INDEX('Parametri Modello'!$B$12:$B$15,MATCH($B10,'Parametri Modello'!$A$12:$A$15,0))),0),"") -> 180 | I10: =IFERROR(INDEX('Input Statistiche 2025_26'!$F$3:$F$665,MATCH($A10,'Input Statistiche 2025_26'!$A$3:$A$665,0)),"") -> 22 | J10: =IFERROR(IF($I10="","",MAX(0,38-$I10)),"") -> 16 | K10: =IFERROR(INDEX('Input Statistiche 2025_26'!$I$3:$I$665,MATCH($A10,'Input Statistiche 2025_26'!$A$3:$A$665,0)),"") -> 9 | L10: =IFERROR(INDEX('Input Statistiche 2025_26'!$O$3:$O$665,MATCH($A10,'Input Statistiche 2025_26'!$A$3:$A$665,0)),"") -> 4 | N10: =IFERROR(INDEX('Input Giocatori 2026_27'!$E$3:$E$493,MATCH($A10,'Input Giocatori 2026_27'!$A$3:$A$493,0)),"") -> 27 | O10: =IFERROR(INDEX('Input Giocatori 2026_27'!$G$3:$G$493,MATCH($A10,'Input Giocatori 2026_27'!$A$3:$A$493,0)),"") -> 230 | P10: =IFERROR(IF($O10="","",IF((1-(COUNTIFS($B$2:$B$492,$B10,$O$2:$O$492,">"&$O10)+1-1)/COUNTIF($B$2:$B$492,$B10))>='Parametri Modello'!$B$63,"Top",IF((1-(COUNTIFS($B$2:$B$492,$B10,$O$2:$O$492,">"&$O10)+1-1)/COUNTIF($B$2:$B$492,$B10))>='Parametri Modello'!$B$64,"Buono",IF((1-(COUNTIFS($B$2:$B$492,$B10,$O$2:$O$492,">"&$O10)+1-1)/COUNTIF($B$2:$B$492,$B10))>='Parametri Modello'!$B$65,"Nella Media","Scommessa/Riserva")))),"") -> Top | Q10: =IF(AND($D10="",$N10>1),SUMPRODUCT(($D$2:$D10="")*($N$2:$N10>1)),"") -> 9 | R10: =IF($D10='Info Lega'!$B$28,COUNTIFS($D$2:$D10,'Info Lega'!$B$28),"") | S10: =IFERROR(INDEX('Input Statistiche 2025_26'!$G$3:$G$665,MATCH($A10,'Input Statistiche 2025_26'!$A$3:$A$665,0)),"") -> 6.52 | T10: =IFERROR(INDEX('Input Statistiche 2025_26'!$H$3:$H$665,MATCH($A10,'Input Statistiche 2025_26'!$A$3:$A$665,0)),"") -> 7.64 | U10: =IF(OR('La Mia Rosa'!$O$12="",$D10<>""),"",IF($F10<='La Mia Rosa'!$O$12*'Parametri Modello'!$B$24,"OK",IF($F10<='La Mia Rosa'!$O$12*'Parametri Modello'!$B$25,"Attenzione","Rischio Alto"))) -> Rischio Alto | V10: =IFERROR(COUNTIFS($B$2:$B$492,$B10,$O$2:$O$492,">"&$O10)+1,"") -> 3 | W10: ='Info Lega'!$B$4-SUMIFS($M$2:$M$492,$D$2:$D$492,'Info Lega'!$B$28) -> 1000 | X10: =('Info Lega'!$B$5-COUNTIFS($D$2:$D$492,'Info Lega'!$B$28,$B$2:$B$492,"P"))+('Info Lega'!$B$6-COUNTIFS($D$2:$D$492,'Info Lega'!$B$28,$B$2:$B$492,"D"))+('Info Lega'!$B$7-COUNTIFS($D$2:$D$492,'Info Lega'!$B$28,$B$2:$B$492,"C"))+('Info Lega'!$B$8-COUNTIFS($D$2:$D$492,'Info Lega'!$B$28,$B$2:$B$492,"A")) -> 25 | Y10: =X10*'Parametri Modello'!$B$30 -> 25 | Z10: =MAX(0,W10-Y10) -> 975 | AA10: =MIN(F10,Z10) -> 158 | AC10: =IF($AB10="","",IF($AB10>$AA10,"PASS",IF($AB10<=$AA10*(1-'Parametri Modello'!$B$68),"BID","ATTENZIONE"))) | AD10: =IF(I10="","",ROUND(100*(1-EXP(-I10/30)),0)) -> 52 | AE10: =IFERROR(INDEX('Stato Asta'!$G$9:$G$12,MATCH($B10,'Stato Asta'!$A$9:$A$12,0)),"") -> 🔴 Non aspettare | AF10: =IFERROR(IF($V10<=INDEX('Parametri Modello'!$C$57:$C$60,MATCH($B10,'Parametri Modello'!$A$57:$A$60,0)),"Titolare","Riserva"),"") -> Titolare | AG10: =IFERROR(INDEX('Pressione Competitiva'!$F$3:$F$6,MATCH($B10,'Pressione Competitiva'!$B$3:$B$6,0)),"") -> 🔴 Molto Alta | AH10: =IF($AB10="","",$AA10-$AB10) | AI10: =IFERROR(IF($AH10="","",IF($AH10>=$AA10*'Parametri Modello'!$B$68,"🟢 Opportunita'",IF($AH10<=$AA10*'Parametri Modello'!$B$69,"🔴 Sovrapprezzo","🟡 Prezzo Corretto"))),"") | AJ10: =IF($AB10="","",IF($AC10="PASS","Prezzo sopra la tua Offerta Max Dinamica ("&$AA10&" cr).",IF($AC10="BID","Margine ampio sul tuo tetto (+"&($AA10-$AB10)&" cr).","Margine ridotto: sei vicino al tuo tetto ("&($AA10-$AB10)&" cr residui)."))) | AK10: =IF(AND($D10="",$N10>1),COUNTIFS($B$2:$B$492,$B10,$P$2:$P$492,$P10,$D$2:$D$492,"",$N$2:$N$492,">1",$O$2:$O$492,">"&$O10)+1,"") -> 3 | AL10: =IF($AK10="","",$B10&"|"&$P10&"|"&$AK10) -> C|Top|3
A11: 5951 | B11: A | C11: Kolo Muani | E11: =IF(COUNTIF('Info Strategia'!$D$2:$D$51,$C11)>0,"SI","NO") -> NO | F11: =IFERROR(ROUND(($G11+($H11-$G11)*'Info Strategia'!$B$6)*(1+IF($E11="SI",'Parametri Modello'!$B$7*'Info Strategia'!$B$6,0)),0),"") -> 231 | G11: =IFERROR(ROUND(MAX(1,(IF($V11<=INDEX('Parametri Modello'!$C$57:$C$60,MATCH($B11,'Parametri Modello'!$A$57:$A$60,0)),IF(INDEX('Parametri Modello'!$E$57:$E$60,MATCH($B11,'Parametri Modello'!$A$57:$A$60,0))=0,0,($O11/INDEX('Parametri Modello'!$E$57:$E$60,MATCH($B11,'Parametri Modello'!$A$57:$A$60,0)))*(INDEX('Parametri Modello'!$D$57:$D$60,MATCH($B11,'Parametri Modello'!$A$57:$A$60,0))*(INDEX('Parametri Modello'!$B$50:$B$53,MATCH($B11,'Parametri Modello'!$A$50:$A$53,0))*'Parametri Modello'!$B$44))),IF(INDEX('Parametri Modello'!$F$57:$F$60,MATCH($B11,'Parametri Modello'!$A$57:$A$60,0))=0,0,($O11/INDEX('Parametri Modello'!$F$57:$F$60,MATCH($B11,'Parametri Modello'!$A$57:$A$60,0)))*((1-INDEX('Parametri Modello'!$D$57:$D$60,MATCH($B11,'Parametri Modello'!$A$57:$A$60,0)))*(INDEX('Parametri Modello'!$B$50:$B$53,MATCH($B11,'Parametri Modello'!$A$50:$A$53,0))*'Parametri Modello'!$B$44))))*(1+IF(IF($B11="D",'Info Lega'!$B$25,IF($B11="C",'Info Lega'!$B$26,"No"))="Si",'Parametri Modello'!$B$5,0))*(1+MAX(-0.25,MIN(0.25,IF(OR($T11="",$I11="",$I11=0,INDEX('Parametri Modello'!$B$19:$B$22,MATCH($B11,'Parametri Modello'!$A$19:$A$22,0))="",INDEX('Parametri Modello'!$B$19:$B$22,MATCH($B11,'Parametri Modello'!$A$19:$A$22,0))=0),0,(($T11-INDEX('Parametri Modello'!$B$19:$B$22,MATCH($B11,'Parametri Modello'!$A$19:$A$22,0)))/INDEX('Parametri Modello'!$B$19:$B$22,MATCH($B11,'Parametri Modello'!$A$19:$A$22,0)))*'Parametri Modello'!$B$9))))*(1+IF('Parametri Modello'!$B$27="Si",MAX(-'Parametri Modello'!$B$28,MIN('Parametri Modello'!$B$28*1.5,IF(OR(INDEX('Parametri Modello'!$F$32:$F$35,MATCH($B11,'Parametri Modello'!$A$32:$A$35,0))="",INDEX('Parametri Modello'!$F$32:$F$35,MATCH($B11,'Parametri Modello'!$A$32:$A$35,0))=0),0,(1/INDEX('Parametri Modello'!$F$32:$F$35,MATCH($B11,'Parametri Modello'!$A$32:$A$35,0))-1)*'Parametri Modello'!$B$28))),0)))*(1-INDEX('Parametri Modello'!$B$12:$B$15,MATCH($B11,'Parametri Modello'!$A$12:$A$15,0)))),0),"") -> 144 | H11: =IFERROR(ROUND((IF($V11<=INDEX('Parametri Modello'!$C$57:$C$60,MATCH($B11,'Parametri Modello'!$A$57:$A$60,0)),IF(INDEX('Parametri Modello'!$E$57:$E$60,MATCH($B11,'Parametri Modello'!$A$57:$A$60,0))=0,0,($O11/INDEX('Parametri Modello'!$E$57:$E$60,MATCH($B11,'Parametri Modello'!$A$57:$A$60,0)))*(INDEX('Parametri Modello'!$D$57:$D$60,MATCH($B11,'Parametri Modello'!$A$57:$A$60,0))*(INDEX('Parametri Modello'!$B$50:$B$53,MATCH($B11,'Parametri Modello'!$A$50:$A$53,0))*'Parametri Modello'!$B$44))),IF(INDEX('Parametri Modello'!$F$57:$F$60,MATCH($B11,'Parametri Modello'!$A$57:$A$60,0))=0,0,($O11/INDEX('Parametri Modello'!$F$57:$F$60,MATCH($B11,'Parametri Modello'!$A$57:$A$60,0)))*((1-INDEX('Parametri Modello'!$D$57:$D$60,MATCH($B11,'Parametri Modello'!$A$57:$A$60,0)))*(INDEX('Parametri Modello'!$B$50:$B$53,MATCH($B11,'Parametri Modello'!$A$50:$A$53,0))*'Parametri Modello'!$B$44))))*(1+IF(IF($B11="D",'Info Lega'!$B$25,IF($B11="C",'Info Lega'!$B$26,"No"))="Si",'Parametri Modello'!$B$5,0))*(1+MAX(-0.25,MIN(0.25,IF(OR($T11="",$I11="",$I11=0,INDEX('Parametri Modello'!$B$19:$B$22,MATCH($B11,'Parametri Modello'!$A$19:$A$22,0))="",INDEX('Parametri Modello'!$B$19:$B$22,MATCH($B11,'Parametri Modello'!$A$19:$A$22,0))=0),0,(($T11-INDEX('Parametri Modello'!$B$19:$B$22,MATCH($B11,'Parametri Modello'!$A$19:$A$22,0)))/INDEX('Parametri Modello'!$B$19:$B$22,MATCH($B11,'Parametri Modello'!$A$19:$A$22,0)))*'Parametri Modello'!$B$9))))*(1+IF('Parametri Modello'!$B$27="Si",MAX(-'Parametri Modello'!$B$28,MIN('Parametri Modello'!$B$28*1.5,IF(OR(INDEX('Parametri Modello'!$F$32:$F$35,MATCH($B11,'Parametri Modello'!$A$32:$A$35,0))="",INDEX('Parametri Modello'!$F$32:$F$35,MATCH($B11,'Parametri Modello'!$A$32:$A$35,0))=0),0,(1/INDEX('Parametri Modello'!$F$32:$F$35,MATCH($B11,'Parametri Modello'!$A$32:$A$35,0))-1)*'Parametri Modello'!$B$28))),0)))*(1+INDEX('Parametri Modello'!$B$12:$B$15,MATCH($B11,'Parametri Modello'!$A$12:$A$15,0))),0),"") -> 268 | I11: =IFERROR(INDEX('Input Statistiche 2025_26'!$F$3:$F$665,MATCH($A11,'Input Statistiche 2025_26'!$A$3:$A$665,0)),"") | J11: =IFERROR(IF($I11="","",MAX(0,38-$I11)),"") | K11: =IFERROR(INDEX('Input Statistiche 2025_26'!$I$3:$I$665,MATCH($A11,'Input Statistiche 2025_26'!$A$3:$A$665,0)),"") | L11: =IFERROR(INDEX('Input Statistiche 2025_26'!$O$3:$O$665,MATCH($A11,'Input Statistiche 2025_26'!$A$3:$A$665,0)),"") | N11: =IFERROR(INDEX('Input Giocatori 2026_27'!$E$3:$E$493,MATCH($A11,'Input Giocatori 2026_27'!$A$3:$A$493,0)),"") -> 26 | O11: =IFERROR(INDEX('Input Giocatori 2026_27'!$G$3:$G$493,MATCH($A11,'Input Giocatori 2026_27'!$A$3:$A$493,0)),"") -> 225 | P11: =IFERROR(IF($O11="","",IF((1-(COUNTIFS($B$2:$B$492,$B11,$O$2:$O$492,">"&$O11)+1-1)/COUNTIF($B$2:$B$492,$B11))>='Parametri Modello'!$B$63,"Top",IF((1-(COUNTIFS($B$2:$B$492,$B11,$O$2:$O$492,">"&$O11)+1-1)/COUNTIF($B$2:$B$492,$B11))>='Parametri Modello'!$B$64,"Buono",IF((1-(COUNTIFS($B$2:$B$492,$B11,$O$2:$O$492,">"&$O11)+1-1)/COUNTIF($B$2:$B$492,$B11))>='Parametri Modello'!$B$65,"Nella Media","Scommessa/Riserva")))),"") -> Top | Q11: =IF(AND($D11="",$N11>1),SUMPRODUCT(($D$2:$D11="")*($N$2:$N11>1)),"") -> 10 | R11: =IF($D11='Info Lega'!$B$28,COUNTIFS($D$2:$D11,'Info Lega'!$B$28),"") | S11: =IFERROR(INDEX('Input Statistiche 2025_26'!$G$3:$G$665,MATCH($A11,'Input Statistiche 2025_26'!$A$3:$A$665,0)),"") | T11: =IFERROR(INDEX('Input Statistiche 2025_26'!$H$3:$H$665,MATCH($A11,'Input Statistiche 2025_26'!$A$3:$A$665,0)),"") | U11: =IF(OR('La Mia Rosa'!$O$12="",$D11<>""),"",IF($F11<='La Mia Rosa'!$O$12*'Parametri Modello'!$B$24,"OK",IF($F11<='La Mia Rosa'!$O$12*'Parametri Modello'!$B$25,"Attenzione","Rischio Alto"))) -> Rischio Alto | V11: =IFERROR(COUNTIFS($B$2:$B$492,$B11,$O$2:$O$492,">"&$O11)+1,"") -> 6 | W11: ='Info Lega'!$B$4-SUMIFS($M$2:$M$492,$D$2:$D$492,'Info Lega'!$B$28) -> 1000 | X11: =('Info Lega'!$B$5-COUNTIFS($D$2:$D$492,'Info Lega'!$B$28,$B$2:$B$492,"P"))+('Info Lega'!$B$6-COUNTIFS($D$2:$D$492,'Info Lega'!$B$28,$B$2:$B$492,"D"))+('Info Lega'!$B$7-COUNTIFS($D$2:$D$492,'Info Lega'!$B$28,$B$2:$B$492,"C"))+('Info Lega'!$B$8-COUNTIFS($D$2:$D$492,'Info Lega'!$B$28,$B$2:$B$492,"A")) -> 25 | Y11: =X11*'Parametri Modello'!$B$30 -> 25 | Z11: =MAX(0,W11-Y11) -> 975 | AA11: =MIN(F11,Z11) -> 231 | AC11: =IF($AB11="","",IF($AB11>$AA11,"PASS",IF($AB11<=$AA11*(1-'Parametri Modello'!$B$68),"BID","ATTENZIONE"))) | AD11: =IF(I11="","",ROUND(100*(1-EXP(-I11/30)),0)) | AE11: =IFERROR(INDEX('Stato Asta'!$G$9:$G$12,MATCH($B11,'Stato Asta'!$A$9:$A$12,0)),"") -> 🔴 Non aspettare | AF11: =IFERROR(IF($V11<=INDEX('Parametri Modello'!$C$57:$C$60,MATCH($B11,'Parametri Modello'!$A$57:$A$60,0)),"Titolare","Riserva"),"") -> Titolare | AG11: =IFERROR(INDEX('Pressione Competitiva'!$F$3:$F$6,MATCH($B11,'Pressione Competitiva'!$B$3:$B$6,0)),"") -> 🔴 Molto Alta | AH11: =IF($AB11="","",$AA11-$AB11) | AI11: =IFERROR(IF($AH11="","",IF($AH11>=$AA11*'Parametri Modello'!$B$68,"🟢 Opportunita'",IF($AH11<=$AA11*'Parametri Modello'!$B$69,"🔴 Sovrapprezzo","🟡 Prezzo Corretto"))),"") | AJ11: =IF($AB11="","",IF($AC11="PASS","Prezzo sopra la tua Offerta Max Dinamica ("&$AA11&" cr).",IF($AC11="BID","Margine ampio sul tuo tetto (+"&($AA11-$AB11)&" cr).","Margine ridotto: sei vicino al tuo tetto ("&($AA11-$AB11)&" cr residui)."))) | AK11: =IF(AND($D11="",$N11>1),COUNTIFS($B$2:$B$492,$B11,$P$2:$P$492,$P11,$D$2:$D$492,"",$N$2:$N$492,">1",$O$2:$O$492,">"&$O11)+1,"") -> 6 | AL11: =IF($AK11="","",$B11&"|"&$P11&"|"&$AK11) -> A|Top|6
A12: 2097 | B12: A | C12: Kean | E12: =IF(COUNTIF('Info Strategia'!$D$2:$D$51,$C12)>0,"SI","NO") -> NO | F12: =IFERROR(ROUND(($G12+($H12-$G12)*'Info Strategia'!$B$6)*(1+IF($E12="SI",'Parametri Modello'!$B$7*'Info Strategia'!$B$6,0)),0),"") -> 218 | G12: =IFERROR(ROUND(MAX(1,(IF($V12<=INDEX('Parametri Modello'!$C$57:$C$60,MATCH($B12,'Parametri Modello'!$A$57:$A$60,0)),IF(INDEX('Parametri Modello'!$E$57:$E$60,MATCH($B12,'Parametri Modello'!$A$57:$A$60,0))=0,0,($O12/INDEX('Parametri Modello'!$E$57:$E$60,MATCH($B12,'Parametri Modello'!$A$57:$A$60,0)))*(INDEX('Parametri Modello'!$D$57:$D$60,MATCH($B12,'Parametri Modello'!$A$57:$A$60,0))*(INDEX('Parametri Modello'!$B$50:$B$53,MATCH($B12,'Parametri Modello'!$A$50:$A$53,0))*'Parametri Modello'!$B$44))),IF(INDEX('Parametri Modello'!$F$57:$F$60,MATCH($B12,'Parametri Modello'!$A$57:$A$60,0))=0,0,($O12/INDEX('Parametri Modello'!$F$57:$F$60,MATCH($B12,'Parametri Modello'!$A$57:$A$60,0)))*((1-INDEX('Parametri Modello'!$D$57:$D$60,MATCH($B12,'Parametri Modello'!$A$57:$A$60,0)))*(INDEX('Parametri Modello'!$B$50:$B$53,MATCH($B12,'Parametri Modello'!$A$50:$A$53,0))*'Parametri Modello'!$B$44))))*(1+IF(IF($B12="D",'Info Lega'!$B$25,IF($B12="C",'Info Lega'!$B$26,"No"))="Si",'Parametri Modello'!$B$5,0))*(1+MAX(-0.25,MIN(0.25,IF(OR($T12="",$I12="",$I12=0,INDEX('Parametri Modello'!$B$19:$B$22,MATCH($B12,'Parametri Modello'!$A$19:$A$22,0))="",INDEX('Parametri Modello'!$B$19:$B$22,MATCH($B12,'Parametri Modello'!$A$19:$A$22,0))=0),0,(($T12-INDEX('Parametri Modello'!$B$19:$B$22,MATCH($B12,'Parametri Modello'!$A$19:$A$22,0)))/INDEX('Parametri Modello'!$B$19:$B$22,MATCH($B12,'Parametri Modello'!$A$19:$A$22,0)))*'Parametri Modello'!$B$9))))*(1+IF('Parametri Modello'!$B$27="Si",MAX(-'Parametri Modello'!$B$28,MIN('Parametri Modello'!$B$28*1.5,IF(OR(INDEX('Parametri Modello'!$F$32:$F$35,MATCH($B12,'Parametri Modello'!$A$32:$A$35,0))="",INDEX('Parametri Modello'!$F$32:$F$35,MATCH($B12,'Parametri Modello'!$A$32:$A$35,0))=0),0,(1/INDEX('Parametri Modello'!$F$32:$F$35,MATCH($B12,'Parametri Modello'!$A$32:$A$35,0))-1)*'Parametri Modello'!$B$28))),0)))*(1-INDEX('Parametri Modello'!$B$12:$B$15,MATCH($B12,'Parametri Modello'!$A$12:$A$15,0)))),0),"") -> 136 | H12: =IFERROR(ROUND((IF($V12<=INDEX('Parametri Modello'!$C$57:$C$60,MATCH($B12,'Parametri Modello'!$A$57:$A$60,0)),IF(INDEX('Parametri Modello'!$E$57:$E$60,MATCH($B12,'Parametri Modello'!$A$57:$A$60,0))=0,0,($O12/INDEX('Parametri Modello'!$E$57:$E$60,MATCH($B12,'Parametri Modello'!$A$57:$A$60,0)))*(INDEX('Parametri Modello'!$D$57:$D$60,MATCH($B12,'Parametri Modello'!$A$57:$A$60,0))*(INDEX('Parametri Modello'!$B$50:$B$53,MATCH($B12,'Parametri Modello'!$A$50:$A$53,0))*'Parametri Modello'!$B$44))),IF(INDEX('Parametri Modello'!$F$57:$F$60,MATCH($B12,'Parametri Modello'!$A$57:$A$60,0))=0,0,($O12/INDEX('Parametri Modello'!$F$57:$F$60,MATCH($B12,'Parametri Modello'!$A$57:$A$60,0)))*((1-INDEX('Parametri Modello'!$D$57:$D$60,MATCH($B12,'Parametri Modello'!$A$57:$A$60,0)))*(INDEX('Parametri Modello'!$B$50:$B$53,MATCH($B12,'Parametri Modello'!$A$50:$A$53,0))*'Parametri Modello'!$B$44))))*(1+IF(IF($B12="D",'Info Lega'!$B$25,IF($B12="C",'Info Lega'!$B$26,"No"))="Si",'Parametri Modello'!$B$5,0))*(1+MAX(-0.25,MIN(0.25,IF(OR($T12="",$I12="",$I12=0,INDEX('Parametri Modello'!$B$19:$B$22,MATCH($B12,'Parametri Modello'!$A$19:$A$22,0))="",INDEX('Parametri Modello'!$B$19:$B$22,MATCH($B12,'Parametri Modello'!$A$19:$A$22,0))=0),0,(($T12-INDEX('Parametri Modello'!$B$19:$B$22,MATCH($B12,'Parametri Modello'!$A$19:$A$22,0)))/INDEX('Parametri Modello'!$B$19:$B$22,MATCH($B12,'Parametri Modello'!$A$19:$A$22,0)))*'Parametri Modello'!$B$9))))*(1+IF('Parametri Modello'!$B$27="Si",MAX(-'Parametri Modello'!$B$28,MIN('Parametri Modello'!$B$28*1.5,IF(OR(INDEX('Parametri Modello'!$F$32:$F$35,MATCH($B12,'Parametri Modello'!$A$32:$A$35,0))="",INDEX('Parametri Modello'!$F$32:$F$35,MATCH($B12,'Parametri Modello'!$A$32:$A$35,0))=0),0,(1/INDEX('Parametri Modello'!$F$32:$F$35,MATCH($B12,'Parametri Modello'!$A$32:$A$35,0))-1)*'Parametri Modello'!$B$28))),0)))*(1+INDEX('Parametri Modello'!$B$12:$B$15,MATCH($B12,'Parametri Modello'!$A$12:$A$15,0))),0),"") -> 253 | I12: =IFERROR(INDEX('Input Statistiche 2025_26'!$F$3:$F$665,MATCH($A12,'Input Statistiche 2025_26'!$A$3:$A$665,0)),"") -> 26 | J12: =IFERROR(IF($I12="","",MAX(0,38-$I12)),"") -> 12 | K12: =IFERROR(INDEX('Input Statistiche 2025_26'!$I$3:$I$665,MATCH($A12,'Input Statistiche 2025_26'!$A$3:$A$665,0)),"") -> 8 | L12: =IFERROR(INDEX('Input Statistiche 2025_26'!$O$3:$O$665,MATCH($A12,'Input Statistiche 2025_26'!$A$3:$A$665,0)),"") -> 1 | N12: =IFERROR(INDEX('Input Giocatori 2026_27'!$E$3:$E$493,MATCH($A12,'Input Giocatori 2026_27'!$A$3:$A$493,0)),"") -> 25 | O12: =IFERROR(INDEX('Input Giocatori 2026_27'!$G$3:$G$493,MATCH($A12,'Input Giocatori 2026_27'!$A$3:$A$493,0)),"") -> 212 | P12: =IFERROR(IF($O12="","",IF((1-(COUNTIFS($B$2:$B$492,$B12,$O$2:$O$492,">"&$O12)+1-1)/COUNTIF($B$2:$B$492,$B12))>='Parametri Modello'!$B$63,"Top",IF((1-(COUNTIFS($B$2:$B$492,$B12,$O$2:$O$492,">"&$O12)+1-1)/COUNTIF($B$2:$B$492,$B12))>='Parametri Modello'!$B$64,"Buono",IF((1-(COUNTIFS($B$2:$B$492,$B12,$O$2:$O$492,">"&$O12)+1-1)/COUNTIF($B$2:$B$492,$B12))>='Parametri Modello'!$B$65,"Nella Media","Scommessa/Riserva")))),"") -> Top | Q12: =IF(AND($D12="",$N12>1),SUMPRODUCT(($D$2:$D12="")*($N$2:$N12>1)),"") -> 11 | R12: =IF($D12='Info Lega'!$B$28,COUNTIFS($D$2:$D12,'Info Lega'!$B$28),"") | S12: =IFERROR(INDEX('Input Statistiche 2025_26'!$G$3:$G$665,MATCH($A12,'Input Statistiche 2025_26'!$A$3:$A$665,0)),"") -> 5.88 | T12: =IFERROR(INDEX('Input Statistiche 2025_26'!$H$3:$H$665,MATCH($A12,'Input Statistiche 2025_26'!$A$3:$A$665,0)),"") -> 6.77 | U12: =IF(OR('La Mia Rosa'!$O$12="",$D12<>""),"",IF($F12<='La Mia Rosa'!$O$12*'Parametri Modello'!$B$24,"OK",IF($F12<='La Mia Rosa'!$O$12*'Parametri Modello'!$B$25,"Attenzione","Rischio Alto"))) -> Rischio Alto | V12: =IFERROR(COUNTIFS($B$2:$B$492,$B12,$O$2:$O$492,">"&$O12)+1,"") -> 7 | W12: ='Info Lega'!$B$4-SUMIFS($M$2:$M$492,$D$2:$D$492,'Info Lega'!$B$28) -> 1000 | X12: =('Info Lega'!$B$5-COUNTIFS($D$2:$D$492,'Info Lega'!$B$28,$B$2:$B$492,"P"))+('Info Lega'!$B$6-COUNTIFS($D$2:$D$492,'Info Lega'!$B$28,$B$2:$B$492,"D"))+('Info Lega'!$B$7-COUNTIFS($D$2:$D$492,'Info Lega'!$B$28,$B$2:$B$492,"C"))+('Info Lega'!$B$8-COUNTIFS($D$2:$D$492,'Info Lega'!$B$28,$B$2:$B$492,"A")) -> 25 | Y12: =X12*'Parametri Modello'!$B$30 -> 25 | Z12: =MAX(0,W12-Y12) -> 975 | AA12: =MIN(F12,Z12) -> 218 | AC12: =IF($AB12="","",IF($AB12>$AA12,"PASS",IF($AB12<=$AA12*(1-'Parametri Modello'!$B$68),"BID","ATTENZIONE"))) | AD12: =IF(I12="","",ROUND(100*(1-EXP(-I12/30)),0)) -> 58 | AE12: =IFERROR(INDEX('Stato Asta'!$G$9:$G$12,MATCH($B12,'Stato Asta'!$A$9:$A$12,0)),"") -> 🔴 Non aspettare | AF12: =IFERROR(IF($V12<=INDEX('Parametri Modello'!$C$57:$C$60,MATCH($B12,'Parametri Modello'!$A$57:$A$60,0)),"Titolare","Riserva"),"") -> Titolare | AG12: =IFERROR(INDEX('Pressione Competitiva'!$F$3:$F$6,MATCH($B12,'Pressione Competitiva'!$B$3:$B$6,0)),"") -> 🔴 Molto Alta | AH12: =IF($AB12="","",$AA12-$AB12) | AI12: =IFERROR(IF($AH12="","",IF($AH12>=$AA12*'Parametri Modello'!$B$68,"🟢 Opportunita'",IF($AH12<=$AA12*'Parametri Modello'!$B$69,"🔴 Sovrapprezzo","🟡 Prezzo Corretto"))),"") | AJ12: =IF($AB12="","",IF($AC12="PASS","Prezzo sopra la tua Offerta Max Dinamica ("&$AA12&" cr).",IF($AC12="BID","Margine ampio sul tuo tetto (+"&($AA12-$AB12)&" cr).","Margine ridotto: sei vicino al tuo tetto ("&($AA12-$AB12)&" cr residui)."))) | AK12: =IF(AND($D12="",$N12>1),COUNTIFS($B$2:$B$492,$B12,$P$2:$P$492,$P12,$D$2:$D$492,"",$N$2:$N$492,">1",$O$2:$O$492,">"&$O12)+1,"") -> 7 | AL12: =IF($AK12="","",$B12&"|"&$P12&"|"&$AK12) -> A|Top|7
A13: 2167 | B13: C | C13: Orsolini | E13: =IF(COUNTIF('Info Strategia'!$D$2:$D$51,$C13)>0,"SI","NO") -> NO | F13: =IFERROR(ROUND(($G13+($H13-$G13)*'Info Strategia'!$B$6)*(1+IF($E13="SI",'Parametri Modello'!$B$7*'Info Strategia'!$B$6,0)),0),"") -> 135 | G13: =IFERROR(ROUND(MAX(1,(IF($V13<=INDEX('Parametri Modello'!$C$57:$C$60,MATCH($B13,'Parametri Modello'!$A$57:$A$60,0)),IF(INDEX('Parametri Modello'!$E$57:$E$60,MATCH($B13,'Parametri Modello'!$A$57:$A$60,0))=0,0,($O13/INDEX('Parametri Modello'!$E$57:$E$60,MATCH($B13,'Parametri Modello'!$A$57:$A$60,0)))*(INDEX('Parametri Modello'!$D$57:$D$60,MATCH($B13,'Parametri Modello'!$A$57:$A$60,0))*(INDEX('Parametri Modello'!$B$50:$B$53,MATCH($B13,'Parametri Modello'!$A$50:$A$53,0))*'Parametri Modello'!$B$44))),IF(INDEX('Parametri Modello'!$F$57:$F$60,MATCH($B13,'Parametri Modello'!$A$57:$A$60,0))=0,0,($O13/INDEX('Parametri Modello'!$F$57:$F$60,MATCH($B13,'Parametri Modello'!$A$57:$A$60,0)))*((1-INDEX('Parametri Modello'!$D$57:$D$60,MATCH($B13,'Parametri Modello'!$A$57:$A$60,0)))*(INDEX('Parametri Modello'!$B$50:$B$53,MATCH($B13,'Parametri Modello'!$A$50:$A$53,0))*'Parametri Modello'!$B$44))))*(1+IF(IF($B13="D",'Info Lega'!$B$25,IF($B13="C",'Info Lega'!$B$26,"No"))="Si",'Parametri Modello'!$B$5,0))*(1+MAX(-0.25,MIN(0.25,IF(OR($T13="",$I13="",$I13=0,INDEX('Parametri Modello'!$B$19:$B$22,MATCH($B13,'Parametri Modello'!$A$19:$A$22,0))="",INDEX('Parametri Modello'!$B$19:$B$22,MATCH($B13,'Parametri Modello'!$A$19:$A$22,0))=0),0,(($T13-INDEX('Parametri Modello'!$B$19:$B$22,MATCH($B13,'Parametri Modello'!$A$19:$A$22,0)))/INDEX('Parametri Modello'!$B$19:$B$22,MATCH($B13,'Parametri Modello'!$A$19:$A$22,0)))*'Parametri Modello'!$B$9))))*(1+IF('Parametri Modello'!$B$27="Si",MAX(-'Parametri Modello'!$B$28,MIN('Parametri Modello'!$B$28*1.5,IF(OR(INDEX('Parametri Modello'!$F$32:$F$35,MATCH($B13,'Parametri Modello'!$A$32:$A$35,0))="",INDEX('Parametri Modello'!$F$32:$F$35,MATCH($B13,'Parametri Modello'!$A$32:$A$35,0))=0),0,(1/INDEX('Parametri Modello'!$F$32:$F$35,MATCH($B13,'Parametri Modello'!$A$32:$A$35,0))-1)*'Parametri Modello'!$B$28))),0)))*(1-INDEX('Parametri Modello'!$B$12:$B$15,MATCH($B13,'Parametri Modello'!$A$12:$A$15,0)))),0),"") -> 92 | H13: =IFERROR(ROUND((IF($V13<=INDEX('Parametri Modello'!$C$57:$C$60,MATCH($B13,'Parametri Modello'!$A$57:$A$60,0)),IF(INDEX('Parametri Modello'!$E$57:$E$60,MATCH($B13,'Parametri Modello'!$A$57:$A$60,0))=0,0,($O13/INDEX('Parametri Modello'!$E$57:$E$60,MATCH($B13,'Parametri Modello'!$A$57:$A$60,0)))*(INDEX('Parametri Modello'!$D$57:$D$60,MATCH($B13,'Parametri Modello'!$A$57:$A$60,0))*(INDEX('Parametri Modello'!$B$50:$B$53,MATCH($B13,'Parametri Modello'!$A$50:$A$53,0))*'Parametri Modello'!$B$44))),IF(INDEX('Parametri Modello'!$F$57:$F$60,MATCH($B13,'Parametri Modello'!$A$57:$A$60,0))=0,0,($O13/INDEX('Parametri Modello'!$F$57:$F$60,MATCH($B13,'Parametri Modello'!$A$57:$A$60,0)))*((1-INDEX('Parametri Modello'!$D$57:$D$60,MATCH($B13,'Parametri Modello'!$A$57:$A$60,0)))*(INDEX('Parametri Modello'!$B$50:$B$53,MATCH($B13,'Parametri Modello'!$A$50:$A$53,0))*'Parametri Modello'!$B$44))))*(1+IF(IF($B13="D",'Info Lega'!$B$25,IF($B13="C",'Info Lega'!$B$26,"No"))="Si",'Parametri Modello'!$B$5,0))*(1+MAX(-0.25,MIN(0.25,IF(OR($T13="",$I13="",$I13=0,INDEX('Parametri Modello'!$B$19:$B$22,MATCH($B13,'Parametri Modello'!$A$19:$A$22,0))="",INDEX('Parametri Modello'!$B$19:$B$22,MATCH($B13,'Parametri Modello'!$A$19:$A$22,0))=0),0,(($T13-INDEX('Parametri Modello'!$B$19:$B$22,MATCH($B13,'Parametri Modello'!$A$19:$A$22,0)))/INDEX('Parametri Modello'!$B$19:$B$22,MATCH($B13,'Parametri Modello'!$A$19:$A$22,0)))*'Parametri Modello'!$B$9))))*(1+IF('Parametri Modello'!$B$27="Si",MAX(-'Parametri Modello'!$B$28,MIN('Parametri Modello'!$B$28*1.5,IF(OR(INDEX('Parametri Modello'!$F$32:$F$35,MATCH($B13,'Parametri Modello'!$A$32:$A$35,0))="",INDEX('Parametri Modello'!$F$32:$F$35,MATCH($B13,'Parametri Modello'!$A$32:$A$35,0))=0),0,(1/INDEX('Parametri Modello'!$F$32:$F$35,MATCH($B13,'Parametri Modello'!$A$32:$A$35,0))-1)*'Parametri Modello'!$B$28))),0)))*(1+INDEX('Parametri Modello'!$B$12:$B$15,MATCH($B13,'Parametri Modello'!$A$12:$A$15,0))),0),"") -> 153 | I13: =IFERROR(INDEX('Input Statistiche 2025_26'!$F$3:$F$665,MATCH($A13,'Input Statistiche 2025_26'!$A$3:$A$665,0)),"") -> 34 | J13: =IFERROR(IF($I13="","",MAX(0,38-$I13)),"") -> 4 | K13: =IFERROR(INDEX('Input Statistiche 2025_26'!$I$3:$I$665,MATCH($A13,'Input Statistiche 2025_26'!$A$3:$A$665,0)),"") -> 10 | L13: =IFERROR(INDEX('Input Statistiche 2025_26'!$O$3:$O$665,MATCH($A13,'Input Statistiche 2025_26'!$A$3:$A$665,0)),"") -> 1 | N13: =IFERROR(INDEX('Input Giocatori 2026_27'!$E$3:$E$493,MATCH($A13,'Input Giocatori 2026_27'!$A$3:$A$493,0)),"") -> 26 | O13: =IFERROR(INDEX('Input Giocatori 2026_27'!$G$3:$G$493,MATCH($A13,'Input Giocatori 2026_27'!$A$3:$A$493,0)),"") -> 200 | P13: =IFERROR(IF($O13="","",IF((1-(COUNTIFS($B$2:$B$492,$B13,$O$2:$O$492,">"&$O13)+1-1)/COUNTIF($B$2:$B$492,$B13))>='Parametri Modello'!$B$63,"Top",IF((1-(COUNTIFS($B$2:$B$492,$B13,$O$2:$O$492,">"&$O13)+1-1)/COUNTIF($B$2:$B$492,$B13))>='Parametri Modello'!$B$64,"Buono",IF((1-(COUNTIFS($B$2:$B$492,$B13,$O$2:$O$492,">"&$O13)+1-1)/COUNTIF($B$2:$B$492,$B13))>='Parametri Modello'!$B$65,"Nella Media","Scommessa/Riserva")))),"") -> Top | Q13: =IF(AND($D13="",$N13>1),SUMPRODUCT(($D$2:$D13="")*($N$2:$N13>1)),"") -> 12 | R13: =IF($D13='Info Lega'!$B$28,COUNTIFS($D$2:$D13,'Info Lega'!$B$28),"") | S13: =IFERROR(INDEX('Input Statistiche 2025_26'!$G$3:$G$665,MATCH($A13,'Input Statistiche 2025_26'!$A$3:$A$665,0)),"") -> 6.06 | T13: =IFERROR(INDEX('Input Statistiche 2025_26'!$H$3:$H$665,MATCH($A13,'Input Statistiche 2025_26'!$A$3:$A$665,0)),"") -> 6.76 | U13: =IF(OR('La Mia Rosa'!$O$12="",$D13<>""),"",IF($F13<='La Mia Rosa'!$O$12*'Parametri Modello'!$B$24,"OK",IF($F13<='La Mia Rosa'!$O$12*'Parametri Modello'!$B$25,"Attenzione","Rischio Alto"))) -> Rischio Alto | V13: =IFERROR(COUNTIFS($B$2:$B$492,$B13,$O$2:$O$492,">"&$O13)+1,"") -> 4 | W13: ='Info Lega'!$B$4-SUMIFS($M$2:$M$492,$D$2:$D$492,'Info Lega'!$B$28) -> 1000 | X13: =('Info Lega'!$B$5-COUNTIFS($D$2:$D$492,'Info Lega'!$B$28,$B$2:$B$492,"P"))+('Info Lega'!$B$6-COUNTIFS($D$2:$D$492,'Info Lega'!$B$28,$B$2:$B$492,"D"))+('Info Lega'!$B$7-COUNTIFS($D$2:$D$492,'Info Lega'!$B$28,$B$2:$B$492,"C"))+('Info Lega'!$B$8-COUNTIFS($D$2:$D$492,'Info Lega'!$B$28,$B$2:$B$492,"A")) -> 25 | Y13: =X13*'Parametri Modello'!$B$30 -> 25 | Z13: =MAX(0,W13-Y13) -> 975 | AA13: =MIN(F13,Z13) -> 135 | AC13: =IF($AB13="","",IF($AB13>$AA13,"PASS",IF($AB13<=$AA13*(1-'Parametri Modello'!$B$68),"BID","ATTENZIONE"))) | AD13: =IF(I13="","",ROUND(100*(1-EXP(-I13/30)),0)) -> 68 | AE13: =IFERROR(INDEX('Stato Asta'!$G$9:$G$12,MATCH($B13,'Stato Asta'!$A$9:$A$12,0)),"") -> 🔴 Non aspettare | AF13: =IFERROR(IF($V13<=INDEX('Parametri Modello'!$C$57:$C$60,MATCH($B13,'Parametri Modello'!$A$57:$A$60,0)),"Titolare","Riserva"),"") -> Titolare | AG13: =IFERROR(INDEX('Pressione Competitiva'!$F$3:$F$6,MATCH($B13,'Pressione Competitiva'!$B$3:$B$6,0)),"") -> 🔴 Molto Alta | AH13: =IF($AB13="","",$AA13-$AB13) | AI13: =IFERROR(IF($AH13="","",IF($AH13>=$AA13*'Parametri Modello'!$B$68,"🟢 Opportunita'",IF($AH13<=$AA13*'Parametri Modello'!$B$69,"🔴 Sovrapprezzo","🟡 Prezzo Corretto"))),"") | AJ13: =IF($AB13="","",IF($AC13="PASS","Prezzo sopra la tua Offerta Max Dinamica ("&$AA13&" cr).",IF($AC13="BID","Margine ampio sul tuo tetto (+"&($AA13-$AB13)&" cr).","Margine ridotto: sei vicino al tuo tetto ("&($AA13-$AB13)&" cr residui)."))) | AK13: =IF(AND($D13="",$N13>1),COUNTIFS($B$2:$B$492,$B13,$P$2:$P$492,$P13,$D$2:$D$492,"",$N$2:$N$492,">1",$O$2:$O$492,">"&$O13)+1,"") -> 4 | AL13: =IF($AK13="","",$B13&"|"&$P13&"|"&$AK13) -> C|Top|4
... A492: 7482 | B492: A | C492: Lauberbach | E492: =IF(COUNTIF('Info Strategia'!$D$2:$D$51,$C492)>0,"SI","NO") -> NO | F492: =IFERROR(ROUND(($G492+($H492-$G492)*'Info Strategia'!$B$6)*(1+IF($E492="SI",'Parametri Modello'!$B$7*'Info Strategia'!$B$6,0)),0),"") -> 0 | G492: =IFERROR(ROUND(MAX(1,(IF($V492<=INDEX('Parametri Modello'!$C$57:$C$60,MATCH($B492,'Parametri Modello'!$A$57:$A$60,0)),IF(INDEX('Parametri Modello'!$E$57:$E$60,MATCH($B492,'Parametri Modello'!$A$57:$A$60,0))=0,0,($O492/INDEX('Parametri Modello'!$E$57:$E$60,MATCH($B492,'Parametri Modello'!$A$57:$A$60,0)))*(INDEX('Parametri Modello'!$D$57:$D$60,MATCH($B492,'Parametri Modello'!$A$57:$A$60,0))*(INDEX('Parametri Modello'!$B$50:$B$53,MATCH($B492,'Parametri Modello'!$A$50:$A$53,0))*'Parametri Modello'!$B$44))),IF(INDEX('Parametri Modello'!$F$57:$F$60,MATCH($B492,'Parametri Modello'!$A$57:$A$60,0))=0,0,($O492/INDEX('Parametri Modello'!$F$57:$F$60,MATCH($B492,'Parametri Modello'!$A$57:$A$60,0)))*((1-INDEX('Parametri Modello'!$D$57:$D$60,MATCH($B492,'Parametri Modello'!$A$57:$A$60,0)))*(INDEX('Parametri Modello'!$B$50:$B$53,MATCH($B492,'Parametri Modello'!$A$50:$A$53,0))*'Parametri Modello'!$B$44))))*(1+IF(IF($B492="D",'Info Lega'!$B$25,IF($B492="C",'Info Lega'!$B$26,"No"))="Si",'Parametri Modello'!$B$5,0))*(1+MAX(-0.25,MIN(0.25,IF(OR($T492="",$I492="",$I492=0,INDEX('Parametri Modello'!$B$19:$B$22,MATCH($B492,'Parametri Modello'!$A$19:$A$22,0))="",INDEX('Parametri Modello'!$B$19:$B$22,MATCH($B492,'Parametri Modello'!$A$19:$A$22,0))=0),0,(($T492-INDEX('Parametri Modello'!$B$19:$B$22,MATCH($B492,'Parametri Modello'!$A$19:$A$22,0)))/INDEX('Parametri Modello'!$B$19:$B$22,MATCH($B492,'Parametri Modello'!$A$19:$A$22,0)))*'Parametri Modello'!$B$9))))*(1+IF('Parametri Modello'!$B$27="Si",MAX(-'Parametri Modello'!$B$28,MIN('Parametri Modello'!$B$28*1.5,IF(OR(INDEX('Parametri Modello'!$F$32:$F$35,MATCH($B492,'Parametri Modello'!$A$32:$A$35,0))="",INDEX('Parametri Modello'!$F$32:$F$35,MATCH($B492,'Parametri Modello'!$A$32:$A$35,0))=0),0,(1/INDEX('Parametri Modello'!$F$32:$F$35,MATCH($B492,'Parametri Modello'!$A$32:$A$35,0))-1)*'Parametri Modello'!$B$28))),0)))*(1-INDEX('Parametri Modello'!$B$12:$B$15,MATCH($B492,'Parametri Modello'!$A$12:$A$15,0)))),0),"") -> 1 | H492: =IFERROR(ROUND((IF($V492<=INDEX('Parametri Modello'!$C$57:$C$60,MATCH($B492,'Parametri Modello'!$A$57:$A$60,0)),IF(INDEX('Parametri Modello'!$E$57:$E$60,MATCH($B492,'Parametri Modello'!$A$57:$A$60,0))=0,0,($O492/INDEX('Parametri Modello'!$E$57:$E$60,MATCH($B492,'Parametri Modello'!$A$57:$A$60,0)))*(INDEX('Parametri Modello'!$D$57:$D$60,MATCH($B492,'Parametri Modello'!$A$57:$A$60,0))*(INDEX('Parametri Modello'!$B$50:$B$53,MATCH($B492,'Parametri Modello'!$A$50:$A$53,0))*'Parametri Modello'!$B$44))),IF(INDEX('Parametri Modello'!$F$57:$F$60,MATCH($B492,'Parametri Modello'!$A$57:$A$60,0))=0,0,($O492/INDEX('Parametri Modello'!$F$57:$F$60,MATCH($B492,'Parametri Modello'!$A$57:$A$60,0)))*((1-INDEX('Parametri Modello'!$D$57:$D$60,MATCH($B492,'Parametri Modello'!$A$57:$A$60,0)))*(INDEX('Parametri Modello'!$B$50:$B$53,MATCH($B492,'Parametri Modello'!$A$50:$A$53,0))*'Parametri Modello'!$B$44))))*(1+IF(IF($B492="D",'Info Lega'!$B$25,IF($B492="C",'Info Lega'!$B$26,"No"))="Si",'Parametri Modello'!$B$5,0))*(1+MAX(-0.25,MIN(0.25,IF(OR($T492="",$I492="",$I492=0,INDEX('Parametri Modello'!$B$19:$B$22,MATCH($B492,'Parametri Modello'!$A$19:$A$22,0))="",INDEX('Parametri Modello'!$B$19:$B$22,MATCH($B492,'Parametri Modello'!$A$19:$A$22,0))=0),0,(($T492-INDEX('Parametri Modello'!$B$19:$B$22,MATCH($B492,'Parametri Modello'!$A$19:$A$22,0)))/INDEX('Parametri Modello'!$B$19:$B$22,MATCH($B492,'Parametri Modello'!$A$19:$A$22,0)))*'Parametri Modello'!$B$9))))*(1+IF('Parametri Modello'!$B$27="Si",MAX(-'Parametri Modello'!$B$28,MIN('Parametri Modello'!$B$28*1.5,IF(OR(INDEX('Parametri Modello'!$F$32:$F$35,MATCH($B492,'Parametri Modello'!$A$32:$A$35,0))="",INDEX('Parametri Modello'!$F$32:$F$35,MATCH($B492,'Parametri Modello'!$A$32:$A$35,0))=0),0,(1/INDEX('Parametri Modello'!$F$32:$F$35,MATCH($B492,'Parametri Modello'!$A$32:$A$35,0))-1)*'Parametri Modello'!$B$28))),0)))*(1+INDEX('Parametri Modello'!$B$12:$B$15,MATCH($B492,'Parametri Modello'!$A$12:$A$15,0))),0),"") -> 0 | I492: =IFERROR(INDEX('Input Statistiche 2025_26'!$F$3:$F$665,MATCH($A492,'Input Statistiche 2025_26'!$A$3:$A$665,0)),"") | J492: =IFERROR(IF($I492="","",MAX(0,38-$I492)),"") | K492: =IFERROR(INDEX('Input Statistiche 2025_26'!$I$3:$I$665,MATCH($A492,'Input Statistiche 2025_26'!$A$3:$A$665,0)),"") | L492: =IFERROR(INDEX('Input Statistiche 2025_26'!$O$3:$O$665,MATCH($A492,'Input Statistiche 2025_26'!$A$3:$A$665,0)),"") | N492: =IFERROR(INDEX('Input Giocatori 2026_27'!$E$3:$E$493,MATCH($A492,'Input Giocatori 2026_27'!$A$3:$A$493,0)),"") -> 1 | O492: =IFERROR(INDEX('Input Giocatori 2026_27'!$G$3:$G$493,MATCH($A492,'Input Giocatori 2026_27'!$A$3:$A$493,0)),"") -> 1 | P492: =IFERROR(IF($O492="","",IF((1-(COUNTIFS($B$2:$B$492,$B492,$O$2:$O$492,">"&$O492)+1-1)/COUNTIF($B$2:$B$492,$B492))>='Parametri Modello'!$B$63,"Top",IF((1-(COUNTIFS($B$2:$B$492,$B492,$O$2:$O$492,">"&$O492)+1-1)/COUNTIF($B$2:$B$492,$B492))>='Parametri Modello'!$B$64,"Buono",IF((1-(COUNTIFS($B$2:$B$492,$B492,$O$2:$O$492,">"&$O492)+1-1)/COUNTIF($B$2:$B$492,$B492))>='Parametri Modello'!$B$65,"Nella Media","Scommessa/Riserva")))),"") -> Scommessa/Riserva | Q492: =IF(AND($D492="",$N492>1),SUMPRODUCT(($D$2:$D492="")*($N$2:$N492>1)),"") | R492: =IF($D492='Info Lega'!$B$28,COUNTIFS($D$2:$D492,'Info Lega'!$B$28),"") | S492: =IFERROR(INDEX('Input Statistiche 2025_26'!$G$3:$G$665,MATCH($A492,'Input Statistiche 2025_26'!$A$3:$A$665,0)),"") | T492: =IFERROR(INDEX('Input Statistiche 2025_26'!$H$3:$H$665,MATCH($A492,'Input Statistiche 2025_26'!$A$3:$A$665,0)),"") | U492: =IF(OR('La Mia Rosa'!$O$12="",$D492<>""),"",IF($F492<='La Mia Rosa'!$O$12*'Parametri Modello'!$B$24,"OK",IF($F492<='La Mia Rosa'!$O$12*'Parametri Modello'!$B$25,"Attenzione","Rischio Alto"))) -> OK | V492: =IFERROR(COUNTIFS($B$2:$B$492,$B492,$O$2:$O$492,">"&$O492)+1,"") -> 81 | W492: ='Info Lega'!$B$4-SUMIFS($M$2:$M$492,$D$2:$D$492,'Info Lega'!$B$28) -> 1000 | X492: =('Info Lega'!$B$5-COUNTIFS($D$2:$D$492,'Info Lega'!$B$28,$B$2:$B$492,"P"))+('Info Lega'!$B$6-COUNTIFS($D$2:$D$492,'Info Lega'!$B$28,$B$2:$B$492,"D"))+('Info Lega'!$B$7-COUNTIFS($D$2:$D$492,'Info Lega'!$B$28,$B$2:$B$492,"C"))+('Info Lega'!$B$8-COUNTIFS($D$2:$D$492,'Info Lega'!$B$28,$B$2:$B$492,"A")) -> 25 | Y492: =X492*'Parametri Modello'!$B$30 -> 25 | Z492: =MAX(0,W492-Y492) -> 975 | AA492: =MIN(F492,Z492) -> 0 | AC492: =IF($AB492="","",IF($AB492>$AA492,"PASS",IF($AB492<=$AA492*(1-'Parametri Modello'!$B$68),"BID","ATTENZIONE"))) | AD492: =IF(I492="","",ROUND(100*(1-EXP(-I492/30)),0)) | AE492: =IFERROR(INDEX('Stato Asta'!$G$9:$G$12,MATCH($B492,'Stato Asta'!$A$9:$A$12,0)),"") -> 🔴 Non aspettare | AF492: =IFERROR(IF($V492<=INDEX('Parametri Modello'!$C$57:$C$60,MATCH($B492,'Parametri Modello'!$A$57:$A$60,0)),"Titolare","Riserva"),"") -> Riserva | AG492: =IFERROR(INDEX('Pressione Competitiva'!$F$3:$F$6,MATCH($B492,'Pressione Competitiva'!$B$3:$B$6,0)),"") -> 🔴 Molto Alta | AH492: =IF($AB492="","",$AA492-$AB492) | AI492: =IFERROR(IF($AH492="","",IF($AH492>=$AA492*'Parametri Modello'!$B$68,"🟢 Opportunita'",IF($AH492<=$AA492*'Parametri Modello'!$B$69,"🔴 Sovrapprezzo","🟡 Prezzo Corretto"))),"") | AJ492: =IF($AB492="","",IF($AC492="PASS","Prezzo sopra la tua Offerta Max Dinamica ("&$AA492&" cr).",IF($AC492="BID","Margine ampio sul tuo tetto (+"&($AA492-$AB492)&" cr).","Margine ridotto: sei vicino al tuo tetto ("&($AA492-$AB492)&" cr residui)."))) | AK492: =IF(AND($D492="",$N492>1),COUNTIFS($B$2:$B$492,$B492,$P$2:$P$492,$P492,$D$2:$D$492,"",$N$2:$N$492,">1",$O$2:$O$492,">"&$O492)+1,"") | AL492: =IF($AK492="","",$B492&"|"&$P492&"|"&$AK492)

Sheet Stato Asta
A1: STATO ASTA — Auction State (si aggiorna da solo mentre assegni giocatori)
A3: Giocatori chiamati / Totale listone | C3: =COUNTIFS('Output Utente'!$D$2:$D$492,"<>")&" / "&COUNTA('Output Utente'!$A$2:$A$492) -> 0 / 491
A4: % Asta completata | C4: =COUNTIFS('Output Utente'!$D$2:$D$492,"<>")/COUNTA('Output Utente'!$A$2:$A$492) -> 0
A5: Budget medio residuo squadre attive | C5: {=AVERAGE(IF('Info Lega'!$D$9:$D$24="Si",'Info Lega'!$B$4-SUMIF('Output Utente'!$D$2:$D$492,'Info Lega'!$B$9:$B$24,'Output Utente'!$M$2:$M$492)))} -> 1000
A6: Prezzo medio pagato finora (tutti i ruoli) | C6: =IFERROR(AVERAGEIF('Output Utente'!$D$2:$D$492,"<>",'Output Utente'!$M$2:$M$492),"")
A8: Ruolo | B8: Top Rimasti | C8: Buoni Rimasti | D8: Top+Buoni Rimasti | E8: Slot Ancora da Riempire (Lega) | F8: Rapporto Qualità/Slot | G8: Pressione Asta | H8: Prezzo Medio Pagato | I8: Media Rimasti | J8: Scommesse Rimaste | K8: Totale Disponibili Ruolo | L8: Quality Coverage (Top+Buoni / Totale)
A9: P | B9: =COUNTIFS('Output Utente'!$B$2:$B$492,"P",'Output Utente'!$P$2:$P$492,"Top",'Output Utente'!$D$2:$D$492,"",'Output Utente'!$N$2:$N$492,">1") -> 7 | C9: =COUNTIFS('Output Utente'!$B$2:$B$492,"P",'Output Utente'!$P$2:$P$492,"Buono",'Output Utente'!$D$2:$D$492,"",'Output Utente'!$N$2:$N$492,">1") -> 11 | D9: =$B9+$C9 -> 18 | E9: ='Parametri Modello'!$D$32 -> 24 | F9: =IFERROR($D9/$E9,"") -> 0.75 | G9: =IF($E9=0,"— (ruolo esaurito)",IF($F9>='Parametri Modello'!$B$46,"🟢 Puoi aspettare",IF($F9>='Parametri Modello'!$B$47,"🟡 Attesa rischiosa","🔴 Non aspettare"))) -> 🔴 Non aspettare | H9: =IFERROR(AVERAGEIFS('Output Utente'!$M$2:$M$492,'Output Utente'!$B$2:$B$492,"P",'Output Utente'!$D$2:$D$492,"<>"),"") | I9: =COUNTIFS('Output Utente'!$B$2:$B$492,"P",'Output Utente'!$P$2:$P$492,"Nella Media",'Output Utente'!$D$2:$D$492,"",'Output Utente'!$N$2:$N$492,">1") -> 6 | J9: =COUNTIFS('Output Utente'!$B$2:$B$492,"P",'Output Utente'!$P$2:$P$492,"Scommessa/Riserva",'Output Utente'!$D$2:$D$492,"",'Output Utente'!$N$2:$N$492,">1") -> 0 | K9: =B9+C9+I9+J9 -> 24 | L9: =IFERROR($D9/$K9,"") -> 0.75
A10: D | B10: =COUNTIFS('Output Utente'!$B$2:$B$492,"D",'Output Utente'!$P$2:$P$492,"Top",'Output Utente'!$D$2:$D$492,"",'Output Utente'!$N$2:$N$492,">1") -> 18 | C10: =COUNTIFS('Output Utente'!$B$2:$B$492,"D",'Output Utente'!$P$2:$P$492,"Buono",'Output Utente'!$D$2:$D$492,"",'Output Utente'!$N$2:$N$492,">1") -> 37 | D10: =$B10+$C10 -> 55 | E10: ='Parametri Modello'!$D$33 -> 64 | F10: =IFERROR($D10/$E10,"") -> 0.859375 | G10: =IF($E10=0,"— (ruolo esaurito)",IF($F10>='Parametri Modello'!$B$46,"🟢 Puoi aspettare",IF($F10>='Parametri Modello'!$B$47,"🟡 Attesa rischiosa","🔴 Non aspettare"))) -> 🔴 Non aspettare | H10: =IFERROR(AVERAGEIFS('Output Utente'!$M$2:$M$492,'Output Utente'!$B$2:$B$492,"D",'Output Utente'!$D$2:$D$492,"<>"),"") | I10: =COUNTIFS('Output Utente'!$B$2:$B$492,"D",'Output Utente'!$P$2:$P$492,"Nella Media",'Output Utente'!$D$2:$D$492,"",'Output Utente'!$N$2:$N$492,">1") -> 56 | J10: =COUNTIFS('Output Utente'!$B$2:$B$492,"D",'Output Utente'!$P$2:$P$492,"Scommessa/Riserva",'Output Utente'!$D$2:$D$492,"",'Output Utente'!$N$2:$N$492,">1") -> 37 | K10: =B10+C10+I10+J10 -> 148 | L10: =IFERROR($D10/$K10,"") -> 0.37162162
A11: C | B11: =COUNTIFS('Output Utente'!$B$2:$B$492,"C",'Output Utente'!$P$2:$P$492,"Top",'Output Utente'!$D$2:$D$492,"",'Output Utente'!$N$2:$N$492,">1") -> 18 | C11: =COUNTIFS('Output Utente'!$B$2:$B$492,"C",'Output Utente'!$P$2:$P$492,"Buono",'Output Utente'!$D$2:$D$492,"",'Output Utente'!$N$2:$N$492,">1") -> 37 | D11: =$B11+$C11 -> 55 | E11: ='Parametri Modello'!$D$34 -> 64 | F11: =IFERROR($D11/$E11,"") -> 0.859375 | G11: =IF($E11=0,"— (ruolo esaurito)",IF($F11>='Parametri Modello'!$B$46,"🟢 Puoi aspettare",IF($F11>='Parametri Modello'!$B$47,"🟡 Attesa rischiosa","🔴 Non aspettare"))) -> 🔴 Non aspettare | H11: =IFERROR(AVERAGEIFS('Output Utente'!$M$2:$M$492,'Output Utente'!$B$2:$B$492,"C",'Output Utente'!$D$2:$D$492,"<>"),"") | I11: =COUNTIFS('Output Utente'!$B$2:$B$492,"C",'Output Utente'!$P$2:$P$492,"Nella Media",'Output Utente'!$D$2:$D$492,"",'Output Utente'!$N$2:$N$492,">1") -> 49 | J11: =COUNTIFS('Output Utente'!$B$2:$B$492,"C",'Output Utente'!$P$2:$P$492,"Scommessa/Riserva",'Output Utente'!$D$2:$D$492,"",'Output Utente'!$N$2:$N$492,">1") -> 51 | K11: =B11+C11+I11+J11 -> 155 | L11: =IFERROR($D11/$K11,"") -> 0.35483871
A12: A | B12: =COUNTIFS('Output Utente'!$B$2:$B$492,"A",'Output Utente'!$P$2:$P$492,"Top",'Output Utente'!$D$2:$D$492,"",'Output Utente'!$N$2:$N$492,">1") -> 9 | C12: =COUNTIFS('Output Utente'!$B$2:$B$492,"A",'Output Utente'!$P$2:$P$492,"Buono",'Output Utente'!$D$2:$D$492,"",'Output Utente'!$N$2:$N$492,">1") -> 17 | D12: =$B12+$C12 -> 26 | E12: ='Parametri Modello'!$D$35 -> 48 | F12: =IFERROR($D12/$E12,"") -> 0.54166667 | G12: =IF($E12=0,"— (ruolo esaurito)",IF($F12>='Parametri Modello'!$B$46,"🟢 Puoi aspettare",IF($F12>='Parametri Modello'!$B$47,"🟡 Attesa rischiosa","🔴 Non aspettare"))) -> 🔴 Non aspettare | H12: =IFERROR(AVERAGEIFS('Output Utente'!$M$2:$M$492,'Output Utente'!$B$2:$B$492,"A",'Output Utente'!$D$2:$D$492,"<>"),"") | I12: =COUNTIFS('Output Utente'!$B$2:$B$492,"A",'Output Utente'!$P$2:$P$492,"Nella Media",'Output Utente'!$D$2:$D$492,"",'Output Utente'!$N$2:$N$492,">1") -> 28 | J12: =COUNTIFS('Output Utente'!$B$2:$B$492,"A",'Output Utente'!$P$2:$P$492,"Scommessa/Riserva",'Output Utente'!$D$2:$D$492,"",'Output Utente'!$N$2:$N$492,">1") -> 23 | K12: =B12+C12+I12+J12 -> 77 | L12: =IFERROR($D12/$K12,"") -> 0.33766234
A15: Nota: Top/Buoni sono la Fascia Aspettativa di Output Utente (posizione nel FVM di ruolo), non una previsione — quindi "Top rimasti" scende man mano che chiami giocatori di quella fascia, indipendentemente da chi li compra.

Sheet Info Lega
A2: Nome Lega | B2: Lega Amici | C2: Opzionale
A3: Numero di Partecipanti | B3: 8
A4: Budget Iniziale | B4: 1000
A5: Portieri Rosa | B5: 3
A6: Difensori Rosa | B6: 8
A7: Centrocampisti Rosa | B7: 8
A8: Attaccanti Rosa | B8: 6 | D8: Attiva
A9: Nome Squadra 1 | B9: xxx1 | D9: =IF(ROW()-8<=$B$3,"Si","No") -> Si
A10: Nome Squadra 2 | B10: xxx2 | D10: =IF(ROW()-8<=$B$3,"Si","No") -> Si
A11: Nome Squadra 3 | B11: xxx3 | D11: =IF(ROW()-8<=$B$3,"Si","No") -> Si
A12: Nome Squadra 4 | B12: xxx4 | D12: =IF(ROW()-8<=$B$3,"Si","No") -> Si
A13: Nome Squadra 5 | B13: xxx5 | D13: =IF(ROW()-8<=$B$3,"Si","No") -> Si
A14: Nome Squadra 6 | B14: xxx6 | D14: =IF(ROW()-8<=$B$3,"Si","No") -> Si
A15: Nome Squadra 7 | B15: xxx7 | D15: =IF(ROW()-8<=$B$3,"Si","No") -> Si
A16: Nome Squadra 8 | B16: xxx8 | D16: =IF(ROW()-8<=$B$3,"Si","No") -> Si
A17: Nome Squadra 9 | B17: xxx9 | D17: =IF(ROW()-8<=$B$3,"Si","No") -> No
A18: Nome Squadra 10 | B18: xxx10 | D18: =IF(ROW()-8<=$B$3,"Si","No") -> No
A19: Nome Squadra 11 | B19: xxx11 | D19: =IF(ROW()-8<=$B$3,"Si","No") -> No
A20: Nome Squadra 12 | B20: xxx12 | D20: =IF(ROW()-8<=$B$3,"Si","No") -> No
... A24: Nome Squadra 16 | B24: xxx16 | D24: =IF(ROW()-8<=$B$3,"Si","No") -> No
A25: Modificatore Difesa | B25: Si
A26: Modificatore Centrocampo | B26: No
A27: Regole chiamata giocatori | B27: A Chiamata Libera
A28: La Mia Squadra | B28: xxx1 | C28: Seleziona il tuo nome squadra dalla lista sopra (B9:B24)

Sheet Info Strategia
A1: Modulo Preferito | B1: 3-4-3 | D1: Lista Giocatori Preferiti (nome esatto come in Input Giocatori)
A2: D | B2: =MID(B1,1,1) -> 3
A3: C | B3: =MID(B1,3,1) -> 4
A4: A | B4: =MID(B1,5,1) -> 3
A5: Giocatori Preferiti
A6: Aggressivita | B6: 0.7

Sheet Parametri Modello
A1: PARAMETRI MOTORE DI PRICING
A3: Budget Base Listone (standard Fantacalcio.it) | B3: 500 | C3: Le quotazioni Qt.A del listone sono tarate su un budget standard di 500 crediti e una rosa 3P-8D-8C-6A. I prezzi vengono riscalati sul tuo Budget Iniziale (Info Lega!B4).
A5: Boost Modificatore Ruolo (%) | B5: 0.15 | C5: Se attivo il Modificatore Difesa o Centrocampo (Info Lega), il prezzo base del ruolo interessato viene aumentato di questa percentuale.
A7: Boost Whichlist / Preferiti (%) | B7: 0.15 | C7: Boost MASSIMO applicato all'Offerta Max se il giocatore e' whichlist. Ora scala con l'Aggressivita' (Info Strategia!B6): aggressivita'=0 -> nessun sovrapprezzo, aggressivita'=1 -> boost pieno.
A9: Peso Performance Storica (Fantamedia vs media ruolo, %) | B9: 0.2 | C9: Quanto la Fantamedia reale 2025/26 (rispetto alla media di ruolo) sposta il prezzo in piu' o in meno. 0% = ignora la storia, guarda solo il mercato. Il fattore e' limitato a +/-25% per non far esplodere i prezzi su piccoli campioni.
A10: Ampiezza range di valutazione per ruolo (Spread %)
A11: Ruolo | B11: Spread %
A12: P | B12: 0.15
A13: D | B13: 0.2
A14: C | B14: 0.25
A15: A | B15: 0.3
C16: Spread = quanto Valutazione Min/Max si allontanano dal prezzo base scalato. Ruoli piu' cari (A, C) hanno piu' varianza di mercato.
A17: Fantamedia media per ruolo (calcolata sui giocatori con dati storici) | C17: Media della Fantamedia per ruolo, calcolata solo sui giocatori che raggiungono la soglia minima di presenze.
A18: Ruolo | B18: Fantamedia Media
A19: P | B19: =IFERROR(AVERAGEIFS('Output Utente'!$T$2:$T$492,'Output Utente'!$B$2:$B$492,"P",'Output Utente'!$T$2:$T$492,"<>",'Output Utente'!$I$2:$I$492,">="&$B$23),"") -> 5.1494444
A20: D | B20: =IFERROR(AVERAGEIFS('Output Utente'!$T$2:$T$492,'Output Utente'!$B$2:$B$492,"D",'Output Utente'!$T$2:$T$492,"<>",'Output Utente'!$I$2:$I$492,">="&$B$23),"") -> 6.0221101
A21: C | B21: =IFERROR(AVERAGEIFS('Output Utente'!$T$2:$T$492,'Output Utente'!$B$2:$B$492,"C",'Output Utente'!$T$2:$T$492,"<>",'Output Utente'!$I$2:$I$492,">="&$B$23),"") -> 6.2805042
A22: A | B22: =IFERROR(AVERAGEIFS('Output Utente'!$T$2:$T$492,'Output Utente'!$B$2:$B$492,"A",'Output Utente'!$T$2:$T$492,"<>",'Output Utente'!$I$2:$I$492,">="&$B$23),"") -> 6.6667857
A23: Presenze minime per storico (media/performance) | B23: 10 | C23: Un giocatore con meno di questa soglia di presenze non influenza la Fantamedia media del ruolo e non riceve bonus/malus dalla performance storica. La soglia e' modificabile.
A24: Soglia 'OK' (x credito medio per slot rimanente) | B24: 1.5 | C24: Sotto la soglia OK: offerta compatibile col ritmo di spesa che ti puoi permettere. Tra OK e Attenzione: fattibile ma ti restringe le prossime chiamate. Sopra: rischi di restare senza budget per gli slot che mancano.
A25: Soglia 'Attenzione' (x credito medio per slot rimanente) | B25: 3
A27: Fattore Scarsità di Ruolo attivo (Si/No) | B27: Si | C27: Confronta, per ogni ruolo, quanti giocatori disponibili restano rispetto agli slot ancora da riempire in tutta la lega. I giocatori con Qt.A=1 possono essere esclusi dal conteggio tramite il parametro dedicato. Il rapporto si aggiorna quando assegni giocatori in Output Utente.
A28: Peso massimo Scarsità (premio/sconto max, %) | B28: 0.3
A29: Escludi Qt.A=1 dalla scarsita' (Si/No) | B29: Si | C29: Se attivo, i giocatori con Qt.A=1 e ancora non assegnati non vengono conteggiati tra i giocatori disponibili per il calcolo della scarsita'. Restano comunque visibili nel listone.
A30: Riserva minima per slot (crediti) | B30: 1 | C30: Crediti minimi da conservare per ogni slot ancora da riempire. Con base d'asta a 1, il minimo teorico è 1 credito per slot.
A31: Max Bid dinamico | B31: ATTIVO | C31: Il Max Bid dinamico viene limitato dal budget realmente spendibile: Budget residuo meno la riserva minima necessaria per tutti gli slot ancora vuoti. | D31: Slot Ancora da Riempire | E31: Giocatori Liberi nel Listone | F31: Rapporto Off./Dom.
A32: P | B32: ='Info Lega'!$B$3*'Info Lega'!$B$5 -> 24 | C32: =COUNTIFS('Output Utente'!$B$2:$B$492,"P",'Output Utente'!$D$2:$D$492,"<>") -> 0 | D32: =$B32-$C32 -> 24 | E32: =IF($B$29="Si",COUNTIFS('Output Utente'!$B$2:$B$492,"P",'Output Utente'!$D$2:$D$492,"",'Output Utente'!$N$2:$N$492,">1"),COUNTIFS('Output Utente'!$B$2:$B$492,"P",'Output Utente'!$D$2:$D$492,"")) -> 24 | F32: =IFERROR($E32/$D32,"") -> 1
A33: D | B33: ='Info Lega'!$B$3*'Info Lega'!$B$6 -> 64 | C33: =COUNTIFS('Output Utente'!$B$2:$B$492,"D",'Output Utente'!$D$2:$D$492,"<>") -> 0 | D33: =$B33-$C33 -> 64 | E33: =IF($B$29="Si",COUNTIFS('Output Utente'!$B$2:$B$492,"D",'Output Utente'!$D$2:$D$492,"",'Output Utente'!$N$2:$N$492,">1"),COUNTIFS('Output Utente'!$B$2:$B$492,"D",'Output Utente'!$D$2:$D$492,"")) -> 148 | F33: =IFERROR($E33/$D33,"") -> 2.3125
A34: C | B34: ='Info Lega'!$B$3*'Info Lega'!$B$7 -> 64 | C34: =COUNTIFS('Output Utente'!$B$2:$B$492,"C",'Output Utente'!$D$2:$D$492,"<>") -> 0 | D34: =$B34-$C34 -> 64 | E34: =IF($B$29="Si",COUNTIFS('Output Utente'!$B$2:$B$492,"C",'Output Utente'!$D$2:$D$492,"",'Output Utente'!$N$2:$N$492,">1"),COUNTIFS('Output Utente'!$B$2:$B$492,"C",'Output Utente'!$D$2:$D$492,"")) -> 155 | F34: =IFERROR($E34/$D34,"") -> 2.421875
A35: A | B35: ='Info Lega'!$B$3*'Info Lega'!$B$8 -> 48 | C35: =COUNTIFS('Output Utente'!$B$2:$B$492,"A",'Output Utente'!$D$2:$D$492,"<>") -> 0 | D35: =$B35-$C35 -> 48 | E35: =IF($B$29="Si",COUNTIFS('Output Utente'!$B$2:$B$492,"A",'Output Utente'!$D$2:$D$492,"",'Output Utente'!$N$2:$N$492,">1"),COUNTIFS('Output Utente'!$B$2:$B$492,"A",'Output Utente'!$D$2:$D$492,"")) -> 77 | F35: =IFERROR($E35/$D35,"") -> 1.6041667
A37: Base di prezzo: pool FVM proporzionale al budget di lega | C37: Pool FVM: per ogni ruolo prende tutti i giocatori fino alla soglia del N-esimo FVM (N = slot totali di quel ruolo nella lega). In caso di pari FVM sulla soglia, tutti i giocatori a pari FVM entrano nel pool. Questo evita un tie-break arbitrario.
A38: Ruolo | B38: Slot Totali Lega | C38: Somma FVM Pool
A39: P | B39: =$B$32 -> 24 | C39: =SUMIFS('Output Utente'!$O$2:$O$492,'Output Utente'!$B$2:$B$492,"P",'Output Utente'!$V$2:$V$492,"<="&$B39) -> 689
A40: D | B40: =$B$33 -> 64 | C40: =SUMIFS('Output Utente'!$O$2:$O$492,'Output Utente'!$B$2:$B$492,"D",'Output Utente'!$V$2:$V$492,"<="&$B40) -> 1998
A41: C | B41: =$B$34 -> 64 | C41: =SUMIFS('Output Utente'!$O$2:$O$492,'Output Utente'!$B$2:$B$492,"C",'Output Utente'!$V$2:$V$492,"<="&$B41) -> 3678
A42: A | B42: =$B$35 -> 48 | C42: =SUMIFS('Output Utente'!$O$2:$O$492,'Output Utente'!$B$2:$B$492,"A",'Output Utente'!$V$2:$V$492,"<="&$B42) -> 4604
A43: Somma FVM Pool TOTALE (tutti i ruoli, denominatore comune) | B43: =SUM($C$39:$C$42) -> 10969 | C43: Correzione: ogni ruolo deve condividere lo stesso budget di lega, non riceverne uno intero a testa. Questa e' la somma di TUTTI i pool per ruolo, usata come denominatore comune.
A44: Budget Totale Lega (Numero Partecipanti x Budget Iniziale) | B44: ='Info Lega'!$B$3*'Info Lega'!$B$4 -> 8000
A46: Soglia Pressione VERDE (Top+Buoni rimasti / slot residui lega, >=) | B46: 2 | C46: Sotto la soglia gialla: Pressione ROSSA (non aspettare). Esempio ChatGPT: 7 Top/Buoni per 3 slot=2.33 (verde), 4 per 3=1.33 (giallo), 2 per 3=0.67 (rosso).
A47: Soglia Pressione GIALLA (>=) | B47: 1
A48: Target storico % budget per ruolo (calibrato su aste reali) | C48: Fonte: Rose_fantalba 2023 e 2025 (dati reali, 8 squadre, 16 aste-ruolo). Sostituisce la distribuzione derivata dal solo FVM, che sovrastimava i difensori (18%->reale 11.6%) e sottostimava portieri e attaccanti.
A49: Ruolo | B49: % Budget Target (storico)
A50: P | B50: 0.093
A51: D | B51: 0.116
A52: C | B52: 0.278
A53: A | B53: 0.515
A55: Modello a due livelli: Titolari vs Riserve (calibrato su aste reali 2023+2025) | C55: Nelle aste reali l'85-96% del budget di ruolo va ai 'titolari' (i migliori N per FVM, N = squadre x titolari-per-ruolo dal modulo preferito). Le riserve costano quasi niente indipendentemente dal loro FVM. Sostituisce la distribuzione proporzionale unica.
A56: Ruolo | B56: Titolari per Squadra | C56: N Titolari Lega | D56: % Budget Ruolo ai Titolari | E56: Somma FVM Titolari | F56: Somma FVM Riserve
A57: P | B57: =1 -> 1 | C57: ='Info Lega'!$B$3*$B57 -> 8 | D57: 0.88 | E57: =SUMIFS('Output Utente'!$O$2:$O$492,'Output Utente'!$B$2:$B$492,"P",'Output Utente'!$V$2:$V$492,"<="&$C57) -> 416 | F57: =$C$39-$E57 -> 273
A58: D | B58: ='Info Strategia'!$B$2 -> 3 | C58: ='Info Lega'!$B$3*$B58 -> 24 | D58: 0.85 | E58: =SUMIFS('Output Utente'!$O$2:$O$492,'Output Utente'!$B$2:$B$492,"D",'Output Utente'!$V$2:$V$492,"<="&$C58) -> 1196 | F58: =$C$40-$E58 -> 802
A59: C | B59: ='Info Strategia'!$B$3 -> 4 | C59: ='Info Lega'!$B$3*$B59 -> 32 | D59: 0.95 | E59: =SUMIFS('Output Utente'!$O$2:$O$492,'Output Utente'!$B$2:$B$492,"C",'Output Utente'!$V$2:$V$492,"<="&$C59) -> 2897 | F59: =$C$41-$E59 -> 781
A60: A | B60: ='Info Strategia'!$B$4 -> 3 | C60: ='Info Lega'!$B$3*$B60 -> 24 | D60: 0.93 | E60: =SUMIFS('Output Utente'!$O$2:$O$492,'Output Utente'!$B$2:$B$492,"A",'Output Utente'!$V$2:$V$492,"<="&$C60) -> 3713 | F60: =$C$42-$E60 -> 891
A62: SOGLIE FASCIA QUALITATIVA (percentile del FVM nel ruolo) | C62: Determinano la Fascia Aspettativa (TOP/BUONO/MEDIA/SCOMMESSA) in 'Output Utente'. Basate su percentile, non su valori assoluti: funzionano anche se cambia il listone.
A63: Percentile minimo TOP (>=) | B63: 0.9 | C63: Es. 0.90 = miglior 10% del ruolo per FVM.
A64: Percentile minimo BUONO (>=) | B64: 0.7 | C64: Tra questa soglia e quella TOP.
A65: Percentile minimo MEDIA (>=) | B65: 0.4 | C65: Sotto questa soglia: SCOMMESSA. Tutte e tre le soglie sono modificabili.
A67: OPPORTUNITY GAP - soglie segnale (in 'Output Utente' e 'Decisione Live') | C67: Gap = Offerta Max Dinamica - Prezzo Attuale. Segnala se il prezzo in asta e' un'opportunita' o un sovrapprezzo rispetto al TUO tetto (non rispetto al FVM).
A68: Soglia Verde: Gap >= % della Offerta Max Dinamica | B68: 0.15 | C68: Sopra: opportunita' (verde). Sotto zero: hai superato il tuo tetto (rosso).
A69: Soglia Rossa: Gap <= % della Offerta Max Dinamica | B69: 0 | C69: Tra le due soglie: prezzo corretto (giallo).
A71: PRESSIONE COMPETITIVA (informativa - NON altera il FVM o l'Offerta Max) | C71: Stima quante squadre avversarie hanno ancora bisogno di un TITOLARE in quel ruolo e quanto budget hanno disponibile. Vedi foglio 'Pressione Competitiva'.
A72: Ruolo | B72: Titolari Standard Assunti per Squadre Avversarie
A73: P | B73: 1 | C73: Fisso: ogni squadra gioca 1 portiere titolare a giornata.
A74: D | B74: ='Info Strategia'!$B$2 -> 3 | C74: Assunzione: le avversarie cercano un numero di titolari per ruolo comparabile al TUO modulo (dato reale non osservabile). Modificabile con un numero fisso se preferisci.
A75: C | B75: ='Info Strategia'!$B$3 -> 4
A76: A | B76: ='Info Strategia'!$B$4 -> 3
A78: Soglia N Squadre Bisognose per Pressione ALTA (>=) | B78: 2 | C78: 2+ squadre ancora a caccia di un titolare nello stesso ruolo = pressione competitiva concreta.
A79: Soglia Budget Medio Disponibile (di quelle squadre) per MOLTO ALTA (>=, crediti) | B79: 150 | C79: Se le squadre bisognose hanno anche molto budget, la pressione sale a MOLTO ALTA.
A81: VERSIONE MOTORE | B81: FantaAuction Engine — Cowork Final | C81: Vedi 'Guida' > Versione / Log delle modifiche per il dettaglio.

Sheet Pressione Competitiva
A1: PRESSIONE COMPETITIVA — quante avversarie cercano ancora un titolare di ruolo, e con quanto budget
B2: Ruolo | C2: N Squadre Bisognose (titolare, escl. te) | D2: Budget Disponibile Combinato | E2: Budget Medio Disponibile | F2: Pressione Competitiva | G2: Motivo
B3: P | C3: =SUMPRODUCT((TeamDetail!$D$2:$D$17="Si")*(TeamDetail!$C$2:$C$17<>'Info Lega'!$B$28)*(TeamDetail!$F$2:$F$17>0)) -> 7 | D3: =ROUND(SUMPRODUCT((TeamDetail!$D$2:$D$17="Si")*(TeamDetail!$C$2:$C$17<>'Info Lega'!$B$28)*(TeamDetail!$F$2:$F$17>0)*TeamDetail!$E$2:$E$17),0) -> 7000 | E3: =IFERROR(ROUND($D3/$C3,0),"") -> 1000 | F3: =IF($C3=0,"🟢 Bassa",IF(AND($C3>='Parametri Modello'!$B$78,$D3/MAX(1,$C3)>='Parametri Modello'!$B$79),"🔴 Molto Alta",IF($C3>='Parametri Modello'!$B$78,"🟠 Alta","🟡 Media"))) -> 🔴 Molto Alta | G3: =IF($C3=0,"Nessuna avversaria (attiva) sembra ancora a caccia di un titolare "&$B3&".",$C3&" squadr"&IF($C3=1,"a","e")&" cerca"&IF($C3=1,"","no")&" ancora un titolare "&$B3&", con "&$D3&" crediti disponibili in totale (media "&$E3&"/squadra).") -> 7 squadre cercano ancora un titolare P, con 7000 crediti disponibili in totale (media 1000/squadra).
B4: D | C4: =SUMPRODUCT((TeamDetail!$D$2:$D$17="Si")*(TeamDetail!$C$2:$C$17<>'Info Lega'!$B$28)*(TeamDetail!$G$2:$G$17>0)) -> 7 | D4: =ROUND(SUMPRODUCT((TeamDetail!$D$2:$D$17="Si")*(TeamDetail!$C$2:$C$17<>'Info Lega'!$B$28)*(TeamDetail!$G$2:$G$17>0)*TeamDetail!$E$2:$E$17),0) -> 7000 | E4: =IFERROR(ROUND($D4/$C4,0),"") -> 1000 | F4: =IF($C4=0,"🟢 Bassa",IF(AND($C4>='Parametri Modello'!$B$78,$D4/MAX(1,$C4)>='Parametri Modello'!$B$79),"🔴 Molto Alta",IF($C4>='Parametri Modello'!$B$78,"🟠 Alta","🟡 Media"))) -> 🔴 Molto Alta | G4: =IF($C4=0,"Nessuna avversaria (attiva) sembra ancora a caccia di un titolare "&$B4&".",$C4&" squadr"&IF($C4=1,"a","e")&" cerca"&IF($C4=1,"","no")&" ancora un titolare "&$B4&", con "&$D4&" crediti disponibili in totale (media "&$E4&"/squadra).") -> 7 squadre cercano ancora un titolare D, con 7000 crediti disponibili in totale (media 1000/squadra).
B5: C | C5: =SUMPRODUCT((TeamDetail!$D$2:$D$17="Si")*(TeamDetail!$C$2:$C$17<>'Info Lega'!$B$28)*(TeamDetail!$H$2:$H$17>0)) -> 7 | D5: =ROUND(SUMPRODUCT((TeamDetail!$D$2:$D$17="Si")*(TeamDetail!$C$2:$C$17<>'Info Lega'!$B$28)*(TeamDetail!$H$2:$H$17>0)*TeamDetail!$E$2:$E$17),0) -> 7000 | E5: =IFERROR(ROUND($D5/$C5,0),"") -> 1000 | F5: =IF($C5=0,"🟢 Bassa",IF(AND($C5>='Parametri Modello'!$B$78,$D5/MAX(1,$C5)>='Parametri Modello'!$B$79),"🔴 Molto Alta",IF($C5>='Parametri Modello'!$B$78,"🟠 Alta","🟡 Media"))) -> 🔴 Molto Alta | G5: =IF($C5=0,"Nessuna avversaria (attiva) sembra ancora a caccia di un titolare "&$B5&".",$C5&" squadr"&IF($C5=1,"a","e")&" cerca"&IF($C5=1,"","no")&" ancora un titolare "&$B5&", con "&$D5&" crediti disponibili in totale (media "&$E5&"/squadra).") -> 7 squadre cercano ancora un titolare C, con 7000 crediti disponibili in totale (media 1000/squadra).
B6: A | C6: =SUMPRODUCT((TeamDetail!$D$2:$D$17="Si")*(TeamDetail!$C$2:$C$17<>'Info Lega'!$B$28)*(TeamDetail!$I$2:$I$17>0)) -> 7 | D6: =ROUND(SUMPRODUCT((TeamDetail!$D$2:$D$17="Si")*(TeamDetail!$C$2:$C$17<>'Info Lega'!$B$28)*(TeamDetail!$I$2:$I$17>0)*TeamDetail!$E$2:$E$17),0) -> 7000 | E6: =IFERROR(ROUND($D6/$C6,0),"") -> 1000 | F6: =IF($C6=0,"🟢 Bassa",IF(AND($C6>='Parametri Modello'!$B$78,$D6/MAX(1,$C6)>='Parametri Modello'!$B$79),"🔴 Molto Alta",IF($C6>='Parametri Modello'!$B$78,"🟠 Alta","🟡 Media"))) -> 🔴 Molto Alta | G6: =IF($C6=0,"Nessuna avversaria (attiva) sembra ancora a caccia di un titolare "&$B6&".",$C6&" squadr"&IF($C6=1,"a","e")&" cerca"&IF($C6=1,"","no")&" ancora un titolare "&$B6&", con "&$D6&" crediti disponibili in totale (media "&$E6&"/squadra).") -> 7 squadre cercano ancora un titolare A, con 7000 crediti disponibili in totale (media 1000/squadra).

Sheet TeamDetail
A1: # | B1: Slot Residui Tot. | C1: Nome Squadra | D1: Attiva | E1: Budget Residuo | F1: Mancanti P (titolare) | G1: Mancanti D (titolare) | H1: Mancanti C (titolare) | I1: Mancanti A (titolare)
A2: 1 | B2: =('Info Lega'!$B$5-COUNTIFS('Output Utente'!$D$2:$D$492,$C2,'Output Utente'!$B$2:$B$492,"P"))+('Info Lega'!$B$6-COUNTIFS('Output Utente'!$D$2:$D$492,$C2,'Output Utente'!$B$2:$B$492,"D"))+('Info Lega'!$B$7-COUNTIFS('Output Utente'!$D$2:$D$492,$C2,'Output Utente'!$B$2:$B$492,"C"))+('Info Lega'!$B$8-COUNTIFS('Output Utente'!$D$2:$D$492,$C2,'Output Utente'!$B$2:$B$492,"A")) -> 25 | C2: ='Info Lega'!$B$9 -> xxx1 | D2: ='Info Lega'!$D$9 -> Si | E2: ='Info Lega'!$B$4-SUMIFS('Output Utente'!$M$2:$M$492,'Output Utente'!$D$2:$D$492,$C2) -> 1000 | F2: =MAX(0,'Parametri Modello'!$B$73-COUNTIFS('Output Utente'!$D$2:$D$492,$C2,'Output Utente'!$B$2:$B$492,"P",'Output Utente'!$AF$2:$AF$492,"Titolare")) -> 1 | G2: =MAX(0,'Parametri Modello'!$B$74-COUNTIFS('Output Utente'!$D$2:$D$492,$C2,'Output Utente'!$B$2:$B$492,"D",'Output Utente'!$AF$2:$AF$492,"Titolare")) -> 3 | H2: =MAX(0,'Parametri Modello'!$B$75-COUNTIFS('Output Utente'!$D$2:$D$492,$C2,'Output Utente'!$B$2:$B$492,"C",'Output Utente'!$AF$2:$AF$492,"Titolare")) -> 4 | I2: =MAX(0,'Parametri Modello'!$B$76-COUNTIFS('Output Utente'!$D$2:$D$492,$C2,'Output Utente'!$B$2:$B$492,"A",'Output Utente'!$AF$2:$AF$492,"Titolare")) -> 3
A3: 2 | B3: =('Info Lega'!$B$5-COUNTIFS('Output Utente'!$D$2:$D$492,$C3,'Output Utente'!$B$2:$B$492,"P"))+('Info Lega'!$B$6-COUNTIFS('Output Utente'!$D$2:$D$492,$C3,'Output Utente'!$B$2:$B$492,"D"))+('Info Lega'!$B$7-COUNTIFS('Output Utente'!$D$2:$D$492,$C3,'Output Utente'!$B$2:$B$492,"C"))+('Info Lega'!$B$8-COUNTIFS('Output Utente'!$D$2:$D$492,$C3,'Output Utente'!$B$2:$B$492,"A")) -> 25 | C3: ='Info Lega'!$B$10 -> xxx2 | D3: ='Info Lega'!$D$10 -> Si | E3: ='Info Lega'!$B$4-SUMIFS('Output Utente'!$M$2:$M$492,'Output Utente'!$D$2:$D$492,$C3) -> 1000 | F3: =MAX(0,'Parametri Modello'!$B$73-COUNTIFS('Output Utente'!$D$2:$D$492,$C3,'Output Utente'!$B$2:$B$492,"P",'Output Utente'!$AF$2:$AF$492,"Titolare")) -> 1 | G3: =MAX(0,'Parametri Modello'!$B$74-COUNTIFS('Output Utente'!$D$2:$D$492,$C3,'Output Utente'!$B$2:$B$492,"D",'Output Utente'!$AF$2:$AF$492,"Titolare")) -> 3 | H3: =MAX(0,'Parametri Modello'!$B$75-COUNTIFS('Output Utente'!$D$2:$D$492,$C3,'Output Utente'!$B$2:$B$492,"C",'Output Utente'!$AF$2:$AF$492,"Titolare")) -> 4 | I3: =MAX(0,'Parametri Modello'!$B$76-COUNTIFS('Output Utente'!$D$2:$D$492,$C3,'Output Utente'!$B$2:$B$492,"A",'Output Utente'!$AF$2:$AF$492,"Titolare")) -> 3
A4: 3 | B4: =('Info Lega'!$B$5-COUNTIFS('Output Utente'!$D$2:$D$492,$C4,'Output Utente'!$B$2:$B$492,"P"))+('Info Lega'!$B$6-COUNTIFS('Output Utente'!$D$2:$D$492,$C4,'Output Utente'!$B$2:$B$492,"D"))+('Info Lega'!$B$7-COUNTIFS('Output Utente'!$D$2:$D$492,$C4,'Output Utente'!$B$2:$B$492,"C"))+('Info Lega'!$B$8-COUNTIFS('Output Utente'!$D$2:$D$492,$C4,'Output Utente'!$B$2:$B$492,"A")) -> 25 | C4: ='Info Lega'!$B$11 -> xxx3 | D4: ='Info Lega'!$D$11 -> Si | E4: ='Info Lega'!$B$4-SUMIFS('Output Utente'!$M$2:$M$492,'Output Utente'!$D$2:$D$492,$C4) -> 1000 | F4: =MAX(0,'Parametri Modello'!$B$73-COUNTIFS('Output Utente'!$D$2:$D$492,$C4,'Output Utente'!$B$2:$B$492,"P",'Output Utente'!$AF$2:$AF$492,"Titolare")) -> 1 | G4: =MAX(0,'Parametri Modello'!$B$74-COUNTIFS('Output Utente'!$D$2:$D$492,$C4,'Output Utente'!$B$2:$B$492,"D",'Output Utente'!$AF$2:$AF$492,"Titolare")) -> 3 | H4: =MAX(0,'Parametri Modello'!$B$75-COUNTIFS('Output Utente'!$D$2:$D$492,$C4,'Output Utente'!$B$2:$B$492,"C",'Output Utente'!$AF$2:$AF$492,"Titolare")) -> 4 | I4: =MAX(0,'Parametri Modello'!$B$76-COUNTIFS('Output Utente'!$D$2:$D$492,$C4,'Output Utente'!$B$2:$B$492,"A",'Output Utente'!$AF$2:$AF$492,"Titolare")) -> 3
A5: 4 | B5: =('Info Lega'!$B$5-COUNTIFS('Output Utente'!$D$2:$D$492,$C5,'Output Utente'!$B$2:$B$492,"P"))+('Info Lega'!$B$6-COUNTIFS('Output Utente'!$D$2:$D$492,$C5,'Output Utente'!$B$2:$B$492,"D"))+('Info Lega'!$B$7-COUNTIFS('Output Utente'!$D$2:$D$492,$C5,'Output Utente'!$B$2:$B$492,"C"))+('Info Lega'!$B$8-COUNTIFS('Output Utente'!$D$2:$D$492,$C5,'Output Utente'!$B$2:$B$492,"A")) -> 25 | C5: ='Info Lega'!$B$12 -> xxx4 | D5: ='Info Lega'!$D$12 -> Si | E5: ='Info Lega'!$B$4-SUMIFS('Output Utente'!$M$2:$M$492,'Output Utente'!$D$2:$D$492,$C5) -> 1000 | F5: =MAX(0,'Parametri Modello'!$B$73-COUNTIFS('Output Utente'!$D$2:$D$492,$C5,'Output Utente'!$B$2:$B$492,"P",'Output Utente'!$AF$2:$AF$492,"Titolare")) -> 1 | G5: =MAX(0,'Parametri Modello'!$B$74-COUNTIFS('Output Utente'!$D$2:$D$492,$C5,'Output Utente'!$B$2:$B$492,"D",'Output Utente'!$AF$2:$AF$492,"Titolare")) -> 3 | H5: =MAX(0,'Parametri Modello'!$B$75-COUNTIFS('Output Utente'!$D$2:$D$492,$C5,'Output Utente'!$B$2:$B$492,"C",'Output Utente'!$AF$2:$AF$492,"Titolare")) -> 4 | I5: =MAX(0,'Parametri Modello'!$B$76-COUNTIFS('Output Utente'!$D$2:$D$492,$C5,'Output Utente'!$B$2:$B$492,"A",'Output Utente'!$AF$2:$AF$492,"Titolare")) -> 3
A6: 5 | B6: =('Info Lega'!$B$5-COUNTIFS('Output Utente'!$D$2:$D$492,$C6,'Output Utente'!$B$2:$B$492,"P"))+('Info Lega'!$B$6-COUNTIFS('Output Utente'!$D$2:$D$492,$C6,'Output Utente'!$B$2:$B$492,"D"))+('Info Lega'!$B$7-COUNTIFS('Output Utente'!$D$2:$D$492,$C6,'Output Utente'!$B$2:$B$492,"C"))+('Info Lega'!$B$8-COUNTIFS('Output Utente'!$D$2:$D$492,$C6,'Output Utente'!$B$2:$B$492,"A")) -> 25 | C6: ='Info Lega'!$B$13 -> xxx5 | D6: ='Info Lega'!$D$13 -> Si | E6: ='Info Lega'!$B$4-SUMIFS('Output Utente'!$M$2:$M$492,'Output Utente'!$D$2:$D$492,$C6) -> 1000 | F6: =MAX(0,'Parametri Modello'!$B$73-COUNTIFS('Output Utente'!$D$2:$D$492,$C6,'Output Utente'!$B$2:$B$492,"P",'Output Utente'!$AF$2:$AF$492,"Titolare")) -> 1 | G6: =MAX(0,'Parametri Modello'!$B$74-COUNTIFS('Output Utente'!$D$2:$D$492,$C6,'Output Utente'!$B$2:$B$492,"D",'Output Utente'!$AF$2:$AF$492,"Titolare")) -> 3 | H6: =MAX(0,'Parametri Modello'!$B$75-COUNTIFS('Output Utente'!$D$2:$D$492,$C6,'Output Utente'!$B$2:$B$492,"C",'Output Utente'!$AF$2:$AF$492,"Titolare")) -> 4 | I6: =MAX(0,'Parametri Modello'!$B$76-COUNTIFS('Output Utente'!$D$2:$D$492,$C6,'Output Utente'!$B$2:$B$492,"A",'Output Utente'!$AF$2:$AF$492,"Titolare")) -> 3
A7: 6 | B7: =('Info Lega'!$B$5-COUNTIFS('Output Utente'!$D$2:$D$492,$C7,'Output Utente'!$B$2:$B$492,"P"))+('Info Lega'!$B$6-COUNTIFS('Output Utente'!$D$2:$D$492,$C7,'Output Utente'!$B$2:$B$492,"D"))+('Info Lega'!$B$7-COUNTIFS('Output Utente'!$D$2:$D$492,$C7,'Output Utente'!$B$2:$B$492,"C"))+('Info Lega'!$B$8-COUNTIFS('Output Utente'!$D$2:$D$492,$C7,'Output Utente'!$B$2:$B$492,"A")) -> 25 | C7: ='Info Lega'!$B$14 -> xxx6 | D7: ='Info Lega'!$D$14 -> Si | E7: ='Info Lega'!$B$4-SUMIFS('Output Utente'!$M$2:$M$492,'Output Utente'!$D$2:$D$492,$C7) -> 1000 | F7: =MAX(0,'Parametri Modello'!$B$73-COUNTIFS('Output Utente'!$D$2:$D$492,$C7,'Output Utente'!$B$2:$B$492,"P",'Output Utente'!$AF$2:$AF$492,"Titolare")) -> 1 | G7: =MAX(0,'Parametri Modello'!$B$74-COUNTIFS('Output Utente'!$D$2:$D$492,$C7,'Output Utente'!$B$2:$B$492,"D",'Output Utente'!$AF$2:$AF$492,"Titolare")) -> 3 | H7: =MAX(0,'Parametri Modello'!$B$75-COUNTIFS('Output Utente'!$D$2:$D$492,$C7,'Output Utente'!$B$2:$B$492,"C",'Output Utente'!$AF$2:$AF$492,"Titolare")) -> 4 | I7: =MAX(0,'Parametri Modello'!$B$76-COUNTIFS('Output Utente'!$D$2:$D$492,$C7,'Output Utente'!$B$2:$B$492,"A",'Output Utente'!$AF$2:$AF$492,"Titolare")) -> 3
A8: 7 | B8: =('Info Lega'!$B$5-COUNTIFS('Output Utente'!$D$2:$D$492,$C8,'Output Utente'!$B$2:$B$492,"P"))+('Info Lega'!$B$6-COUNTIFS('Output Utente'!$D$2:$D$492,$C8,'Output Utente'!$B$2:$B$492,"D"))+('Info Lega'!$B$7-COUNTIFS('Output Utente'!$D$2:$D$492,$C8,'Output Utente'!$B$2:$B$492,"C"))+('Info Lega'!$B$8-COUNTIFS('Output Utente'!$D$2:$D$492,$C8,'Output Utente'!$B$2:$B$492,"A")) -> 25 | C8: ='Info Lega'!$B$15 -> xxx7 | D8: ='Info Lega'!$D$15 -> Si | E8: ='Info Lega'!$B$4-SUMIFS('Output Utente'!$M$2:$M$492,'Output Utente'!$D$2:$D$492,$C8) -> 1000 | F8: =MAX(0,'Parametri Modello'!$B$73-COUNTIFS('Output Utente'!$D$2:$D$492,$C8,'Output Utente'!$B$2:$B$492,"P",'Output Utente'!$AF$2:$AF$492,"Titolare")) -> 1 | G8: =MAX(0,'Parametri Modello'!$B$74-COUNTIFS('Output Utente'!$D$2:$D$492,$C8,'Output Utente'!$B$2:$B$492,"D",'Output Utente'!$AF$2:$AF$492,"Titolare")) -> 3 | H8: =MAX(0,'Parametri Modello'!$B$75-COUNTIFS('Output Utente'!$D$2:$D$492,$C8,'Output Utente'!$B$2:$B$492,"C",'Output Utente'!$AF$2:$AF$492,"Titolare")) -> 4 | I8: =MAX(0,'Parametri Modello'!$B$76-COUNTIFS('Output Utente'!$D$2:$D$492,$C8,'Output Utente'!$B$2:$B$492,"A",'Output Utente'!$AF$2:$AF$492,"Titolare")) -> 3
A9: 8 | B9: =('Info Lega'!$B$5-COUNTIFS('Output Utente'!$D$2:$D$492,$C9,'Output Utente'!$B$2:$B$492,"P"))+('Info Lega'!$B$6-COUNTIFS('Output Utente'!$D$2:$D$492,$C9,'Output Utente'!$B$2:$B$492,"D"))+('Info Lega'!$B$7-COUNTIFS('Output Utente'!$D$2:$D$492,$C9,'Output Utente'!$B$2:$B$492,"C"))+('Info Lega'!$B$8-COUNTIFS('Output Utente'!$D$2:$D$492,$C9,'Output Utente'!$B$2:$B$492,"A")) -> 25 | C9: ='Info Lega'!$B$16 -> xxx8 | D9: ='Info Lega'!$D$16 -> Si | E9: ='Info Lega'!$B$4-SUMIFS('Output Utente'!$M$2:$M$492,'Output Utente'!$D$2:$D$492,$C9) -> 1000 | F9: =MAX(0,'Parametri Modello'!$B$73-COUNTIFS('Output Utente'!$D$2:$D$492,$C9,'Output Utente'!$B$2:$B$492,"P",'Output Utente'!$AF$2:$AF$492,"Titolare")) -> 1 | G9: =MAX(0,'Parametri Modello'!$B$74-COUNTIFS('Output Utente'!$D$2:$D$492,$C9,'Output Utente'!$B$2:$B$492,"D",'Output Utente'!$AF$2:$AF$492,"Titolare")) -> 3 | H9: =MAX(0,'Parametri Modello'!$B$75-COUNTIFS('Output Utente'!$D$2:$D$492,$C9,'Output Utente'!$B$2:$B$492,"C",'Output Utente'!$AF$2:$AF$492,"Titolare")) -> 4 | I9: =MAX(0,'Parametri Modello'!$B$76-COUNTIFS('Output Utente'!$D$2:$D$492,$C9,'Output Utente'!$B$2:$B$492,"A",'Output Utente'!$AF$2:$AF$492,"Titolare")) -> 3
A10: 9 | B10: =('Info Lega'!$B$5-COUNTIFS('Output Utente'!$D$2:$D$492,$C10,'Output Utente'!$B$2:$B$492,"P"))+('Info Lega'!$B$6-COUNTIFS('Output Utente'!$D$2:$D$492,$C10,'Output Utente'!$B$2:$B$492,"D"))+('Info Lega'!$B$7-COUNTIFS('Output Utente'!$D$2:$D$492,$C10,'Output Utente'!$B$2:$B$492,"C"))+('Info Lega'!$B$8-COUNTIFS('Output Utente'!$D$2:$D$492,$C10,'Output Utente'!$B$2:$B$492,"A")) -> 25 | C10: ='Info Lega'!$B$17 -> xxx9 | D10: ='Info Lega'!$D$17 -> No | E10: ='Info Lega'!$B$4-SUMIFS('Output Utente'!$M$2:$M$492,'Output Utente'!$D$2:$D$492,$C10) -> 1000 | F10: =MAX(0,'Parametri Modello'!$B$73-COUNTIFS('Output Utente'!$D$2:$D$492,$C10,'Output Utente'!$B$2:$B$492,"P",'Output Utente'!$AF$2:$AF$492,"Titolare")) -> 1 | G10: =MAX(0,'Parametri Modello'!$B$74-COUNTIFS('Output Utente'!$D$2:$D$492,$C10,'Output Utente'!$B$2:$B$492,"D",'Output Utente'!$AF$2:$AF$492,"Titolare")) -> 3 | H10: =MAX(0,'Parametri Modello'!$B$75-COUNTIFS('Output Utente'!$D$2:$D$492,$C10,'Output Utente'!$B$2:$B$492,"C",'Output Utente'!$AF$2:$AF$492,"Titolare")) -> 4 | I10: =MAX(0,'Parametri Modello'!$B$76-COUNTIFS('Output Utente'!$D$2:$D$492,$C10,'Output Utente'!$B$2:$B$492,"A",'Output Utente'!$AF$2:$AF$492,"Titolare")) -> 3
A11: 10 | B11: =('Info Lega'!$B$5-COUNTIFS('Output Utente'!$D$2:$D$492,$C11,'Output Utente'!$B$2:$B$492,"P"))+('Info Lega'!$B$6-COUNTIFS('Output Utente'!$D$2:$D$492,$C11,'Output Utente'!$B$2:$B$492,"D"))+('Info Lega'!$B$7-COUNTIFS('Output Utente'!$D$2:$D$492,$C11,'Output Utente'!$B$2:$B$492,"C"))+('Info Lega'!$B$8-COUNTIFS('Output Utente'!$D$2:$D$492,$C11,'Output Utente'!$B$2:$B$492,"A")) -> 25 | C11: ='Info Lega'!$B$18 -> xxx10 | D11: ='Info Lega'!$D$18 -> No | E11: ='Info Lega'!$B$4-SUMIFS('Output Utente'!$M$2:$M$492,'Output Utente'!$D$2:$D$492,$C11) -> 1000 | F11: =MAX(0,'Parametri Modello'!$B$73-COUNTIFS('Output Utente'!$D$2:$D$492,$C11,'Output Utente'!$B$2:$B$492,"P",'Output Utente'!$AF$2:$AF$492,"Titolare")) -> 1 | G11: =MAX(0,'Parametri Modello'!$B$74-COUNTIFS('Output Utente'!$D$2:$D$492,$C11,'Output Utente'!$B$2:$B$492,"D",'Output Utente'!$AF$2:$AF$492,"Titolare")) -> 3 | H11: =MAX(0,'Parametri Modello'!$B$75-COUNTIFS('Output Utente'!$D$2:$D$492,$C11,'Output Utente'!$B$2:$B$492,"C",'Output Utente'!$AF$2:$AF$492,"Titolare")) -> 4 | I11: =MAX(0,'Parametri Modello'!$B$76-COUNTIFS('Output Utente'!$D$2:$D$492,$C11,'Output Utente'!$B$2:$B$492,"A",'Output Utente'!$AF$2:$AF$492,"Titolare")) -> 3
A12: 11 | B12: =('Info Lega'!$B$5-COUNTIFS('Output Utente'!$D$2:$D$492,$C12,'Output Utente'!$B$2:$B$492,"P"))+('Info Lega'!$B$6-COUNTIFS('Output Utente'!$D$2:$D$492,$C12,'Output Utente'!$B$2:$B$492,"D"))+('Info Lega'!$B$7-COUNTIFS('Output Utente'!$D$2:$D$492,$C12,'Output Utente'!$B$2:$B$492,"C"))+('Info Lega'!$B$8-COUNTIFS('Output Utente'!$D$2:$D$492,$C12,'Output Utente'!$B$2:$B$492,"A")) -> 25 | C12: ='Info Lega'!$B$19 -> xxx11 | D12: ='Info Lega'!$D$19 -> No | E12: ='Info Lega'!$B$4-SUMIFS('Output Utente'!$M$2:$M$492,'Output Utente'!$D$2:$D$492,$C12) -> 1000 | F12: =MAX(0,'Parametri Modello'!$B$73-COUNTIFS('Output Utente'!$D$2:$D$492,$C12,'Output Utente'!$B$2:$B$492,"P",'Output Utente'!$AF$2:$AF$492,"Titolare")) -> 1 | G12: =MAX(0,'Parametri Modello'!$B$74-COUNTIFS('Output Utente'!$D$2:$D$492,$C12,'Output Utente'!$B$2:$B$492,"D",'Output Utente'!$AF$2:$AF$492,"Titolare")) -> 3 | H12: =MAX(0,'Parametri Modello'!$B$75-COUNTIFS('Output Utente'!$D$2:$D$492,$C12,'Output Utente'!$B$2:$B$492,"C",'Output Utente'!$AF$2:$AF$492,"Titolare")) -> 4 | I12: =MAX(0,'Parametri Modello'!$B$76-COUNTIFS('Output Utente'!$D$2:$D$492,$C12,'Output Utente'!$B$2:$B$492,"A",'Output Utente'!$AF$2:$AF$492,"Titolare")) -> 3
A13: 12 | B13: =('Info Lega'!$B$5-COUNTIFS('Output Utente'!$D$2:$D$492,$C13,'Output Utente'!$B$2:$B$492,"P"))+('Info Lega'!$B$6-COUNTIFS('Output Utente'!$D$2:$D$492,$C13,'Output Utente'!$B$2:$B$492,"D"))+('Info Lega'!$B$7-COUNTIFS('Output Utente'!$D$2:$D$492,$C13,'Output Utente'!$B$2:$B$492,"C"))+('Info Lega'!$B$8-COUNTIFS('Output Utente'!$D$2:$D$492,$C13,'Output Utente'!$B$2:$B$492,"A")) -> 25 | C13: ='Info Lega'!$B$20 -> xxx12 | D13: ='Info Lega'!$D$20 -> No | E13: ='Info Lega'!$B$4-SUMIFS('Output Utente'!$M$2:$M$492,'Output Utente'!$D$2:$D$492,$C13) -> 1000 | F13: =MAX(0,'Parametri Modello'!$B$73-COUNTIFS('Output Utente'!$D$2:$D$492,$C13,'Output Utente'!$B$2:$B$492,"P",'Output Utente'!$AF$2:$AF$492,"Titolare")) -> 1 | G13: =MAX(0,'Parametri Modello'!$B$74-COUNTIFS('Output Utente'!$D$2:$D$492,$C13,'Output Utente'!$B$2:$B$492,"D",'Output Utente'!$AF$2:$AF$492,"Titolare")) -> 3 | H13: =MAX(0,'Parametri Modello'!$B$75-COUNTIFS('Output Utente'!$D$2:$D$492,$C13,'Output Utente'!$B$2:$B$492,"C",'Output Utente'!$AF$2:$AF$492,"Titolare")) -> 4 | I13: =MAX(0,'Parametri Modello'!$B$76-COUNTIFS('Output Utente'!$D$2:$D$492,$C13,'Output Utente'!$B$2:$B$492,"A",'Output Utente'!$AF$2:$AF$492,"Titolare")) -> 3
A14: 13 | B14: =('Info Lega'!$B$5-COUNTIFS('Output Utente'!$D$2:$D$492,$C14,'Output Utente'!$B$2:$B$492,"P"))+('Info Lega'!$B$6-COUNTIFS('Output Utente'!$D$2:$D$492,$C14,'Output Utente'!$B$2:$B$492,"D"))+('Info Lega'!$B$7-COUNTIFS('Output Utente'!$D$2:$D$492,$C14,'Output Utente'!$B$2:$B$492,"C"))+('Info Lega'!$B$8-COUNTIFS('Output Utente'!$D$2:$D$492,$C14,'Output Utente'!$B$2:$B$492,"A")) -> 25 | C14: ='Info Lega'!$B$21 -> xxx13 | D14: ='Info Lega'!$D$21 -> No | E14: ='Info Lega'!$B$4-SUMIFS('Output Utente'!$M$2:$M$492,'Output Utente'!$D$2:$D$492,$C14) -> 1000 | F14: =MAX(0,'Parametri Modello'!$B$73-COUNTIFS('Output Utente'!$D$2:$D$492,$C14,'Output Utente'!$B$2:$B$492,"P",'Output Utente'!$AF$2:$AF$492,"Titolare")) -> 1 | G14: =MAX(0,'Parametri Modello'!$B$74-COUNTIFS('Output Utente'!$D$2:$D$492,$C14,'Output Utente'!$B$2:$B$492,"D",'Output Utente'!$AF$2:$AF$492,"Titolare")) -> 3 | H14: =MAX(0,'Parametri Modello'!$B$75-COUNTIFS('Output Utente'!$D$2:$D$492,$C14,'Output Utente'!$B$2:$B$492,"C",'Output Utente'!$AF$2:$AF$492,"Titolare")) -> 4 | I14: =MAX(0,'Parametri Modello'!$B$76-COUNTIFS('Output Utente'!$D$2:$D$492,$C14,'Output Utente'!$B$2:$B$492,"A",'Output Utente'!$AF$2:$AF$492,"Titolare")) -> 3
A15: 14 | B15: =('Info Lega'!$B$5-COUNTIFS('Output Utente'!$D$2:$D$492,$C15,'Output Utente'!$B$2:$B$492,"P"))+('Info Lega'!$B$6-COUNTIFS('Output Utente'!$D$2:$D$492,$C15,'Output Utente'!$B$2:$B$492,"D"))+('Info Lega'!$B$7-COUNTIFS('Output Utente'!$D$2:$D$492,$C15,'Output Utente'!$B$2:$B$492,"C"))+('Info Lega'!$B$8-COUNTIFS('Output Utente'!$D$2:$D$492,$C15,'Output Utente'!$B$2:$B$492,"A")) -> 25 | C15: ='Info Lega'!$B$22 -> xxx14 | D15: ='Info Lega'!$D$22 -> No | E15: ='Info Lega'!$B$4-SUMIFS('Output Utente'!$M$2:$M$492,'Output Utente'!$D$2:$D$492,$C15) -> 1000 | F15: =MAX(0,'Parametri Modello'!$B$73-COUNTIFS('Output Utente'!$D$2:$D$492,$C15,'Output Utente'!$B$2:$B$492,"P",'Output Utente'!$AF$2:$AF$492,"Titolare")) -> 1 | G15: =MAX(0,'Parametri Modello'!$B$74-COUNTIFS('Output Utente'!$D$2:$D$492,$C15,'Output Utente'!$B$2:$B$492,"D",'Output Utente'!$AF$2:$AF$492,"Titolare")) -> 3 | H15: =MAX(0,'Parametri Modello'!$B$75-COUNTIFS('Output Utente'!$D$2:$D$492,$C15,'Output Utente'!$B$2:$B$492,"C",'Output Utente'!$AF$2:$AF$492,"Titolare")) -> 4 | I15: =MAX(0,'Parametri Modello'!$B$76-COUNTIFS('Output Utente'!$D$2:$D$492,$C15,'Output Utente'!$B$2:$B$492,"A",'Output Utente'!$AF$2:$AF$492,"Titolare")) -> 3
A16: 15 | B16: =('Info Lega'!$B$5-COUNTIFS('Output Utente'!$D$2:$D$492,$C16,'Output Utente'!$B$2:$B$492,"P"))+('Info Lega'!$B$6-COUNTIFS('Output Utente'!$D$2:$D$492,$C16,'Output Utente'!$B$2:$B$492,"D"))+('Info Lega'!$B$7-COUNTIFS('Output Utente'!$D$2:$D$492,$C16,'Output Utente'!$B$2:$B$492,"C"))+('Info Lega'!$B$8-COUNTIFS('Output Utente'!$D$2:$D$492,$C16,'Output Utente'!$B$2:$B$492,"A")) -> 25 | C16: ='Info Lega'!$B$23 -> xxx15 | D16: ='Info Lega'!$D$23 -> No | E16: ='Info Lega'!$B$4-SUMIFS('Output Utente'!$M$2:$M$492,'Output Utente'!$D$2:$D$492,$C16) -> 1000 | F16: =MAX(0,'Parametri Modello'!$B$73-COUNTIFS('Output Utente'!$D$2:$D$492,$C16,'Output Utente'!$B$2:$B$492,"P",'Output Utente'!$AF$2:$AF$492,"Titolare")) -> 1 | G16: =MAX(0,'Parametri Modello'!$B$74-COUNTIFS('Output Utente'!$D$2:$D$492,$C16,'Output Utente'!$B$2:$B$492,"D",'Output Utente'!$AF$2:$AF$492,"Titolare")) -> 3 | H16: =MAX(0,'Parametri Modello'!$B$75-COUNTIFS('Output Utente'!$D$2:$D$492,$C16,'Output Utente'!$B$2:$B$492,"C",'Output Utente'!$AF$2:$AF$492,"Titolare")) -> 4 | I16: =MAX(0,'Parametri Modello'!$B$76-COUNTIFS('Output Utente'!$D$2:$D$492,$C16,'Output Utente'!$B$2:$B$492,"A",'Output Utente'!$AF$2:$AF$492,"Titolare")) -> 3
A17: 16 | B17: =('Info Lega'!$B$5-COUNTIFS('Output Utente'!$D$2:$D$492,$C17,'Output Utente'!$B$2:$B$492,"P"))+('Info Lega'!$B$6-COUNTIFS('Output Utente'!$D$2:$D$492,$C17,'Output Utente'!$B$2:$B$492,"D"))+('Info Lega'!$B$7-COUNTIFS('Output Utente'!$D$2:$D$492,$C17,'Output Utente'!$B$2:$B$492,"C"))+('Info Lega'!$B$8-COUNTIFS('Output Utente'!$D$2:$D$492,$C17,'Output Utente'!$B$2:$B$492,"A")) -> 25 | C17: ='Info Lega'!$B$24 -> xxx16 | D17: ='Info Lega'!$D$24 -> No | E17: ='Info Lega'!$B$4-SUMIFS('Output Utente'!$M$2:$M$492,'Output Utente'!$D$2:$D$492,$C17) -> 1000 | F17: =MAX(0,'Parametri Modello'!$B$73-COUNTIFS('Output Utente'!$D$2:$D$492,$C17,'Output Utente'!$B$2:$B$492,"P",'Output Utente'!$AF$2:$AF$492,"Titolare")) -> 1 | G17: =MAX(0,'Parametri Modello'!$B$74-COUNTIFS('Output Utente'!$D$2:$D$492,$C17,'Output Utente'!$B$2:$B$492,"D",'Output Utente'!$AF$2:$AF$492,"Titolare")) -> 3 | H17: =MAX(0,'Parametri Modello'!$B$75-COUNTIFS('Output Utente'!$D$2:$D$492,$C17,'Output Utente'!$B$2:$B$492,"C",'Output Utente'!$AF$2:$AF$492,"Titolare")) -> 4 | I17: =MAX(0,'Parametri Modello'!$B$76-COUNTIFS('Output Utente'!$D$2:$D$492,$C17,'Output Utente'!$B$2:$B$492,"A",'Output Utente'!$AF$2:$AF$492,"Titolare")) -> 3

Sheet Giocatori Da Chiamare
A1: GIOCATORI ANCORA DA CHIAMARE — per ruolo e fascia
A2: Se lasci andare questo giocatore, quali alternative avrai piu' avanti? Solo giocatori non assegnati e con Qt.A>1.
A4: TOP
B5: Portieri | C5: Difensori | D5: Centrocampisti | E5: Attaccanti
A6: 1 | B6: =IFERROR(INDEX('Output Utente'!$C$2:$C$492,MATCH("P|Top|1",'Output Utente'!$AL$2:$AL$492,0)),"") -> Svilar | C6: =IFERROR(INDEX('Output Utente'!$C$2:$C$492,MATCH("D|Top|1",'Output Utente'!$AL$2:$AL$492,0)),"") -> Dimarco | D6: =IFERROR(INDEX('Output Utente'!$C$2:$C$492,MATCH("C|Top|1",'Output Utente'!$AL$2:$AL$492,0)),"") -> Paz N. | E6: =IFERROR(INDEX('Output Utente'!$C$2:$C$492,MATCH("A|Top|1",'Output Utente'!$AL$2:$AL$492,0)),"") -> Martinez L.
A7: 2 | B7: =IFERROR(INDEX('Output Utente'!$C$2:$C$492,MATCH("P|Top|2",'Output Utente'!$AL$2:$AL$492,0)),"") -> Martinez Jo. | C7: =IFERROR(INDEX('Output Utente'!$C$2:$C$492,MATCH("D|Top|2",'Output Utente'!$AL$2:$AL$492,0)),"") -> Wesley | D7: =IFERROR(INDEX('Output Utente'!$C$2:$C$492,MATCH("C|Top|2",'Output Utente'!$AL$2:$AL$492,0)),"") -> McTominay | E7: =IFERROR(INDEX('Output Utente'!$C$2:$C$492,MATCH("A|Top|2",'Output Utente'!$AL$2:$AL$492,0)),"") -> Malen
A8: 3 | B8: =IFERROR(INDEX('Output Utente'!$C$2:$C$492,MATCH("P|Top|3",'Output Utente'!$AL$2:$AL$492,0)),"") -> Butez | C8: =IFERROR(INDEX('Output Utente'!$C$2:$C$492,MATCH("D|Top|3",'Output Utente'!$AL$2:$AL$492,0)),"") -> Akanji | D8: =IFERROR(INDEX('Output Utente'!$C$2:$C$492,MATCH("C|Top|3",'Output Utente'!$AL$2:$AL$492,0)),"") -> Calhanoglu | E8: =IFERROR(INDEX('Output Utente'!$C$2:$C$492,MATCH("A|Top|3",'Output Utente'!$AL$2:$AL$492,0)),"") -> Thuram
A9: 4 | B9: =IFERROR(INDEX('Output Utente'!$C$2:$C$492,MATCH("P|Top|4",'Output Utente'!$AL$2:$AL$492,0)),"") -> Carnesecchi | C9: =IFERROR(INDEX('Output Utente'!$C$2:$C$492,MATCH("D|Top|4",'Output Utente'!$AL$2:$AL$492,0)),"") -> Bremer | D9: =IFERROR(INDEX('Output Utente'!$C$2:$C$492,MATCH("C|Top|4",'Output Utente'!$AL$2:$AL$492,0)),"") -> Orsolini | E9: =IFERROR(INDEX('Output Utente'!$C$2:$C$492,MATCH("A|Top|4",'Output Utente'!$AL$2:$AL$492,0)),"") -> Hojlund
A10: 5 | B10: =IFERROR(INDEX('Output Utente'!$C$2:$C$492,MATCH("P|Top|5",'Output Utente'!$AL$2:$AL$492,0)),"") -> Maignan | C10: =IFERROR(INDEX('Output Utente'!$C$2:$C$492,MATCH("D|Top|5",'Output Utente'!$AL$2:$AL$492,0)),"") -> Mancini | D10: =IFERROR(INDEX('Output Utente'!$C$2:$C$492,MATCH("C|Top|5",'Output Utente'!$AL$2:$AL$492,0)),"") -> Pulisic | E10: =IFERROR(INDEX('Output Utente'!$C$2:$C$492,MATCH("A|Top|5",'Output Utente'!$AL$2:$AL$492,0)),"") -> Ramos G.
A11: 6 | B11: =IFERROR(INDEX('Output Utente'!$C$2:$C$492,MATCH("P|Top|6",'Output Utente'!$AL$2:$AL$492,0)),"") -> De Gea | C11: =IFERROR(INDEX('Output Utente'!$C$2:$C$492,MATCH("D|Top|6",'Output Utente'!$AL$2:$AL$492,0)),"") -> Pavlovic | D11: =IFERROR(INDEX('Output Utente'!$C$2:$C$492,MATCH("C|Top|6",'Output Utente'!$AL$2:$AL$492,0)),"") -> Rabiot | E11: =IFERROR(INDEX('Output Utente'!$C$2:$C$492,MATCH("A|Top|6",'Output Utente'!$AL$2:$AL$492,0)),"") -> Kolo Muani
A12: 7 | B12: =IFERROR(INDEX('Output Utente'!$C$2:$C$492,MATCH("P|Top|7",'Output Utente'!$AL$2:$AL$492,0)),"") | C12: =IFERROR(INDEX('Output Utente'!$C$2:$C$492,MATCH("D|Top|7",'Output Utente'!$AL$2:$AL$492,0)),"") -> Rrahmani | D12: =IFERROR(INDEX('Output Utente'!$C$2:$C$492,MATCH("C|Top|7",'Output Utente'!$AL$2:$AL$492,0)),"") -> Baturina | E12: =IFERROR(INDEX('Output Utente'!$C$2:$C$492,MATCH("A|Top|7",'Output Utente'!$AL$2:$AL$492,0)),"") -> Kean
A13: 8 | B13: =IFERROR(INDEX('Output Utente'!$C$2:$C$492,MATCH("P|Top|8",'Output Utente'!$AL$2:$AL$492,0)),"") | C13: =IFERROR(INDEX('Output Utente'!$C$2:$C$492,MATCH("D|Top|8",'Output Utente'!$AL$2:$AL$492,0)),"") -> Kalulu | D13: =IFERROR(INDEX('Output Utente'!$C$2:$C$492,MATCH("C|Top|8",'Output Utente'!$AL$2:$AL$492,0)),"") -> De Bruyne | E13: =IFERROR(INDEX('Output Utente'!$C$2:$C$492,MATCH("A|Top|8",'Output Utente'!$AL$2:$AL$492,0)),"") -> Yildiz
A14: 9 | B14: =IFERROR(INDEX('Output Utente'!$C$2:$C$492,MATCH("P|Top|9",'Output Utente'!$AL$2:$AL$492,0)),"") | C14: =IFERROR(INDEX('Output Utente'!$C$2:$C$492,MATCH("D|Top|9",'Output Utente'!$AL$2:$AL$492,0)),"") | D14: =IFERROR(INDEX('Output Utente'!$C$2:$C$492,MATCH("C|Top|9",'Output Utente'!$AL$2:$AL$492,0)),"") -> Zaccagni | E14: =IFERROR(INDEX('Output Utente'!$C$2:$C$492,MATCH("A|Top|9",'Output Utente'!$AL$2:$AL$492,0)),"") -> Douvikas
A15: 10 | B15: =IFERROR(INDEX('Output Utente'!$C$2:$C$492,MATCH("P|Top|10",'Output Utente'!$AL$2:$AL$492,0)),"") | C15: =IFERROR(INDEX('Output Utente'!$C$2:$C$492,MATCH("D|Top|10",'Output Utente'!$AL$2:$AL$492,0)),"") -> Bastoni | D15: =IFERROR(INDEX('Output Utente'!$C$2:$C$492,MATCH("C|Top|10",'Output Utente'!$AL$2:$AL$492,0)),"") -> Da Cunha | E15: =IFERROR(INDEX('Output Utente'!$C$2:$C$492,MATCH("A|Top|10",'Output Utente'!$AL$2:$AL$492,0)),"")
A16: 11 | B16: =IFERROR(INDEX('Output Utente'!$C$2:$C$492,MATCH("P|Top|11",'Output Utente'!$AL$2:$AL$492,0)),"") | C16: =IFERROR(INDEX('Output Utente'!$C$2:$C$492,MATCH("D|Top|11",'Output Utente'!$AL$2:$AL$492,0)),"") | D16: =IFERROR(INDEX('Output Utente'!$C$2:$C$492,MATCH("C|Top|11",'Output Utente'!$AL$2:$AL$492,0)),"") | E16: =IFERROR(INDEX('Output Utente'!$C$2:$C$492,MATCH("A|Top|11",'Output Utente'!$AL$2:$AL$492,0)),"")
A17: 12 | B17: =IFERROR(INDEX('Output Utente'!$C$2:$C$492,MATCH("P|Top|12",'Output Utente'!$AL$2:$AL$492,0)),"") | C17: =IFERROR(INDEX('Output Utente'!$C$2:$C$492,MATCH("D|Top|12",'Output Utente'!$AL$2:$AL$492,0)),"") -> Di Lorenzo | D17: =IFERROR(INDEX('Output Utente'!$C$2:$C$492,MATCH("C|Top|12",'Output Utente'!$AL$2:$AL$492,0)),"") -> Atta | E17: =IFERROR(INDEX('Output Utente'!$C$2:$C$492,MATCH("A|Top|12",'Output Utente'!$AL$2:$AL$492,0)),"")
A18: 13 | B18: =IFERROR(INDEX('Output Utente'!$C$2:$C$492,MATCH("P|Top|13",'Output Utente'!$AL$2:$AL$492,0)),"") | C18: =IFERROR(INDEX('Output Utente'!$C$2:$C$492,MATCH("D|Top|13",'Output Utente'!$AL$2:$AL$492,0)),"") | D18: =IFERROR(INDEX('Output Utente'!$C$2:$C$492,MATCH("C|Top|13",'Output Utente'!$AL$2:$AL$492,0)),"") -> Barella | E18: =IFERROR(INDEX('Output Utente'!$C$2:$C$492,MATCH("A|Top|13",'Output Utente'!$AL$2:$AL$492,0)),"")
A19: 14 | B19: =IFERROR(INDEX('Output Utente'!$C$2:$C$492,MATCH("P|Top|14",'Output Utente'!$AL$2:$AL$492,0)),"") | C19: =IFERROR(INDEX('Output Utente'!$C$2:$C$492,MATCH("D|Top|14",'Output Utente'!$AL$2:$AL$492,0)),"") -> Stones | D19: =IFERROR(INDEX('Output Utente'!$C$2:$C$492,MATCH("C|Top|14",'Output Utente'!$AL$2:$AL$492,0)),"") -> Vlasic | E19: =IFERROR(INDEX('Output Utente'!$C$2:$C$492,MATCH("A|Top|14",'Output Utente'!$AL$2:$AL$492,0)),"")
A20: 15 | B20: =IFERROR(INDEX('Output Utente'!$C$2:$C$492,MATCH("P|Top|15",'Output Utente'!$AL$2:$AL$492,0)),"") | C20: =IFERROR(INDEX('Output Utente'!$C$2:$C$492,MATCH("D|Top|15",'Output Utente'!$AL$2:$AL$492,0)),"") -> Bisseck | D20: =IFERROR(INDEX('Output Utente'!$C$2:$C$492,MATCH("C|Top|15",'Output Utente'!$AL$2:$AL$492,0)),"") -> McKennie | E20: =IFERROR(INDEX('Output Utente'!$C$2:$C$492,MATCH("A|Top|15",'Output Utente'!$AL$2:$AL$492,0)),"")
A22: BUONI
B23: Portieri | C23: Difensori | D23: Centrocampisti | E23: Attaccanti
A24: 1 | B24: =IFERROR(INDEX('Output Utente'!$C$2:$C$492,MATCH("P|Buono|1",'Output Utente'!$AL$2:$AL$492,0)),"") -> Di Gregorio | C24: =IFERROR(INDEX('Output Utente'!$C$2:$C$492,MATCH("D|Buono|1",'Output Utente'!$AL$2:$AL$492,0)),"") -> Dodò | D24: =IFERROR(INDEX('Output Utente'!$C$2:$C$492,MATCH("C|Buono|1",'Output Utente'!$AL$2:$AL$492,0)),"") -> Alajbegovic | E24: =IFERROR(INDEX('Output Utente'!$C$2:$C$492,MATCH("A|Buono|1",'Output Utente'!$AL$2:$AL$492,0)),"") -> Scamacca
A25: 2 | B25: =IFERROR(INDEX('Output Utente'!$C$2:$C$492,MATCH("P|Buono|2",'Output Utente'!$AL$2:$AL$492,0)),"") -> Skorupski | C25: =IFERROR(INDEX('Output Utente'!$C$2:$C$492,MATCH("D|Buono|2",'Output Utente'!$AL$2:$AL$492,0)),"") -> Scalvini | D25: =IFERROR(INDEX('Output Utente'!$C$2:$C$492,MATCH("C|Buono|2",'Output Utente'!$AL$2:$AL$492,0)),"") -> Zambo Anguissa | E25: =IFERROR(INDEX('Output Utente'!$C$2:$C$492,MATCH("A|Buono|2",'Output Utente'!$AL$2:$AL$492,0)),"") -> Davis K.
A26: 3 | B26: =IFERROR(INDEX('Output Utente'!$C$2:$C$492,MATCH("P|Buono|3",'Output Utente'!$AL$2:$AL$492,0)),"") -> Mandas | C26: =IFERROR(INDEX('Output Utente'!$C$2:$C$492,MATCH("D|Buono|3",'Output Utente'!$AL$2:$AL$492,0)),"") -> Cambiaso | D26: =IFERROR(INDEX('Output Utente'!$C$2:$C$492,MATCH("C|Buono|3",'Output Utente'!$AL$2:$AL$492,0)),"") -> Modric | E26: =IFERROR(INDEX('Output Utente'!$C$2:$C$492,MATCH("A|Buono|3",'Output Utente'!$AL$2:$AL$492,0)),"") -> Leao
A27: 4 | B27: =IFERROR(INDEX('Output Utente'!$C$2:$C$492,MATCH("P|Buono|4",'Output Utente'!$AL$2:$AL$492,0)),"") -> Okoye | C27: =IFERROR(INDEX('Output Utente'!$C$2:$C$492,MATCH("D|Buono|4",'Output Utente'!$AL$2:$AL$492,0)),"") | D27: =IFERROR(INDEX('Output Utente'!$C$2:$C$492,MATCH("C|Buono|4",'Output Utente'!$AL$2:$AL$492,0)),"") -> Politano | E27: =IFERROR(INDEX('Output Utente'!$C$2:$C$492,MATCH("A|Buono|4",'Output Utente'!$AL$2:$AL$492,0)),"") -> Berardi
A28: 5 | B28: =IFERROR(INDEX('Output Utente'!$C$2:$C$492,MATCH("P|Buono|5",'Output Utente'!$AL$2:$AL$492,0)),"") -> Caprile | C28: =IFERROR(INDEX('Output Utente'!$C$2:$C$492,MATCH("D|Buono|5",'Output Utente'!$AL$2:$AL$492,0)),"") | D28: =IFERROR(INDEX('Output Utente'!$C$2:$C$492,MATCH("C|Buono|5",'Output Utente'!$AL$2:$AL$492,0)),"") -> Ederson D.S. | E28: =IFERROR(INDEX('Output Utente'!$C$2:$C$492,MATCH("A|Buono|5",'Output Utente'!$AL$2:$AL$492,0)),"") -> De Ketelaere
A29: 6 | B29: =IFERROR(INDEX('Output Utente'!$C$2:$C$492,MATCH("P|Buono|6",'Output Utente'!$AL$2:$AL$492,0)),"") -> Falcone | C29: =IFERROR(INDEX('Output Utente'!$C$2:$C$492,MATCH("D|Buono|6",'Output Utente'!$AL$2:$AL$492,0)),"") -> Hermoso | D29: =IFERROR(INDEX('Output Utente'!$C$2:$C$492,MATCH("C|Buono|6",'Output Utente'!$AL$2:$AL$492,0)),"") -> Saelemaekers | E29: =IFERROR(INDEX('Output Utente'!$C$2:$C$492,MATCH("A|Buono|6",'Output Utente'!$AL$2:$AL$492,0)),"") -> Krstovic
A30: 7 | B30: =IFERROR(INDEX('Output Utente'!$C$2:$C$492,MATCH("P|Buono|7",'Output Utente'!$AL$2:$AL$492,0)),"") -> Suzuki | C30: =IFERROR(INDEX('Output Utente'!$C$2:$C$492,MATCH("D|Buono|7",'Output Utente'!$AL$2:$AL$492,0)),"") -> Bartesaghi | D30: =IFERROR(INDEX('Output Utente'!$C$2:$C$492,MATCH("C|Buono|7",'Output Utente'!$AL$2:$AL$492,0)),"") -> Samardzic | E30: =IFERROR(INDEX('Output Utente'!$C$2:$C$492,MATCH("A|Buono|7",'Output Utente'!$AL$2:$AL$492,0)),"") -> Esposito F.P.
A31: 8 | B31: =IFERROR(INDEX('Output Utente'!$C$2:$C$492,MATCH("P|Buono|8",'Output Utente'!$AL$2:$AL$492,0)),"") -> Bijlow | C31: =IFERROR(INDEX('Output Utente'!$C$2:$C$492,MATCH("D|Buono|8",'Output Utente'!$AL$2:$AL$492,0)),"") -> Zappacosta | D31: =IFERROR(INDEX('Output Utente'!$C$2:$C$492,MATCH("C|Buono|8",'Output Utente'!$AL$2:$AL$492,0)),"") | E31: =IFERROR(INDEX('Output Utente'!$C$2:$C$492,MATCH("A|Buono|8",'Output Utente'!$AL$2:$AL$492,0)),"") -> Laurientè
A32: 9 | B32: =IFERROR(INDEX('Output Utente'!$C$2:$C$492,MATCH("P|Buono|9",'Output Utente'!$AL$2:$AL$492,0)),"") -> Muric | C32: =IFERROR(INDEX('Output Utente'!$C$2:$C$492,MATCH("D|Buono|9",'Output Utente'!$AL$2:$AL$492,0)),"") | D32: =IFERROR(INDEX('Output Utente'!$C$2:$C$492,MATCH("C|Buono|9",'Output Utente'!$AL$2:$AL$492,0)),"") -> Zielinski | E32: =IFERROR(INDEX('Output Utente'!$C$2:$C$492,MATCH("A|Buono|9",'Output Utente'!$AL$2:$AL$492,0)),"") -> Dovbyk
A33: 10 | B33: =IFERROR(INDEX('Output Utente'!$C$2:$C$492,MATCH("P|Buono|10",'Output Utente'!$AL$2:$AL$492,0)),"") -> Stankovic F. | C33: =IFERROR(INDEX('Output Utente'!$C$2:$C$492,MATCH("D|Buono|10",'Output Utente'!$AL$2:$AL$492,0)),"") | D33: =IFERROR(INDEX('Output Utente'!$C$2:$C$492,MATCH("C|Buono|10",'Output Utente'!$AL$2:$AL$492,0)),"") | E33: =IFERROR(INDEX('Output Utente'!$C$2:$C$492,MATCH("A|Buono|10",'Output Utente'!$AL$2:$AL$492,0)),"") -> Castro S.
A34: 11 | B34: =IFERROR(INDEX('Output Utente'!$C$2:$C$492,MATCH("P|Buono|11",'Output Utente'!$AL$2:$AL$492,0)),"") -> Thiam | C34: =IFERROR(INDEX('Output Utente'!$C$2:$C$492,MATCH("D|Buono|11",'Output Utente'!$AL$2:$AL$492,0)),"") | D34: =IFERROR(INDEX('Output Utente'!$C$2:$C$492,MATCH("C|Buono|11",'Output Utente'!$AL$2:$AL$492,0)),"") | E34: =IFERROR(INDEX('Output Utente'!$C$2:$C$492,MATCH("A|Buono|11",'Output Utente'!$AL$2:$AL$492,0)),"") -> Simeone
A35: 12 | B35: =IFERROR(INDEX('Output Utente'!$C$2:$C$492,MATCH("P|Buono|12",'Output Utente'!$AL$2:$AL$492,0)),"") | C35: =IFERROR(INDEX('Output Utente'!$C$2:$C$492,MATCH("D|Buono|12",'Output Utente'!$AL$2:$AL$492,0)),"") | D35: =IFERROR(INDEX('Output Utente'!$C$2:$C$492,MATCH("C|Buono|12",'Output Utente'!$AL$2:$AL$492,0)),"") | E35: =IFERROR(INDEX('Output Utente'!$C$2:$C$492,MATCH("A|Buono|12",'Output Utente'!$AL$2:$AL$492,0)),"") -> Pellegrino M.
A36: 13 | B36: =IFERROR(INDEX('Output Utente'!$C$2:$C$492,MATCH("P|Buono|13",'Output Utente'!$AL$2:$AL$492,0)),"") | C36: =IFERROR(INDEX('Output Utente'!$C$2:$C$492,MATCH("D|Buono|13",'Output Utente'!$AL$2:$AL$492,0)),"") -> Jimenez A. | D36: =IFERROR(INDEX('Output Utente'!$C$2:$C$492,MATCH("C|Buono|13",'Output Utente'!$AL$2:$AL$492,0)),"") -> Perrone | E36: =IFERROR(INDEX('Output Utente'!$C$2:$C$492,MATCH("A|Buono|13",'Output Utente'!$AL$2:$AL$492,0)),"") -> Dybala
A37: 14 | B37: =IFERROR(INDEX('Output Utente'!$C$2:$C$492,MATCH("P|Buono|14",'Output Utente'!$AL$2:$AL$492,0)),"") | C37: =IFERROR(INDEX('Output Utente'!$C$2:$C$492,MATCH("D|Buono|14",'Output Utente'!$AL$2:$AL$492,0)),"") | D37: =IFERROR(INDEX('Output Utente'!$C$2:$C$492,MATCH("C|Buono|14",'Output Utente'!$AL$2:$AL$492,0)),"") -> Rowe | E37: =IFERROR(INDEX('Output Utente'!$C$2:$C$492,MATCH("A|Buono|14",'Output Utente'!$AL$2:$AL$492,0)),"") -> Colombo
A38: 15 | B38: =IFERROR(INDEX('Output Utente'!$C$2:$C$492,MATCH("P|Buono|15",'Output Utente'!$AL$2:$AL$492,0)),"") | C38: =IFERROR(INDEX('Output Utente'!$C$2:$C$492,MATCH("D|Buono|15",'Output Utente'!$AL$2:$AL$492,0)),"") | D38: =IFERROR(INDEX('Output Utente'!$C$2:$C$492,MATCH("C|Buono|15",'Output Utente'!$AL$2:$AL$492,0)),"") | E38: =IFERROR(INDEX('Output Utente'!$C$2:$C$492,MATCH("A|Buono|15",'Output Utente'!$AL$2:$AL$492,0)),"") -> Raspadori
A40: MEDIA
B41: Portieri | C41: Difensori | D41: Centrocampisti | E41: Attaccanti
A42: 1 | B42: =IFERROR(INDEX('Output Utente'!$C$2:$C$492,MATCH("P|Nella Media|1",'Output Utente'!$AL$2:$AL$492,0)),"") -> Perin | C42: =IFERROR(INDEX('Output Utente'!$C$2:$C$492,MATCH("D|Nella Media|1",'Output Utente'!$AL$2:$AL$492,0)),"") -> Hien | D42: =IFERROR(INDEX('Output Utente'!$C$2:$C$492,MATCH("C|Nella Media|1",'Output Utente'!$AL$2:$AL$492,0)),"") -> Odgaard | E42: =IFERROR(INDEX('Output Utente'!$C$2:$C$492,MATCH("A|Nella Media|1",'Output Utente'!$AL$2:$AL$492,0)),"") -> Soulè
A43: 2 | B43: =IFERROR(INDEX('Output Utente'!$C$2:$C$492,MATCH("P|Nella Media|2",'Output Utente'!$AL$2:$AL$492,0)),"") | C43: =IFERROR(INDEX('Output Utente'!$C$2:$C$492,MATCH("D|Nella Media|2",'Output Utente'!$AL$2:$AL$492,0)),"") | D43: =IFERROR(INDEX('Output Utente'!$C$2:$C$492,MATCH("C|Nella Media|2",'Output Utente'!$AL$2:$AL$492,0)),"") | E43: =IFERROR(INDEX('Output Utente'!$C$2:$C$492,MATCH("A|Nella Media|2",'Output Utente'!$AL$2:$AL$492,0)),"") -> Nkunku
A44: 3 | B44: =IFERROR(INDEX('Output Utente'!$C$2:$C$492,MATCH("P|Nella Media|3",'Output Utente'!$AL$2:$AL$492,0)),"") -> Palmisani | C44: =IFERROR(INDEX('Output Utente'!$C$2:$C$492,MATCH("D|Nella Media|3",'Output Utente'!$AL$2:$AL$492,0)),"") | D44: =IFERROR(INDEX('Output Utente'!$C$2:$C$492,MATCH("C|Nella Media|3",'Output Utente'!$AL$2:$AL$492,0)),"") -> Bernardeschi | E44: =IFERROR(INDEX('Output Utente'!$C$2:$C$492,MATCH("A|Nella Media|3",'Output Utente'!$AL$2:$AL$492,0)),"")
A45: 4 | B45: =IFERROR(INDEX('Output Utente'!$C$2:$C$492,MATCH("P|Nella Media|4",'Output Utente'!$AL$2:$AL$492,0)),"") | C45: =IFERROR(INDEX('Output Utente'!$C$2:$C$492,MATCH("D|Nella Media|4",'Output Utente'!$AL$2:$AL$492,0)),"") | D45: =IFERROR(INDEX('Output Utente'!$C$2:$C$492,MATCH("C|Nella Media|4",'Output Utente'!$AL$2:$AL$492,0)),"") | E45: =IFERROR(INDEX('Output Utente'!$C$2:$C$492,MATCH("A|Nella Media|4",'Output Utente'!$AL$2:$AL$492,0)),"") -> Esposito Se.
A46: 5 | B46: =IFERROR(INDEX('Output Utente'!$C$2:$C$492,MATCH("P|Nella Media|5",'Output Utente'!$AL$2:$AL$492,0)),"") -> Daffara | C46: =IFERROR(INDEX('Output Utente'!$C$2:$C$492,MATCH("D|Nella Media|5",'Output Utente'!$AL$2:$AL$492,0)),"") | D46: =IFERROR(INDEX('Output Utente'!$C$2:$C$492,MATCH("C|Nella Media|5",'Output Utente'!$AL$2:$AL$492,0)),"") -> Konè I. | E46: =IFERROR(INDEX('Output Utente'!$C$2:$C$492,MATCH("A|Nella Media|5",'Output Utente'!$AL$2:$AL$492,0)),"")
A47: 6 | B47: =IFERROR(INDEX('Output Utente'!$C$2:$C$492,MATCH("P|Nella Media|6",'Output Utente'!$AL$2:$AL$492,0)),"") | C47: =IFERROR(INDEX('Output Utente'!$C$2:$C$492,MATCH("D|Nella Media|6",'Output Utente'!$AL$2:$AL$492,0)),"") -> Kristensen T. | D47: =IFERROR(INDEX('Output Utente'!$C$2:$C$492,MATCH("C|Nella Media|6",'Output Utente'!$AL$2:$AL$492,0)),"") | E47: =IFERROR(INDEX('Output Utente'!$C$2:$C$492,MATCH("A|Nella Media|6",'Output Utente'!$AL$2:$AL$492,0)),"") -> Lukaku
A48: 7 | B48: =IFERROR(INDEX('Output Utente'!$C$2:$C$492,MATCH("P|Nella Media|7",'Output Utente'!$AL$2:$AL$492,0)),"") | C48: =IFERROR(INDEX('Output Utente'!$C$2:$C$492,MATCH("D|Nella Media|7",'Output Utente'!$AL$2:$AL$492,0)),"") | D48: =IFERROR(INDEX('Output Utente'!$C$2:$C$492,MATCH("C|Nella Media|7",'Output Utente'!$AL$2:$AL$492,0)),"") | E48: =IFERROR(INDEX('Output Utente'!$C$2:$C$492,MATCH("A|Nella Media|7",'Output Utente'!$AL$2:$AL$492,0)),"") -> David
A49: 8 | B49: =IFERROR(INDEX('Output Utente'!$C$2:$C$492,MATCH("P|Nella Media|8",'Output Utente'!$AL$2:$AL$492,0)),"") | C49: =IFERROR(INDEX('Output Utente'!$C$2:$C$492,MATCH("D|Nella Media|8",'Output Utente'!$AL$2:$AL$492,0)),"") | D49: =IFERROR(INDEX('Output Utente'!$C$2:$C$492,MATCH("C|Nella Media|8",'Output Utente'!$AL$2:$AL$492,0)),"") | E49: =IFERROR(INDEX('Output Utente'!$C$2:$C$492,MATCH("A|Nella Media|8",'Output Utente'!$AL$2:$AL$492,0)),"") -> Bowie
A50: 9 | B50: =IFERROR(INDEX('Output Utente'!$C$2:$C$492,MATCH("P|Nella Media|9",'Output Utente'!$AL$2:$AL$492,0)),"") | C50: =IFERROR(INDEX('Output Utente'!$C$2:$C$492,MATCH("D|Nella Media|9",'Output Utente'!$AL$2:$AL$492,0)),"") | D50: =IFERROR(INDEX('Output Utente'!$C$2:$C$492,MATCH("C|Nella Media|9",'Output Utente'!$AL$2:$AL$492,0)),"") | E50: =IFERROR(INDEX('Output Utente'!$C$2:$C$492,MATCH("A|Nella Media|9",'Output Utente'!$AL$2:$AL$492,0)),"") -> Cutrone
A51: 10 | B51: =IFERROR(INDEX('Output Utente'!$C$2:$C$492,MATCH("P|Nella Media|10",'Output Utente'!$AL$2:$AL$492,0)),"") | C51: =IFERROR(INDEX('Output Utente'!$C$2:$C$492,MATCH("D|Nella Media|10",'Output Utente'!$AL$2:$AL$492,0)),"") | D51: =IFERROR(INDEX('Output Utente'!$C$2:$C$492,MATCH("C|Nella Media|10",'Output Utente'!$AL$2:$AL$492,0)),"") | E51: =IFERROR(INDEX('Output Utente'!$C$2:$C$492,MATCH("A|Nella Media|10",'Output Utente'!$AL$2:$AL$492,0)),"") -> Ratkov
A52: 11 | B52: =IFERROR(INDEX('Output Utente'!$C$2:$C$492,MATCH("P|Nella Media|11",'Output Utente'!$AL$2:$AL$492,0)),"") | C52: =IFERROR(INDEX('Output Utente'!$C$2:$C$492,MATCH("D|Nella Media|11",'Output Utente'!$AL$2:$AL$492,0)),"") | D52: =IFERROR(INDEX('Output Utente'!$C$2:$C$492,MATCH("C|Nella Media|11",'Output Utente'!$AL$2:$AL$492,0)),"") -> Fazzini | E52: =IFERROR(INDEX('Output Utente'!$C$2:$C$492,MATCH("A|Nella Media|11",'Output Utente'!$AL$2:$AL$492,0)),"")
A53: 12 | B53: =IFERROR(INDEX('Output Utente'!$C$2:$C$492,MATCH("P|Nella Media|12",'Output Utente'!$AL$2:$AL$492,0)),"") | C53: =IFERROR(INDEX('Output Utente'!$C$2:$C$492,MATCH("D|Nella Media|12",'Output Utente'!$AL$2:$AL$492,0)),"") -> Obert | D53: =IFERROR(INDEX('Output Utente'!$C$2:$C$492,MATCH("C|Nella Media|12",'Output Utente'!$AL$2:$AL$492,0)),"") | E53: =IFERROR(INDEX('Output Utente'!$C$2:$C$492,MATCH("A|Nella Media|12",'Output Utente'!$AL$2:$AL$492,0)),"") -> Dia
A54: 13 | B54: =IFERROR(INDEX('Output Utente'!$C$2:$C$492,MATCH("P|Nella Media|13",'Output Utente'!$AL$2:$AL$492,0)),"") | C54: =IFERROR(INDEX('Output Utente'!$C$2:$C$492,MATCH("D|Nella Media|13",'Output Utente'!$AL$2:$AL$492,0)),"") | D54: =IFERROR(INDEX('Output Utente'!$C$2:$C$492,MATCH("C|Nella Media|13",'Output Utente'!$AL$2:$AL$492,0)),"") | E54: =IFERROR(INDEX('Output Utente'!$C$2:$C$492,MATCH("A|Nella Media|13",'Output Utente'!$AL$2:$AL$492,0)),"") -> Ghedjemis
A55: 14 | B55: =IFERROR(INDEX('Output Utente'!$C$2:$C$492,MATCH("P|Nella Media|14",'Output Utente'!$AL$2:$AL$492,0)),"") | C55: =IFERROR(INDEX('Output Utente'!$C$2:$C$492,MATCH("D|Nella Media|14",'Output Utente'!$AL$2:$AL$492,0)),"") -> Marcandalli | D55: =IFERROR(INDEX('Output Utente'!$C$2:$C$492,MATCH("C|Nella Media|14",'Output Utente'!$AL$2:$AL$492,0)),"") | E55: =IFERROR(INDEX('Output Utente'!$C$2:$C$492,MATCH("A|Nella Media|14",'Output Utente'!$AL$2:$AL$492,0)),"") -> Yeboah J.
A56: 15 | B56: =IFERROR(INDEX('Output Utente'!$C$2:$C$492,MATCH("P|Nella Media|15",'Output Utente'!$AL$2:$AL$492,0)),"") | C56: =IFERROR(INDEX('Output Utente'!$C$2:$C$492,MATCH("D|Nella Media|15",'Output Utente'!$AL$2:$AL$492,0)),"") | D56: =IFERROR(INDEX('Output Utente'!$C$2:$C$492,MATCH("C|Nella Media|15",'Output Utente'!$AL$2:$AL$492,0)),"") | E56: =IFERROR(INDEX('Output Utente'!$C$2:$C$492,MATCH("A|Nella Media|15",'Output Utente'!$AL$2:$AL$492,0)),"") -> Geubbels
A58: SCOMMESSE
B59: Portieri | C59: Difensori | D59: Centrocampisti | E59: Attaccanti
A60: 1 | B60: =IFERROR(INDEX('Output Utente'!$C$2:$C$492,MATCH("P|Scommessa/Riserva|1",'Output Utente'!$AL$2:$AL$492,0)),"") | C60: =IFERROR(INDEX('Output Utente'!$C$2:$C$492,MATCH("D|Scommessa/Riserva|1",'Output Utente'!$AL$2:$AL$492,0)),"") -> Zappa | D60: =IFERROR(INDEX('Output Utente'!$C$2:$C$492,MATCH("C|Scommessa/Riserva|1",'Output Utente'!$AL$2:$AL$492,0)),"") -> Amondarain | E60: =IFERROR(INDEX('Output Utente'!$C$2:$C$492,MATCH("A|Scommessa/Riserva|1",'Output Utente'!$AL$2:$AL$492,0)),"") -> Noslin
A61: 2 | B61: =IFERROR(INDEX('Output Utente'!$C$2:$C$492,MATCH("P|Scommessa/Riserva|2",'Output Utente'!$AL$2:$AL$492,0)),"") | C61: =IFERROR(INDEX('Output Utente'!$C$2:$C$492,MATCH("D|Scommessa/Riserva|2",'Output Utente'!$AL$2:$AL$492,0)),"") | D61: =IFERROR(INDEX('Output Utente'!$C$2:$C$492,MATCH("C|Scommessa/Riserva|2",'Output Utente'!$AL$2:$AL$492,0)),"") | E61: =IFERROR(INDEX('Output Utente'!$C$2:$C$492,MATCH("A|Scommessa/Riserva|2",'Output Utente'!$AL$2:$AL$492,0)),"") -> Sulemana K.
A62: 3 | B62: =IFERROR(INDEX('Output Utente'!$C$2:$C$492,MATCH("P|Scommessa/Riserva|3",'Output Utente'!$AL$2:$AL$492,0)),"") | C62: =IFERROR(INDEX('Output Utente'!$C$2:$C$492,MATCH("D|Scommessa/Riserva|3",'Output Utente'!$AL$2:$AL$492,0)),"") | D62: =IFERROR(INDEX('Output Utente'!$C$2:$C$492,MATCH("C|Scommessa/Riserva|3",'Output Utente'!$AL$2:$AL$492,0)),"") | E62: =IFERROR(INDEX('Output Utente'!$C$2:$C$492,MATCH("A|Scommessa/Riserva|3",'Output Utente'!$AL$2:$AL$492,0)),"") -> Kvernadze
A63: 4 | B63: =IFERROR(INDEX('Output Utente'!$C$2:$C$492,MATCH("P|Scommessa/Riserva|4",'Output Utente'!$AL$2:$AL$492,0)),"") | C63: =IFERROR(INDEX('Output Utente'!$C$2:$C$492,MATCH("D|Scommessa/Riserva|4",'Output Utente'!$AL$2:$AL$492,0)),"") | D63: =IFERROR(INDEX('Output Utente'!$C$2:$C$492,MATCH("C|Scommessa/Riserva|4",'Output Utente'!$AL$2:$AL$492,0)),"") | E63: =IFERROR(INDEX('Output Utente'!$C$2:$C$492,MATCH("A|Scommessa/Riserva|4",'Output Utente'!$AL$2:$AL$492,0)),"") -> Gimenez
A64: 5 | B64: =IFERROR(INDEX('Output Utente'!$C$2:$C$492,MATCH("P|Scommessa/Riserva|5",'Output Utente'!$AL$2:$AL$492,0)),"") | C64: =IFERROR(INDEX('Output Utente'!$C$2:$C$492,MATCH("D|Scommessa/Riserva|5",'Output Utente'!$AL$2:$AL$492,0)),"") | D64: =IFERROR(INDEX('Output Utente'!$C$2:$C$492,MATCH("C|Scommessa/Riserva|5",'Output Utente'!$AL$2:$AL$492,0)),"") | E64: =IFERROR(INDEX('Output Utente'!$C$2:$C$492,MATCH("A|Scommessa/Riserva|5",'Output Utente'!$AL$2:$AL$492,0)),"")
A65: 6 | B65: =IFERROR(INDEX('Output Utente'!$C$2:$C$492,MATCH("P|Scommessa/Riserva|6",'Output Utente'!$AL$2:$AL$492,0)),"") | C65: =IFERROR(INDEX('Output Utente'!$C$2:$C$492,MATCH("D|Scommessa/Riserva|6",'Output Utente'!$AL$2:$AL$492,0)),"") | D65: =IFERROR(INDEX('Output Utente'!$C$2:$C$492,MATCH("C|Scommessa/Riserva|6",'Output Utente'!$AL$2:$AL$492,0)),"") | E65: =IFERROR(INDEX('Output Utente'!$C$2:$C$492,MATCH("A|Scommessa/Riserva|6",'Output Utente'!$AL$2:$AL$492,0)),"")
A66: 7 | B66: =IFERROR(INDEX('Output Utente'!$C$2:$C$492,MATCH("P|Scommessa/Riserva|7",'Output Utente'!$AL$2:$AL$492,0)),"") | C66: =IFERROR(INDEX('Output Utente'!$C$2:$C$492,MATCH("D|Scommessa/Riserva|7",'Output Utente'!$AL$2:$AL$492,0)),"") -> Pongracic | D66: =IFERROR(INDEX('Output Utente'!$C$2:$C$492,MATCH("C|Scommessa/Riserva|7",'Output Utente'!$AL$2:$AL$492,0)),"") | E66: =IFERROR(INDEX('Output Utente'!$C$2:$C$492,MATCH("A|Scommessa/Riserva|7",'Output Utente'!$AL$2:$AL$492,0)),"") -> Frigan
A67: 8 | B67: =IFERROR(INDEX('Output Utente'!$C$2:$C$492,MATCH("P|Scommessa/Riserva|8",'Output Utente'!$AL$2:$AL$492,0)),"") | C67: =IFERROR(INDEX('Output Utente'!$C$2:$C$492,MATCH("D|Scommessa/Riserva|8",'Output Utente'!$AL$2:$AL$492,0)),"") | D67: =IFERROR(INDEX('Output Utente'!$C$2:$C$492,MATCH("C|Scommessa/Riserva|8",'Output Utente'!$AL$2:$AL$492,0)),"") | E67: =IFERROR(INDEX('Output Utente'!$C$2:$C$492,MATCH("A|Scommessa/Riserva|8",'Output Utente'!$AL$2:$AL$492,0)),"") -> Elphege
A68: 9 | B68: =IFERROR(INDEX('Output Utente'!$C$2:$C$492,MATCH("P|Scommessa/Riserva|9",'Output Utente'!$AL$2:$AL$492,0)),"") | C68: =IFERROR(INDEX('Output Utente'!$C$2:$C$492,MATCH("D|Scommessa/Riserva|9",'Output Utente'!$AL$2:$AL$492,0)),"") | D68: =IFERROR(INDEX('Output Utente'!$C$2:$C$492,MATCH("C|Scommessa/Riserva|9",'Output Utente'!$AL$2:$AL$492,0)),"") | E68: =IFERROR(INDEX('Output Utente'!$C$2:$C$492,MATCH("A|Scommessa/Riserva|9",'Output Utente'!$AL$2:$AL$492,0)),"") -> Morata
A69: 10 | B69: =IFERROR(INDEX('Output Utente'!$C$2:$C$492,MATCH("P|Scommessa/Riserva|10",'Output Utente'!$AL$2:$AL$492,0)),"") | C69: =IFERROR(INDEX('Output Utente'!$C$2:$C$492,MATCH("D|Scommessa/Riserva|10",'Output Utente'!$AL$2:$AL$492,0)),"") | D69: =IFERROR(INDEX('Output Utente'!$C$2:$C$492,MATCH("C|Scommessa/Riserva|10",'Output Utente'!$AL$2:$AL$492,0)),"") | E69: =IFERROR(INDEX('Output Utente'!$C$2:$C$492,MATCH("A|Scommessa/Riserva|10",'Output Utente'!$AL$2:$AL$492,0)),"")
A70: 11 | B70: =IFERROR(INDEX('Output Utente'!$C$2:$C$492,MATCH("P|Scommessa/Riserva|11",'Output Utente'!$AL$2:$AL$492,0)),"") | C70: =IFERROR(INDEX('Output Utente'!$C$2:$C$492,MATCH("D|Scommessa/Riserva|11",'Output Utente'!$AL$2:$AL$492,0)),"") | D70: =IFERROR(INDEX('Output Utente'!$C$2:$C$492,MATCH("C|Scommessa/Riserva|11",'Output Utente'!$AL$2:$AL$492,0)),"") -> Chukwueze | E70: =IFERROR(INDEX('Output Utente'!$C$2:$C$492,MATCH("A|Scommessa/Riserva|11",'Output Utente'!$AL$2:$AL$492,0)),"")
A71: 12 | B71: =IFERROR(INDEX('Output Utente'!$C$2:$C$492,MATCH("P|Scommessa/Riserva|12",'Output Utente'!$AL$2:$AL$492,0)),"") | C71: =IFERROR(INDEX('Output Utente'!$C$2:$C$492,MATCH("D|Scommessa/Riserva|12",'Output Utente'!$AL$2:$AL$492,0)),"") | D71: =IFERROR(INDEX('Output Utente'!$C$2:$C$492,MATCH("C|Scommessa/Riserva|12",'Output Utente'!$AL$2:$AL$492,0)),"") | E71: =IFERROR(INDEX('Output Utente'!$C$2:$C$492,MATCH("A|Scommessa/Riserva|12",'Output Utente'!$AL$2:$AL$492,0)),"")
A72: 13 | B72: =IFERROR(INDEX('Output Utente'!$C$2:$C$492,MATCH("P|Scommessa/Riserva|13",'Output Utente'!$AL$2:$AL$492,0)),"") | C72: =IFERROR(INDEX('Output Utente'!$C$2:$C$492,MATCH("D|Scommessa/Riserva|13",'Output Utente'!$AL$2:$AL$492,0)),"") -> Kossounou | D72: =IFERROR(INDEX('Output Utente'!$C$2:$C$492,MATCH("C|Scommessa/Riserva|13",'Output Utente'!$AL$2:$AL$492,0)),"") | E72: =IFERROR(INDEX('Output Utente'!$C$2:$C$492,MATCH("A|Scommessa/Riserva|13",'Output Utente'!$AL$2:$AL$492,0)),"")
A73: 14 | B73: =IFERROR(INDEX('Output Utente'!$C$2:$C$492,MATCH("P|Scommessa/Riserva|14",'Output Utente'!$AL$2:$AL$492,0)),"") | C73: =IFERROR(INDEX('Output Utente'!$C$2:$C$492,MATCH("D|Scommessa/Riserva|14",'Output Utente'!$AL$2:$AL$492,0)),"") | D73: =IFERROR(INDEX('Output Utente'!$C$2:$C$492,MATCH("C|Scommessa/Riserva|14",'Output Utente'!$AL$2:$AL$492,0)),"") | E73: =IFERROR(INDEX('Output Utente'!$C$2:$C$492,MATCH("A|Scommessa/Riserva|14",'Output Utente'!$AL$2:$AL$492,0)),"") -> Borrelli
A74: 15 | B74: =IFERROR(INDEX('Output Utente'!$C$2:$C$492,MATCH("P|Scommessa/Riserva|15",'Output Utente'!$AL$2:$AL$492,0)),"") | C74: =IFERROR(INDEX('Output Utente'!$C$2:$C$492,MATCH("D|Scommessa/Riserva|15",'Output Utente'!$AL$2:$AL$492,0)),"") | D74: =IFERROR(INDEX('Output Utente'!$C$2:$C$492,MATCH("C|Scommessa/Riserva|15",'Output Utente'!$AL$2:$AL$492,0)),"") | E74: =IFERROR(INDEX('Output Utente'!$C$2:$C$492,MATCH("A|Scommessa/Riserva|15",'Output Utente'!$AL$2:$AL$492,0)),"")

Sheet Giocatori Liberi
A1: GIOCATORI ANCORA DISPONIBILI (non ancora chiamati all'asta)
A3: # | B3: Id | C3: R | D3: Nome | E3: Squadra Serie A | F3: Qt.A | G3: FVM/1000 | H3: Fascia Aspettativa | I3: Offerta Max | J3: Valutazione Min | K3: Valutazione Max | L3: Whichlist | M3: Sostenibilità | N3: Pressione Ruolo
A4: 1 | B4: =IFERROR(INDEX('Output Utente'!$A$2:$A$492,MATCH(1,'Output Utente'!$Q$2:$Q$492,0)),"") -> 2764 | C4: =IFERROR(INDEX('Output Utente'!$B$2:$B$492,MATCH(1,'Output Utente'!$Q$2:$Q$492,0)),"") -> A | D4: =IFERROR(INDEX('Output Utente'!$C$2:$C$492,MATCH(1,'Output Utente'!$Q$2:$Q$492,0)),"") -> Martinez L. | E4: =IFERROR(INDEX('Input Giocatori 2026_27'!$D$3:$D$493,MATCH($B4,'Input Giocatori 2026_27'!$A$3:$A$493,0)),"") -> Inter | F4: =IFERROR(INDEX('Output Utente'!$N$2:$N$492,MATCH(1,'Output Utente'!$Q$2:$Q$492,0)),"") -> 35 | G4: =IFERROR(INDEX('Output Utente'!$O$2:$O$492,MATCH(1,'Output Utente'!$Q$2:$Q$492,0)),"") -> 370 | H4: =IFERROR(INDEX('Output Utente'!$P$2:$P$492,MATCH(1,'Output Utente'!$Q$2:$Q$492,0)),"") -> Top | I4: =IFERROR(INDEX('Output Utente'!$F$2:$F$492,MATCH(1,'Output Utente'!$Q$2:$Q$492,0)),"") -> 397 | J4: =IFERROR(INDEX('Output Utente'!$G$2:$G$492,MATCH(1,'Output Utente'!$Q$2:$Q$492,0)),"") -> 248 | K4: =IFERROR(INDEX('Output Utente'!$H$2:$H$492,MATCH(1,'Output Utente'!$Q$2:$Q$492,0)),"") -> 461 | L4: =IFERROR(INDEX('Output Utente'!$E$2:$E$492,MATCH(1,'Output Utente'!$Q$2:$Q$492,0)),"") -> NO | M4: =IFERROR(INDEX('Output Utente'!$U$2:$U$492,MATCH(1,'Output Utente'!$Q$2:$Q$492,0)),"") -> Rischio Alto | N4: =IFERROR(INDEX('Output Utente'!$AE$2:$AE$492,MATCH(1,'Output Utente'!$Q$2:$Q$492,0)),"") -> 🔴 Non aspettare
A5: 2 | B5: =IFERROR(INDEX('Output Utente'!$A$2:$A$492,MATCH(2,'Output Utente'!$Q$2:$Q$492,0)),"") -> 5585 | C5: =IFERROR(INDEX('Output Utente'!$B$2:$B$492,MATCH(2,'Output Utente'!$Q$2:$Q$492,0)),"") -> A | D5: =IFERROR(INDEX('Output Utente'!$C$2:$C$492,MATCH(2,'Output Utente'!$Q$2:$Q$492,0)),"") -> Malen | E5: =IFERROR(INDEX('Input Giocatori 2026_27'!$D$3:$D$493,MATCH($B5,'Input Giocatori 2026_27'!$A$3:$A$493,0)),"") -> Roma | F5: =IFERROR(INDEX('Output Utente'!$N$2:$N$492,MATCH(2,'Output Utente'!$Q$2:$Q$492,0)),"") -> 34 | G5: =IFERROR(INDEX('Output Utente'!$O$2:$O$492,MATCH(2,'Output Utente'!$Q$2:$Q$492,0)),"") -> 365 | H5: =IFERROR(INDEX('Output Utente'!$P$2:$P$492,MATCH(2,'Output Utente'!$Q$2:$Q$492,0)),"") -> Top | I5: =IFERROR(INDEX('Output Utente'!$F$2:$F$492,MATCH(2,'Output Utente'!$Q$2:$Q$492,0)),"") -> 400 | J5: =IFERROR(INDEX('Output Utente'!$G$2:$G$492,MATCH(2,'Output Utente'!$Q$2:$Q$492,0)),"") -> 250 | K5: =IFERROR(INDEX('Output Utente'!$H$2:$H$492,MATCH(2,'Output Utente'!$Q$2:$Q$492,0)),"") -> 464 | L5: =IFERROR(INDEX('Output Utente'!$E$2:$E$492,MATCH(2,'Output Utente'!$Q$2:$Q$492,0)),"") -> NO | M5: =IFERROR(INDEX('Output Utente'!$U$2:$U$492,MATCH(2,'Output Utente'!$Q$2:$Q$492,0)),"") -> Rischio Alto | N5: =IFERROR(INDEX('Output Utente'!$AE$2:$AE$492,MATCH(2,'Output Utente'!$Q$2:$Q$492,0)),"") -> 🔴 Non aspettare
A6: 3 | B6: =IFERROR(INDEX('Output Utente'!$A$2:$A$492,MATCH(3,'Output Utente'!$Q$2:$Q$492,0)),"") -> 4871 | C6: =IFERROR(INDEX('Output Utente'!$B$2:$B$492,MATCH(3,'Output Utente'!$Q$2:$Q$492,0)),"") -> A | D6: =IFERROR(INDEX('Output Utente'!$C$2:$C$492,MATCH(3,'Output Utente'!$Q$2:$Q$492,0)),"") -> Thuram | E6: =IFERROR(INDEX('Input Giocatori 2026_27'!$D$3:$D$493,MATCH($B6,'Input Giocatori 2026_27'!$A$3:$A$493,0)),"") -> Inter | F6: =IFERROR(INDEX('Output Utente'!$N$2:$N$492,MATCH(3,'Output Utente'!$Q$2:$Q$492,0)),"") -> 29 | G6: =IFERROR(INDEX('Output Utente'!$O$2:$O$492,MATCH(3,'Output Utente'!$Q$2:$Q$492,0)),"") -> 280 | H6: =IFERROR(INDEX('Output Utente'!$P$2:$P$492,MATCH(3,'Output Utente'!$Q$2:$Q$492,0)),"") -> Top | I6: =IFERROR(INDEX('Output Utente'!$F$2:$F$492,MATCH(3,'Output Utente'!$Q$2:$Q$492,0)),"") -> 298 | J6: =IFERROR(INDEX('Output Utente'!$G$2:$G$492,MATCH(3,'Output Utente'!$Q$2:$Q$492,0)),"") -> 186 | K6: =IFERROR(INDEX('Output Utente'!$H$2:$H$492,MATCH(3,'Output Utente'!$Q$2:$Q$492,0)),"") -> 346 | L6: =IFERROR(INDEX('Output Utente'!$E$2:$E$492,MATCH(3,'Output Utente'!$Q$2:$Q$492,0)),"") -> NO | M6: =IFERROR(INDEX('Output Utente'!$U$2:$U$492,MATCH(3,'Output Utente'!$Q$2:$Q$492,0)),"") -> Rischio Alto | N6: =IFERROR(INDEX('Output Utente'!$AE$2:$AE$492,MATCH(3,'Output Utente'!$Q$2:$Q$492,0)),"") -> 🔴 Non aspettare
A7: 4 | B7: =IFERROR(INDEX('Output Utente'!$A$2:$A$492,MATCH(4,'Output Utente'!$Q$2:$Q$492,0)),"") -> 6052 | C7: =IFERROR(INDEX('Output Utente'!$B$2:$B$492,MATCH(4,'Output Utente'!$Q$2:$Q$492,0)),"") -> A | D7: =IFERROR(INDEX('Output Utente'!$C$2:$C$492,MATCH(4,'Output Utente'!$Q$2:$Q$492,0)),"") -> Hojlund | E7: =IFERROR(INDEX('Input Giocatori 2026_27'!$D$3:$D$493,MATCH($B7,'Input Giocatori 2026_27'!$A$3:$A$493,0)),"") -> Napoli | F7: =IFERROR(INDEX('Output Utente'!$N$2:$N$492,MATCH(4,'Output Utente'!$Q$2:$Q$492,0)),"") -> 28 | G7: =IFERROR(INDEX('Output Utente'!$O$2:$O$492,MATCH(4,'Output Utente'!$Q$2:$Q$492,0)),"") -> 271 | H7: =IFERROR(INDEX('Output Utente'!$P$2:$P$492,MATCH(4,'Output Utente'!$Q$2:$Q$492,0)),"") -> Top | I7: =IFERROR(INDEX('Output Utente'!$F$2:$F$492,MATCH(4,'Output Utente'!$Q$2:$Q$492,0)),"") -> 284 | J7: =IFERROR(INDEX('Output Utente'!$G$2:$G$492,MATCH(4,'Output Utente'!$Q$2:$Q$492,0)),"") -> 178 | K7: =IFERROR(INDEX('Output Utente'!$H$2:$H$492,MATCH(4,'Output Utente'!$Q$2:$Q$492,0)),"") -> 330 | L7: =IFERROR(INDEX('Output Utente'!$E$2:$E$492,MATCH(4,'Output Utente'!$Q$2:$Q$492,0)),"") -> NO | M7: =IFERROR(INDEX('Output Utente'!$U$2:$U$492,MATCH(4,'Output Utente'!$Q$2:$Q$492,0)),"") -> Rischio Alto | N7: =IFERROR(INDEX('Output Utente'!$AE$2:$AE$492,MATCH(4,'Output Utente'!$Q$2:$Q$492,0)),"") -> 🔴 Non aspettare
A8: 5 | B8: =IFERROR(INDEX('Output Utente'!$A$2:$A$492,MATCH(5,'Output Utente'!$Q$2:$Q$492,0)),"") -> 254 | C8: =IFERROR(INDEX('Output Utente'!$B$2:$B$492,MATCH(5,'Output Utente'!$Q$2:$Q$492,0)),"") -> D | D8: =IFERROR(INDEX('Output Utente'!$C$2:$C$492,MATCH(5,'Output Utente'!$Q$2:$Q$492,0)),"") -> Dimarco | E8: =IFERROR(INDEX('Input Giocatori 2026_27'!$D$3:$D$493,MATCH($B8,'Input Giocatori 2026_27'!$A$3:$A$493,0)),"") -> Inter | F8: =IFERROR(INDEX('Output Utente'!$N$2:$N$492,MATCH(5,'Output Utente'!$Q$2:$Q$492,0)),"") -> 32 | G8: =IFERROR(INDEX('Output Utente'!$O$2:$O$492,MATCH(5,'Output Utente'!$Q$2:$Q$492,0)),"") -> 265 | H8: =IFERROR(INDEX('Output Utente'!$P$2:$P$492,MATCH(5,'Output Utente'!$Q$2:$Q$492,0)),"") -> Top | I8: =IFERROR(INDEX('Output Utente'!$F$2:$F$492,MATCH(5,'Output Utente'!$Q$2:$Q$492,0)),"") -> 190 | J8: =IFERROR(INDEX('Output Utente'!$G$2:$G$492,MATCH(5,'Output Utente'!$Q$2:$Q$492,0)),"") -> 141 | K8: =IFERROR(INDEX('Output Utente'!$H$2:$H$492,MATCH(5,'Output Utente'!$Q$2:$Q$492,0)),"") -> 211 | L8: =IFERROR(INDEX('Output Utente'!$E$2:$E$492,MATCH(5,'Output Utente'!$Q$2:$Q$492,0)),"") -> NO | M8: =IFERROR(INDEX('Output Utente'!$U$2:$U$492,MATCH(5,'Output Utente'!$Q$2:$Q$492,0)),"") -> Rischio Alto | N8: =IFERROR(INDEX('Output Utente'!$AE$2:$AE$492,MATCH(5,'Output Utente'!$Q$2:$Q$492,0)),"") -> 🔴 Non aspettare
A9: 6 | B9: =IFERROR(INDEX('Output Utente'!$A$2:$A$492,MATCH(6,'Output Utente'!$Q$2:$Q$492,0)),"") -> 6875 | C9: =IFERROR(INDEX('Output Utente'!$B$2:$B$492,MATCH(6,'Output Utente'!$Q$2:$Q$492,0)),"") -> C | D9: =IFERROR(INDEX('Output Utente'!$C$2:$C$492,MATCH(6,'Output Utente'!$Q$2:$Q$492,0)),"") -> Paz N. | E9: =IFERROR(INDEX('Input Giocatori 2026_27'!$D$3:$D$493,MATCH($B9,'Input Giocatori 2026_27'!$A$3:$A$493,0)),"") -> Como | F9: =IFERROR(INDEX('Output Utente'!$N$2:$N$492,MATCH(6,'Output Utente'!$Q$2:$Q$492,0)),"") -> 30 | G9: =IFERROR(INDEX('Output Utente'!$O$2:$O$492,MATCH(6,'Output Utente'!$Q$2:$Q$492,0)),"") -> 250 | H9: =IFERROR(INDEX('Output Utente'!$P$2:$P$492,MATCH(6,'Output Utente'!$Q$2:$Q$492,0)),"") -> Top | I9: =IFERROR(INDEX('Output Utente'!$F$2:$F$492,MATCH(6,'Output Utente'!$Q$2:$Q$492,0)),"") -> 171 | J9: =IFERROR(INDEX('Output Utente'!$G$2:$G$492,MATCH(6,'Output Utente'!$Q$2:$Q$492,0)),"") -> 116 | K9: =IFERROR(INDEX('Output Utente'!$H$2:$H$492,MATCH(6,'Output Utente'!$Q$2:$Q$492,0)),"") -> 194 | L9: =IFERROR(INDEX('Output Utente'!$E$2:$E$492,MATCH(6,'Output Utente'!$Q$2:$Q$492,0)),"") -> NO | M9: =IFERROR(INDEX('Output Utente'!$U$2:$U$492,MATCH(6,'Output Utente'!$Q$2:$Q$492,0)),"") -> Rischio Alto | N9: =IFERROR(INDEX('Output Utente'!$AE$2:$AE$492,MATCH(6,'Output Utente'!$Q$2:$Q$492,0)),"") -> 🔴 Non aspettare
A10: 7 | B10: =IFERROR(INDEX('Output Utente'!$A$2:$A$492,MATCH(7,'Output Utente'!$Q$2:$Q$492,0)),"") -> 4777 | C10: =IFERROR(INDEX('Output Utente'!$B$2:$B$492,MATCH(7,'Output Utente'!$Q$2:$Q$492,0)),"") -> C | D10: =IFERROR(INDEX('Output Utente'!$C$2:$C$492,MATCH(7,'Output Utente'!$Q$2:$Q$492,0)),"") -> McTominay | E10: =IFERROR(INDEX('Input Giocatori 2026_27'!$D$3:$D$493,MATCH($B10,'Input Giocatori 2026_27'!$A$3:$A$493,0)),"") -> Napoli | F10: =IFERROR(INDEX('Output Utente'!$N$2:$N$492,MATCH(7,'Output Utente'!$Q$2:$Q$492,0)),"") -> 28 | G10: =IFERROR(INDEX('Output Utente'!$O$2:$O$492,MATCH(7,'Output Utente'!$Q$2:$Q$492,0)),"") -> 240 | H10: =IFERROR(INDEX('Output Utente'!$P$2:$P$492,MATCH(7,'Output Utente'!$Q$2:$Q$492,0)),"") -> Top | I10: =IFERROR(INDEX('Output Utente'!$F$2:$F$492,MATCH(7,'Output Utente'!$Q$2:$Q$492,0)),"") -> 164 | J10: =IFERROR(INDEX('Output Utente'!$G$2:$G$492,MATCH(7,'Output Utente'!$Q$2:$Q$492,0)),"") -> 112 | K10: =IFERROR(INDEX('Output Utente'!$H$2:$H$492,MATCH(7,'Output Utente'!$Q$2:$Q$492,0)),"") -> 186 | L10: =IFERROR(INDEX('Output Utente'!$E$2:$E$492,MATCH(7,'Output Utente'!$Q$2:$Q$492,0)),"") -> NO | M10: =IFERROR(INDEX('Output Utente'!$U$2:$U$492,MATCH(7,'Output Utente'!$Q$2:$Q$492,0)),"") -> Rischio Alto | N10: =IFERROR(INDEX('Output Utente'!$AE$2:$AE$492,MATCH(7,'Output Utente'!$Q$2:$Q$492,0)),"") -> 🔴 Non aspettare
A11: 8 | B11: =IFERROR(INDEX('Output Utente'!$A$2:$A$492,MATCH(8,'Output Utente'!$Q$2:$Q$492,0)),"") -> 6397 | C11: =IFERROR(INDEX('Output Utente'!$B$2:$B$492,MATCH(8,'Output Utente'!$Q$2:$Q$492,0)),"") -> A | D11: =IFERROR(INDEX('Output Utente'!$C$2:$C$492,MATCH(8,'Output Utente'!$Q$2:$Q$492,0)),"") -> Ramos G. | E11: =IFERROR(INDEX('Input Giocatori 2026_27'!$D$3:$D$493,MATCH($B11,'Input Giocatori 2026_27'!$A$3:$A$493,0)),"") -> Milan | F11: =IFERROR(INDEX('Output Utente'!$N$2:$N$492,MATCH(8,'Output Utente'!$Q$2:$Q$492,0)),"") -> 27 | G11: =IFERROR(INDEX('Output Utente'!$O$2:$O$492,MATCH(8,'Output Utente'!$Q$2:$Q$492,0)),"") -> 240 | H11: =IFERROR(INDEX('Output Utente'!$P$2:$P$492,MATCH(8,'Output Utente'!$Q$2:$Q$492,0)),"") -> Top | I11: =IFERROR(INDEX('Output Utente'!$F$2:$F$492,MATCH(8,'Output Utente'!$Q$2:$Q$492,0)),"") -> 246 | J11: =IFERROR(INDEX('Output Utente'!$G$2:$G$492,MATCH(8,'Output Utente'!$Q$2:$Q$492,0)),"") -> 154 | K11: =IFERROR(INDEX('Output Utente'!$H$2:$H$492,MATCH(8,'Output Utente'!$Q$2:$Q$492,0)),"") -> 286 | L11: =IFERROR(INDEX('Output Utente'!$E$2:$E$492,MATCH(8,'Output Utente'!$Q$2:$Q$492,0)),"") -> NO | M11: =IFERROR(INDEX('Output Utente'!$U$2:$U$492,MATCH(8,'Output Utente'!$Q$2:$Q$492,0)),"") -> Rischio Alto | N11: =IFERROR(INDEX('Output Utente'!$AE$2:$AE$492,MATCH(8,'Output Utente'!$Q$2:$Q$492,0)),"") -> 🔴 Non aspettare
A12: 9 | B12: =IFERROR(INDEX('Output Utente'!$A$2:$A$492,MATCH(9,'Output Utente'!$Q$2:$Q$492,0)),"") -> 2194 | C12: =IFERROR(INDEX('Output Utente'!$B$2:$B$492,MATCH(9,'Output Utente'!$Q$2:$Q$492,0)),"") -> C | D12: =IFERROR(INDEX('Output Utente'!$C$2:$C$492,MATCH(9,'Output Utente'!$Q$2:$Q$492,0)),"") -> Calhanoglu | E12: =IFERROR(INDEX('Input Giocatori 2026_27'!$D$3:$D$493,MATCH($B12,'Input Giocatori 2026_27'!$A$3:$A$493,0)),"") -> Inter | F12: =IFERROR(INDEX('Output Utente'!$N$2:$N$492,MATCH(9,'Output Utente'!$Q$2:$Q$492,0)),"") -> 27 | G12: =IFERROR(INDEX('Output Utente'!$O$2:$O$492,MATCH(9,'Output Utente'!$Q$2:$Q$492,0)),"") -> 230 | H12: =IFERROR(INDEX('Output Utente'!$P$2:$P$492,MATCH(9,'Output Utente'!$Q$2:$Q$492,0)),"") -> Top | I12: =IFERROR(INDEX('Output Utente'!$F$2:$F$492,MATCH(9,'Output Utente'!$Q$2:$Q$492,0)),"") -> 158 | J12: =IFERROR(INDEX('Output Utente'!$G$2:$G$492,MATCH(9,'Output Utente'!$Q$2:$Q$492,0)),"") -> 108 | K12: =IFERROR(INDEX('Output Utente'!$H$2:$H$492,MATCH(9,'Output Utente'!$Q$2:$Q$492,0)),"") -> 180 | L12: =IFERROR(INDEX('Output Utente'!$E$2:$E$492,MATCH(9,'Output Utente'!$Q$2:$Q$492,0)),"") -> NO | M12: =IFERROR(INDEX('Output Utente'!$U$2:$U$492,MATCH(9,'Output Utente'!$Q$2:$Q$492,0)),"") -> Rischio Alto | N12: =IFERROR(INDEX('Output Utente'!$AE$2:$AE$492,MATCH(9,'Output Utente'!$Q$2:$Q$492,0)),"") -> 🔴 Non aspettare
A13: 10 | B13: =IFERROR(INDEX('Output Utente'!$A$2:$A$492,MATCH(10,'Output Utente'!$Q$2:$Q$492,0)),"") -> 5951 | C13: =IFERROR(INDEX('Output Utente'!$B$2:$B$492,MATCH(10,'Output Utente'!$Q$2:$Q$492,0)),"") -> A | D13: =IFERROR(INDEX('Output Utente'!$C$2:$C$492,MATCH(10,'Output Utente'!$Q$2:$Q$492,0)),"") -> Kolo Muani | E13: =IFERROR(INDEX('Input Giocatori 2026_27'!$D$3:$D$493,MATCH($B13,'Input Giocatori 2026_27'!$A$3:$A$493,0)),"") -> Juventus | F13: =IFERROR(INDEX('Output Utente'!$N$2:$N$492,MATCH(10,'Output Utente'!$Q$2:$Q$492,0)),"") -> 26 | G13: =IFERROR(INDEX('Output Utente'!$O$2:$O$492,MATCH(10,'Output Utente'!$Q$2:$Q$492,0)),"") -> 225 | H13: =IFERROR(INDEX('Output Utente'!$P$2:$P$492,MATCH(10,'Output Utente'!$Q$2:$Q$492,0)),"") -> Top | I13: =IFERROR(INDEX('Output Utente'!$F$2:$F$492,MATCH(10,'Output Utente'!$Q$2:$Q$492,0)),"") -> 231 | J13: =IFERROR(INDEX('Output Utente'!$G$2:$G$492,MATCH(10,'Output Utente'!$Q$2:$Q$492,0)),"") -> 144 | K13: =IFERROR(INDEX('Output Utente'!$H$2:$H$492,MATCH(10,'Output Utente'!$Q$2:$Q$492,0)),"") -> 268 | L13: =IFERROR(INDEX('Output Utente'!$E$2:$E$492,MATCH(10,'Output Utente'!$Q$2:$Q$492,0)),"") -> NO | M13: =IFERROR(INDEX('Output Utente'!$U$2:$U$492,MATCH(10,'Output Utente'!$Q$2:$Q$492,0)),"") -> Rischio Alto | N13: =IFERROR(INDEX('Output Utente'!$AE$2:$AE$492,MATCH(10,'Output Utente'!$Q$2:$Q$492,0)),"") -> 🔴 Non aspettare
A14: 11 | B14: =IFERROR(INDEX('Output Utente'!$A$2:$A$492,MATCH(11,'Output Utente'!$Q$2:$Q$492,0)),"") -> 2097 | C14: =IFERROR(INDEX('Output Utente'!$B$2:$B$492,MATCH(11,'Output Utente'!$Q$2:$Q$492,0)),"") -> A | D14: =IFERROR(INDEX('Output Utente'!$C$2:$C$492,MATCH(11,'Output Utente'!$Q$2:$Q$492,0)),"") -> Kean | E14: =IFERROR(INDEX('Input Giocatori 2026_27'!$D$3:$D$493,MATCH($B14,'Input Giocatori 2026_27'!$A$3:$A$493,0)),"") -> Fiorentina | F14: =IFERROR(INDEX('Output Utente'!$N$2:$N$492,MATCH(11,'Output Utente'!$Q$2:$Q$492,0)),"") -> 25 | G14: =IFERROR(INDEX('Output Utente'!$O$2:$O$492,MATCH(11,'Output Utente'!$Q$2:$Q$492,0)),"") -> 212 | H14: =IFERROR(INDEX('Output Utente'!$P$2:$P$492,MATCH(11,'Output Utente'!$Q$2:$Q$492,0)),"") -> Top | I14: =IFERROR(INDEX('Output Utente'!$F$2:$F$492,MATCH(11,'Output Utente'!$Q$2:$Q$492,0)),"") -> 218 | J14: =IFERROR(INDEX('Output Utente'!$G$2:$G$492,MATCH(11,'Output Utente'!$Q$2:$Q$492,0)),"") -> 136 | K14: =IFERROR(INDEX('Output Utente'!$H$2:$H$492,MATCH(11,'Output Utente'!$Q$2:$Q$492,0)),"") -> 253 | L14: =IFERROR(INDEX('Output Utente'!$E$2:$E$492,MATCH(11,'Output Utente'!$Q$2:$Q$492,0)),"") -> NO | M14: =IFERROR(INDEX('Output Utente'!$U$2:$U$492,MATCH(11,'Output Utente'!$Q$2:$Q$492,0)),"") -> Rischio Alto | N14: =IFERROR(INDEX('Output Utente'!$AE$2:$AE$492,MATCH(11,'Output Utente'!$Q$2:$Q$492,0)),"") -> 🔴 Non aspettare
A15: 12 | B15: =IFERROR(INDEX('Output Utente'!$A$2:$A$492,MATCH(12,'Output Utente'!$Q$2:$Q$492,0)),"") -> 2167 | C15: =IFERROR(INDEX('Output Utente'!$B$2:$B$492,MATCH(12,'Output Utente'!$Q$2:$Q$492,0)),"") -> C | D15: =IFERROR(INDEX('Output Utente'!$C$2:$C$492,MATCH(12,'Output Utente'!$Q$2:$Q$492,0)),"") -> Orsolini | E15: =IFERROR(INDEX('Input Giocatori 2026_27'!$D$3:$D$493,MATCH($B15,'Input Giocatori 2026_27'!$A$3:$A$493,0)),"") -> Bologna | F15: =IFERROR(INDEX('Output Utente'!$N$2:$N$492,MATCH(12,'Output Utente'!$Q$2:$Q$492,0)),"") -> 26 | G15: =IFERROR(INDEX('Output Utente'!$O$2:$O$492,MATCH(12,'Output Utente'!$Q$2:$Q$492,0)),"") -> 200 | H15: =IFERROR(INDEX('Output Utente'!$P$2:$P$492,MATCH(12,'Output Utente'!$Q$2:$Q$492,0)),"") -> Top | I15: =IFERROR(INDEX('Output Utente'!$F$2:$F$492,MATCH(12,'Output Utente'!$Q$2:$Q$492,0)),"") -> 135 | J15: =IFERROR(INDEX('Output Utente'!$G$2:$G$492,MATCH(12,'Output Utente'!$Q$2:$Q$492,0)),"") -> 92 | K15: =IFERROR(INDEX('Output Utente'!$H$2:$H$492,MATCH(12,'Output Utente'!$Q$2:$Q$492,0)),"") -> 153 | L15: =IFERROR(INDEX('Output Utente'!$E$2:$E$492,MATCH(12,'Output Utente'!$Q$2:$Q$492,0)),"") -> NO | M15: =IFERROR(INDEX('Output Utente'!$U$2:$U$492,MATCH(12,'Output Utente'!$Q$2:$Q$492,0)),"") -> Rischio Alto | N15: =IFERROR(INDEX('Output Utente'!$AE$2:$AE$492,MATCH(12,'Output Utente'!$Q$2:$Q$492,0)),"") -> 🔴 Non aspettare
A16: 13 | B16: =IFERROR(INDEX('Output Utente'!$A$2:$A$492,MATCH(13,'Output Utente'!$Q$2:$Q$492,0)),"") -> 6434 | C16: =IFERROR(INDEX('Output Utente'!$B$2:$B$492,MATCH(13,'Output Utente'!$Q$2:$Q$492,0)),"") -> A | D16: =IFERROR(INDEX('Output Utente'!$C$2:$C$492,MATCH(13,'Output Utente'!$Q$2:$Q$492,0)),"") -> Yildiz | E16: =IFERROR(INDEX('Input Giocatori 2026_27'!$D$3:$D$493,MATCH($B16,'Input Giocatori 2026_27'!$A$3:$A$493,0)),"") -> Juventus | F16: =IFERROR(INDEX('Output Utente'!$N$2:$N$492,MATCH(13,'Output Utente'!$Q$2:$Q$492,0)),"") -> 23 | G16: =IFERROR(INDEX('Output Utente'!$O$2:$O$492,MATCH(13,'Output Utente'!$Q$2:$Q$492,0)),"") -> 200 | H16: =IFERROR(INDEX('Output Utente'!$P$2:$P$492,MATCH(13,'Output Utente'!$Q$2:$Q$492,0)),"") -> Top | I16: =IFERROR(INDEX('Output Utente'!$F$2:$F$492,MATCH(13,'Output Utente'!$Q$2:$Q$492,0)),"") -> 209 | J16: =IFERROR(INDEX('Output Utente'!$G$2:$G$492,MATCH(13,'Output Utente'!$Q$2:$Q$492,0)),"") -> 131 | K16: =IFERROR(INDEX('Output Utente'!$H$2:$H$492,MATCH(13,'Output Utente'!$Q$2:$Q$492,0)),"") -> 243 | L16: =IFERROR(INDEX('Output Utente'!$E$2:$E$492,MATCH(13,'Output Utente'!$Q$2:$Q$492,0)),"") -> NO | M16: =IFERROR(INDEX('Output Utente'!$U$2:$U$492,MATCH(13,'Output Utente'!$Q$2:$Q$492,0)),"") -> Rischio Alto | N16: =IFERROR(INDEX('Output Utente'!$AE$2:$AE$492,MATCH(13,'Output Utente'!$Q$2:$Q$492,0)),"") -> 🔴 Non aspettare
A17: 14 | B17: =IFERROR(INDEX('Output Utente'!$A$2:$A$492,MATCH(14,'Output Utente'!$Q$2:$Q$492,0)),"") -> 2423 | C17: =IFERROR(INDEX('Output Utente'!$B$2:$B$492,MATCH(14,'Output Utente'!$Q$2:$Q$492,0)),"") -> C | D17: =IFERROR(INDEX('Output Utente'!$C$2:$C$492,MATCH(14,'Output Utente'!$Q$2:$Q$492,0)),"") -> Pulisic | E17: =IFERROR(INDEX('Input Giocatori 2026_27'!$D$3:$D$493,MATCH($B17,'Input Giocatori 2026_27'!$A$3:$A$493,0)),"") -> Milan | F17: =IFERROR(INDEX('Output Utente'!$N$2:$N$492,MATCH(14,'Output Utente'!$Q$2:$Q$492,0)),"") -> 25 | G17: =IFERROR(INDEX('Output Utente'!$O$2:$O$492,MATCH(14,'Output Utente'!$Q$2:$Q$492,0)),"") -> 180 | H17: =IFERROR(INDEX('Output Utente'!$P$2:$P$492,MATCH(14,'Output Utente'!$Q$2:$Q$492,0)),"") -> Top | I17: =IFERROR(INDEX('Output Utente'!$F$2:$F$492,MATCH(14,'Output Utente'!$Q$2:$Q$492,0)),"") -> 122 | J17: =IFERROR(INDEX('Output Utente'!$G$2:$G$492,MATCH(14,'Output Utente'!$Q$2:$Q$492,0)),"") -> 83 | K17: =IFERROR(INDEX('Output Utente'!$H$2:$H$492,MATCH(14,'Output Utente'!$Q$2:$Q$492,0)),"") -> 139 | L17: =IFERROR(INDEX('Output Utente'!$E$2:$E$492,MATCH(14,'Output Utente'!$Q$2:$Q$492,0)),"") -> NO | M17: =IFERROR(INDEX('Output Utente'!$U$2:$U$492,MATCH(14,'Output Utente'!$Q$2:$Q$492,0)),"") -> Rischio Alto | N17: =IFERROR(INDEX('Output Utente'!$AE$2:$AE$492,MATCH(14,'Output Utente'!$Q$2:$Q$492,0)),"") -> 🔴 Non aspettare
A18: 15 | B18: =IFERROR(INDEX('Output Utente'!$A$2:$A$492,MATCH(15,'Output Utente'!$Q$2:$Q$492,0)),"") -> 7017 | C18: =IFERROR(INDEX('Output Utente'!$B$2:$B$492,MATCH(15,'Output Utente'!$Q$2:$Q$492,0)),"") -> A | D18: =IFERROR(INDEX('Output Utente'!$C$2:$C$492,MATCH(15,'Output Utente'!$Q$2:$Q$492,0)),"") -> Douvikas | E18: =IFERROR(INDEX('Input Giocatori 2026_27'!$D$3:$D$493,MATCH($B18,'Input Giocatori 2026_27'!$A$3:$A$493,0)),"") -> Como | F18: =IFERROR(INDEX('Output Utente'!$N$2:$N$492,MATCH(15,'Output Utente'!$Q$2:$Q$492,0)),"") -> 20 | G18: =IFERROR(INDEX('Output Utente'!$O$2:$O$492,MATCH(15,'Output Utente'!$Q$2:$Q$492,0)),"") -> 157 | H18: =IFERROR(INDEX('Output Utente'!$P$2:$P$492,MATCH(15,'Output Utente'!$Q$2:$Q$492,0)),"") -> Top | I18: =IFERROR(INDEX('Output Utente'!$F$2:$F$492,MATCH(15,'Output Utente'!$Q$2:$Q$492,0)),"") -> 165 | J18: =IFERROR(INDEX('Output Utente'!$G$2:$G$492,MATCH(15,'Output Utente'!$Q$2:$Q$492,0)),"") -> 103 | K18: =IFERROR(INDEX('Output Utente'!$H$2:$H$492,MATCH(15,'Output Utente'!$Q$2:$Q$492,0)),"") -> 191 | L18: =IFERROR(INDEX('Output Utente'!$E$2:$E$492,MATCH(15,'Output Utente'!$Q$2:$Q$492,0)),"") -> NO | M18: =IFERROR(INDEX('Output Utente'!$U$2:$U$492,MATCH(15,'Output Utente'!$Q$2:$Q$492,0)),"") -> Rischio Alto | N18: =IFERROR(INDEX('Output Utente'!$AE$2:$AE$492,MATCH(15,'Output Utente'!$Q$2:$Q$492,0)),"") -> 🔴 Non aspettare
